Workbook

Sheet Start
A1: Opportunity Cost • Security
A3: A guided comparison of security work, protection and resources | Improved edition 6.2
A5: Start with one process, not the entire catalog. C001–C011 are examples; C012–C050 are prepared for live cases. Blue cells are inputs. Blank means unknown; a numeric 0 means confirmed zero.
A8: LIVE CASES | E8: APPROVED FORECASTS | I8: MEASURED / ELIGIBLE
A9: =COUNTIF(Cases!B7:B56,"Live") -> 0 | E9: =SUM(Checks!K7:K56) -> 0 | I9: =SUM(Checks!L7:L56) -> 0
A12: =IF(OR(COUNTBLANK('Review & Decision'!M7:M56)>0,COUNTBLANK(Checks!J7:J56)>0,COUNT(Checks!K7:K56)<50,COUNT(Checks!L7:L56)<50,COUNT(Checks!M7:M56)<50,COUNTIF(Checks!AG7:AG56,0)>0),"Integrity warning: missing readiness output or duplicate/missing key. Do not rely on planning totals.",IF(COUNTIF(Checks!AF7:AF56,"Missing measured evidence")>0,"Action required: one or more live Realized cases lack complete measurement evidence.","Readiness checks present. Examples, unchecked reviews and open decisions are excluded from live planning.")) -> Readiness checks present. Examples, unchecked reviews and open decisions are excluded from live planning.
A15: A clear path through one case
A16: =IFERROR(HYPERLINK("#'Case View'!A1","1 Explore / select a case"),"1 Explore / select a case") -> 1 Explore / select a case | E16: Read C001 as an example, then select C012 for your own case.
A18: =IFERROR(HYPERLINK("#'Cases'!C18","2 Define scope and proposal"),"2 Define scope and proposal") -> 2 Define scope and proposal | E18: Set type to Live. Name one process, owner, protection purpose and proposed change.
A20: =IFERROR(HYPERLINK("#'Current'!B18","3 Compare both profiles"),"3 Compare both profiles") -> 3 Compare both profiles | E20: Enter current and full proposed annual workload, cash costs, transition cost and sources.
A22: =IFERROR(HYPERLINK("#'Review & Decision'!B18","4 Review and approve"),"4 Review and approve") -> 4 Review and approve | E22: Record local evidence, clear the challenge review and approve an effective date.
A24: =IFERROR(HYPERLINK("#'Actuals'!B18","5 Measure; then plan"),"5 Measure; then plan") -> 5 Measure; then plan | E24: Add period-backed actual results when implemented. Reinvestment keeps cash separate.
A27: =IFERROR(HYPERLINK("#'Guide'!A1","Read the short user guide"),"Read the short user guide") -> Read the short user guide | E27: =IFERROR(HYPERLINK("#'Reinvestment'!A1","Open the live resource plan"),"Open the live resource plan") -> Open the live resource plan | I27: =IFERROR(HYPERLINK("#'Settings'!A1","Settings / workload helper"),"Settings / workload helper") -> Settings / workload helper
A29: Live portfolio — model potential is not an approved resource
A30: Annual change | E30: Modeled potential | G30: Approved forecast | I30: Measured | K30: Planning supply
A31: Business hours | E31: =SUMIFS(Checks!P7:P56,Checks!B7:B56,"Live",Checks!AH7:AH56,1) -> 0 | G31: =SUMIFS(Checks!P7:P56,Checks!K7:K56,1) -> 0 | I31: =SUMIFS(Checks!AL7:AL56,Checks!L7:L56,1) -> 0 | K31: =SUM(Checks!AA7:AA56) -> 0
A32: Specialist-team hours | E32: =SUMIFS(Checks!S7:S56,Checks!B7:B56,"Live",Checks!AH7:AH56,1) -> 0 | G32: =SUMIFS(Checks!S7:S56,Checks!K7:K56,1) -> 0 | I32: =SUMIFS(Checks!AM7:AM56,Checks!L7:L56,1) -> 0 | K32: =SUM(Checks!AB7:AB56) -> 0
A33: Recurring cash change | E33: =SUMIFS(Checks!V7:V56,Checks!B7:B56,"Live",Checks!AH7:AH56,1) -> 0 | G33: =SUMIFS(Checks!V7:V56,Checks!K7:K56,1) -> 0 | I33: =SUMIFS(Checks!AN7:AN56,Checks!L7:L56,1) -> 0 | K33: =SUM(Checks!AC7:AC56) -> 0
A34: Time-valued benefit • not cash | E34: =SUMIFS(Checks!Y7:Y56,Checks!B7:B56,"Live",Checks!AH7:AH56,1) -> 0 | G34: =SUMIFS(Checks!Y7:Y56,Checks!K7:K56,1) -> 0 | I34: =SUMIFS(Checks!AO7:AO56,Checks!L7:L56,1) -> 0 | K34: Not spendable
A35: One-time funding required | E35: =SUMIFS(Checks!Z7:Z56,Checks!B7:B56,"Live",Checks!AH7:AH56,1) -> 0 | G35: =SUMIFS(Checks!Z7:Z56,Checks!K7:K56,1) -> 0 | I35: Not future funding | K35: =SUM(Checks!AD7:AD56) -> 0
A38: Example portfolio — illustrative assumptions, excluded from the live plan
A39: Current annual cost | H39: =SUMIFS(Checks!W7:W56,Checks!B7:B56,"Example",Checks!AH7:AH56,1) -> 1423050
A40: Net business hours | H40: =SUMIFS(Checks!P7:P56,Checks!B7:B56,"Example",Checks!AH7:AH56,1) -> 14313.333
A41: Net specialist hours | H41: =SUMIFS(Checks!S7:S56,Checks!B7:B56,"Example",Checks!AH7:AH56,1) -> 1370
A42: Recurring cash change | H42: =SUMIFS(Checks!V7:V56,Checks!B7:B56,"Example",Checks!AH7:AH56,1) -> -97000
A43: Time-valued benefit | H43: =SUMIFS(Checks!Y7:Y56,Checks!B7:B56,"Example",Checks!AH7:AH56,1) -> 899050
A45: Capacity: 50 prepared case IDs and 20 demand rows. Tables support filtering and whole-table sorting; key-based links keep reviews attached to their cases. Adding arbitrary rows is not supported. Formulas are visibly separated but the workbook is not access-controlled: retain a baseline copy and do not overwrite calculated cells.

Sheet Case View
A1: Your case at a glance
A3: Select a case ID. This is a read-only summary; use the edit links below to enter data in its keyed input rows.
A5: =IFERROR(HYPERLINK("#'Start'!A1","← Start"),"← Start") -> ← Start | C5: C001 | E5: ="Case type: "&IF(COUNTIFS(Cases!$A$7:$A$56,$C$5,Cases!$B$7:$B$56,"<>")=1,IFERROR(INDEX(Cases!$B$7:$B$56,MATCH($C$5,Cases!$A$7:$A$56,0)),""),"") -> Case type: Example
A7: =IF(COUNTIFS(Checks!$A$7:$A$56,$C$5,Checks!$J$7:$J$56,"<>")=1,IFERROR(INDEX(Checks!$J$7:$J$56,MATCH($C$5,Checks!$A$7:$A$56,0)),""),"") -> Example only — never in live planning
A10: Scope and proposed change
A11: Activity | D11: =IF(COUNTIFS(Cases!$A$7:$A$56,$C$5,Cases!$C$7:$C$56,"<>")=1,IFERROR(INDEX(Cases!$C$7:$C$56,MATCH($C$5,Cases!$A$7:$A$56,0)),""),"") -> Document classification prompts
A13: Process / scope | D13: =IF(COUNTIFS(Cases!$A$7:$A$56,$C$5,Cases!$D$7:$D$56,"<>")=1,IFERROR(INDEX(Cases!$D$7:$D$56,MATCH($C$5,Cases!$A$7:$A$56,0)),""),"") -> Illustrative organization; replace with a precise local process.
A15: Protection purpose | D15: =IF(COUNTIFS(Cases!$A$7:$A$56,$C$5,Cases!$F$7:$F$56,"<>")=1,IFERROR(INDEX(Cases!$F$7:$F$56,MATCH($C$5,Cases!$A$7:$A$56,0)),""),"") -> Apply appropriate handling to sensitive information, including data leaving its original context.
A17: Chosen proposal | D17: =IF(COUNTIFS(Cases!$A$7:$A$56,$C$5,Cases!$G$7:$G$56,"<>")=1,IFERROR(INDEX(Cases!$G$7:$G$56,MATCH($C$5,Cases!$A$7:$A$56,0)),""),"") -> Replace
A19: Change / retained work | D19: =IF(COUNTIFS(Cases!$A$7:$A$56,$C$5,Cases!$H$7:$H$56,"<>")=1,IFERROR(INDEX(Cases!$H$7:$H$56,MATCH($C$5,Cases!$A$7:$A$56,0)),""),"") -> Full post-change operating profile; unchanged work is included.
A22: Annual comparison — current minus proposed; positive means a reduction
A23: Metric | E23: Current | G23: Proposed | I23: Change / benefit
A24: Business hours / year | E24: =IFERROR(INDEX(Checks!$N$7:$N$56,MATCH($C$5,Checks!$A$7:$A$56,0)),"") -> 7333.3333 | G24: =IFERROR(INDEX(Checks!$O$7:$O$56,MATCH($C$5,Checks!$A$7:$A$56,0)),"") -> 300 | I24: =IFERROR(INDEX(Checks!$P$7:$P$56,MATCH($C$5,Checks!$A$7:$A$56,0)),"") -> 7033.3333
A25: Specialist hours / year | E25: =IFERROR(INDEX(Checks!$Q$7:$Q$56,MATCH($C$5,Checks!$A$7:$A$56,0)),"") -> 150 | G25: =IFERROR(INDEX(Checks!$R$7:$R$56,MATCH($C$5,Checks!$A$7:$A$56,0)),"") -> 80 | I25: =IFERROR(INDEX(Checks!$S$7:$S$56,MATCH($C$5,Checks!$A$7:$A$56,0)),"") -> 70
A26: Recurring cash / year | E26: =IFERROR(INDEX(Checks!$T$7:$T$56,MATCH($C$5,Checks!$A$7:$A$56,0)),"") -> 0 | G26: =IFERROR(INDEX(Checks!$U$7:$U$56,MATCH($C$5,Checks!$A$7:$A$56,0)),"") -> 60000 | I26: =IFERROR(INDEX(Checks!$V$7:$V$56,MATCH($C$5,Checks!$A$7:$A$56,0)),"") -> -60000
A27: Cost including valued time / year | E27: =IFERROR(INDEX(Checks!$W$7:$W$56,MATCH($C$5,Checks!$A$7:$A$56,0)),"") -> 451250 | G27: =IFERROR(INDEX(Checks!$X$7:$X$56,MATCH($C$5,Checks!$A$7:$A$56,0)),"") -> 84000 | I27: =IFERROR(INDEX(Checks!$Y$7:$Y$56,MATCH($C$5,Checks!$A$7:$A$56,0)),"") -> 367250
A28: One-time implementation cost is additional. Time-valued benefit is not a cash saving. | I28: =IFERROR(INDEX(Checks!$Z$7:$Z$56,MATCH($C$5,Checks!$A$7:$A$56,0)),"") -> 40000
A31: Decision, evidence and actual measurement
A32: Local confidence | E32: Decision | I32: Benefit stage
A33: =IF(COUNTIFS('Review & Decision'!$A$7:$A$56,$C$5,'Review & Decision'!$B$7:$B$56,"<>")=1,IFERROR(INDEX('Review & Decision'!$B$7:$B$56,MATCH($C$5,'Review & Decision'!$A$7:$A$56,0)),""),"") -> Hypothesis | E33: =IF(COUNTIFS('Review & Decision'!$A$7:$A$56,$C$5,'Review & Decision'!$E$7:$E$56,"<>")=1,IFERROR(INDEX('Review & Decision'!$E$7:$E$56,MATCH($C$5,'Review & Decision'!$A$7:$A$56,0)),""),"") -> Open | I33: =IF(COUNTIFS('Review & Decision'!$A$7:$A$56,$C$5,'Review & Decision'!$H$7:$H$56,"<>")=1,IFERROR(INDEX('Review & Decision'!$H$7:$H$56,MATCH($C$5,'Review & Decision'!$A$7:$A$56,0)),""),"") -> Modeled
A35: Evidence reference | D35: =IF(COUNTIFS('Review & Decision'!$A$7:$A$56,$C$5,'Review & Decision'!$D$7:$D$56,"<>")=1,IFERROR(INDEX('Review & Decision'!$D$7:$D$56,MATCH($C$5,'Review & Decision'!$A$7:$A$56,0)),""),"") -> Illustrative scenario; no local validation.
A38: Challenge review | D38: =IF(COUNTIFS('Challenge Review'!$A$7:$A$56,$C$5,'Challenge Review'!$K$7:$K$56,"<>")=1,IFERROR(INDEX('Challenge Review'!$K$7:$K$56,MATCH($C$5,'Challenge Review'!$A$7:$A$56,0)),""),"") -> Unchecked
A41: Measurement status | D41: =IF(COUNTIFS(Actuals!$A$7:$A$56,$C$5,Actuals!$M$7:$M$56,"<>")=1,IFERROR(INDEX(Actuals!$M$7:$M$56,MATCH($C$5,Actuals!$A$7:$A$56,0)),""),"") -> Measurements incomplete
A44: Measured result | D44: =IF(IFERROR(INDEX(Checks!$I$7:$I$56,MATCH($C$5,Checks!$A$7:$A$56,0)),"")=1,"Measurements documented. See Actuals for signed changes, period and verification.","No complete, period-backed measurement is available.") -> No complete, period-backed measurement is available.
A47: Edit this case — links follow the case ID even after sorting
A48: =IFERROR(HYPERLINK("#'Cases'!C"&(MATCH($C$5,Cases!$A$7:$A$56,0)+6),"1 Scope and proposal"),"1 Scope and proposal") -> 1 Scope and proposal | E48: =IFERROR(HYPERLINK("#'Current'!B"&(MATCH($C$5,Current!$A$7:$A$56,0)+6),"2a Current profile"),"2a Current profile") -> 2a Current profile | I48: =IFERROR(HYPERLINK("#'Proposed'!B"&(MATCH($C$5,Proposed!$A$7:$A$56,0)+6),"2b Proposed profile"),"2b Proposed profile") -> 2b Proposed profile
A51: =IFERROR(HYPERLINK("#'Review & Decision'!B"&(MATCH($C$5,'Review & Decision'!$A$7:$A$56,0)+6),"3 Evidence / decision"),"3 Evidence / decision") -> 3 Evidence / decision | E51: =IFERROR(HYPERLINK("#'Challenge Review'!B"&(MATCH($C$5,'Challenge Review'!$A$7:$A$56,0)+6),"3b Challenge review"),"3b Challenge review") -> 3b Challenge review | I51: =IFERROR(HYPERLINK("#'Actuals'!B"&(MATCH($C$5,Actuals!$A$7:$A$56,0)+6),"4 Actual measurements"),"4 Actual measurements") -> 4 Actual measurements
A54: A workbook estimate does not authorize a control change. Confirm protection, obligations, rare-event exposure and a like-for-like alternative. Examples are hypotheses for comparison—not recommendations to retire the named controls.

Sheet Cases
A1: 01 Define the case
A3: Blue cells are editable. Use one activity in one process. Start a live case in C012; keep example records as Example.
A5: =IFERROR(HYPERLINK("#'Start'!A1","← Start"),"← Start") -> ← Start
A6: Case ID | B6: Case type | C6: Activity | D6: Process / scope | E6: Case owner | F6: Protection purpose | G6: Chosen proposal | H6: What changes / remains | I6: Assumptions / scope notes
A7: C001 | B7: Example | C7: Document classification prompts | D7: Illustrative organization; replace with a precise local process. | E7: Example only | F7: Apply appropriate handling to sensitive information, including data leaving its original context. | G7: Replace | H7: Full post-change operating profile; unchanged work is included. | I7: Illustrative, unvalidated assumptions migrated from the attached v5 workbook.
A8: C002 | B8: Example | C8: Periodic password changes | D8: Illustrative organization; replace with a precise local process. | E8: Example only | F8: Reduce the risk of compromised human authentication secrets. | G8: Replace | H8: Full post-change operating profile; unchanged work is included. | I8: Illustrative, unvalidated assumptions migrated from the attached v5 workbook.
A9: C003 | B9: Example | C9: Awareness training and phishing exercises | D9: Illustrative organization; replace with a precise local process. | E9: Example only | F9: Build relevant security capabilities, reliable reporting and appropriate responses. | G9: Simplify | H9: Full post-change operating profile; unchanged work is included. | I9: Illustrative, unvalidated assumptions migrated from the attached v5 workbook.
A10: C004 | B10: Example | C10: Quarterly access reviews | D10: Illustrative organization; replace with a precise local process. | E10: Example only | F10: Remove unnecessary access and identify inappropriate privileged access. | G10: Replace | H10: Full post-change operating profile; unchanged work is included. | I10: Illustrative, unvalidated assumptions migrated from the attached v5 workbook.
A11: C005 | B11: Example | C11: Supplier security questionnaires | D11: Illustrative organization; replace with a precise local process. | E11: Example only | F11: Understand and manage supplier access, exposure and operational dependency. | G11: Replace | H11: Full post-change operating profile; unchanged work is included. | I11: Illustrative, unvalidated assumptions migrated from the attached v5 workbook.
A12: C006 | B12: Example | C12: Vulnerability remediation prioritization | D12: Illustrative organization; replace with a precise local process. | E12: Example only | F12: Reduce exploitable weaknesses according to reachability and business consequences. | G12: Simplify | H12: Full post-change operating profile; unchanged work is included. | I12: Illustrative, unvalidated assumptions migrated from the attached v5 workbook.
A13: C007 | B13: Example | C13: Workplace access restrictions | D13: Illustrative organization; replace with a precise local process. | E13: Example only | F13: Limit unauthorized data movement and access while supporting legitimate work. | G13: Simplify | H13: Full post-change operating profile; unchanged work is included. | I13: Illustrative, unvalidated assumptions migrated from the attached v5 workbook.
A14: C008 | B14: Example | C14: Policy and risk assessment workshops | D14: Illustrative organization; replace with a precise local process. | E14: Example only | F14: Enable risk-informed decisions and communicate clear security expectations. | G14: Simplify | H14: Full post-change operating profile; unchanged work is included. | I14: Illustrative, unvalidated assumptions migrated from the attached v5 workbook.
A15: C009 | B15: Example | C15: Phishing-resistant authentication | D15: Illustrative organization; replace with a precise local process. | E15: Example only | F15: Resist credential theft and phishing-mediated account compromise. | G15: Retain | H15: Retain current protection and operating profile. | I15: Illustrative, unvalidated assumptions migrated from the attached v5 workbook.
A16: C010 | B16: Example | C16: Endpoint detection and response | D16: Illustrative organization; replace with a precise local process. | E16: Example only | F16: Detect and respond to compromise within a suitable operational window. | G16: Retain | H16: Retain current protection and operating profile. | I16: Illustrative, unvalidated assumptions migrated from the attached v5 workbook.
A17: C011 | B17: Example | C17: Critical-service recovery tests | D17: Illustrative organization; replace with a precise local process. | E17: Example only | F17: Demonstrate restoration of critical services under credible disruption scenarios. | G17: Retain | H17: Retain current protection and operating profile. | I17: Illustrative, unvalidated assumptions migrated from the attached v5 workbook.
A18: C012 | B18: Inactive
A19: C013 | B19: Inactive
A20: C014 | B20: Inactive
A21: C015 | B21: Inactive
A22: C016 | B22: Inactive
A23: C017 | B23: Inactive
A24: C018 | B24: Inactive
A25: C019 | B25: Inactive
A26: C020 | B26: Inactive
A27: C021 | B27: Inactive
A28: C022 | B28: Inactive
A29: C023 | B29: Inactive
... A56: C050 | B56: Inactive

Sheet Current
A1: 02a Current annual workload and cost
A3: Enter required annual figures and confirmed zeros. Cash means non-labor spend; employment cost is valued through hours. Execution hours apply to the selected group; additional specialist hours are separate.
A5: =IFERROR(HYPERLINK("#'Start'!A1","← Start"),"← Start") -> ← Start
A6: Case ID | B6: Execution group | C6: Execution h/year | D6: Additional specialist h/year | E6: Recurring cash €/year | F6: Estimate / measurement source | G6: Input status | H6: Business h/year | I6: Specialist h/year | J6: Time cost €/year | K6: Total cost €/year
A7: C001 | B7: Staff | C7: 7333.3333 | D7: 150 | E7: 0 | F7: Original example 1; annual hours retained from source. Not measured. | G7: =IF(AND(COUNT(C7:E7)=3,MIN(C7:E7)>=0,OR(B7="Staff",B7="Management",B7="Specialist"),LEN(TRIM(F7))>0,COUNT(Settings!$B$9:$B$11)=3,MIN(Settings!$B$9:$B$11)>=0),"Ready","Complete blue inputs") -> Ready | H7: =IF(G7="Ready",IF(B7="Specialist",0,C7),"") -> 7333.3333 | I7: =IF(G7="Ready",D7+IF(B7="Specialist",C7,0),"") -> 150 | J7: =IF(G7="Ready",C7*IF(B7="Staff",Settings!$B$9,IF(B7="Management",Settings!$B$10,Settings!$B$11))+D7*Settings!$B$11,"") -> 451250 | K7: =IF(G7="Ready",J7+E7,"") -> 451250
A8: C002 | B8: Staff | C8: 1733.3333 | D8: 0 | E8: 0 | F8: Original example 2; annual hours retained from source. Not measured. | G8: =IF(AND(COUNT(C8:E8)=3,MIN(C8:E8)>=0,OR(B8="Staff",B8="Management",B8="Specialist"),LEN(TRIM(F8))>0,COUNT(Settings!$B$9:$B$11)=3,MIN(Settings!$B$9:$B$11)>=0),"Ready","Complete blue inputs") -> Ready | H8: =IF(G8="Ready",IF(B8="Specialist",0,C8),"") -> 1733.3333 | I8: =IF(G8="Ready",D8+IF(B8="Specialist",C8,0),"") -> 0 | J8: =IF(G8="Ready",C8*IF(B8="Staff",Settings!$B$9,IF(B8="Management",Settings!$B$10,Settings!$B$11))+D8*Settings!$B$11,"") -> 104000 | K8: =IF(G8="Ready",J8+E8,"") -> 104000
A9: C003 | B9: Staff | C9: 2296.6667 | D9: 200 | E9: 0 | F9: Original example 3; annual hours retained from source. Not measured. | G9: =IF(AND(COUNT(C9:E9)=3,MIN(C9:E9)>=0,OR(B9="Staff",B9="Management",B9="Specialist"),LEN(TRIM(F9))>0,COUNT(Settings!$B$9:$B$11)=3,MIN(Settings!$B$9:$B$11)>=0),"Ready","Complete blue inputs") -> Ready | H9: =IF(G9="Ready",IF(B9="Specialist",0,C9),"") -> 2296.6667 | I9: =IF(G9="Ready",D9+IF(B9="Specialist",C9,0),"") -> 200 | J9: =IF(G9="Ready",C9*IF(B9="Staff",Settings!$B$9,IF(B9="Management",Settings!$B$10,Settings!$B$11))+D9*Settings!$B$11,"") -> 152800 | K9: =IF(G9="Ready",J9+E9,"") -> 152800
A10: C004 | B10: Management | C10: 800 | D10: 160 | E10: 0 | F10: Original example 4; annual hours retained from source. Not measured. | G10: =IF(AND(COUNT(C10:E10)=3,MIN(C10:E10)>=0,OR(B10="Staff",B10="Management",B10="Specialist"),LEN(TRIM(F10))>0,COUNT(Settings!$B$9:$B$11)=3,MIN(Settings!$B$9:$B$11)>=0),"Ready","Complete blue inputs") -> Ready | H10: =IF(G10="Ready",IF(B10="Specialist",0,C10),"") -> 800 | I10: =IF(G10="Ready",D10+IF(B10="Specialist",C10,0),"") -> 160 | J10: =IF(G10="Ready",C10*IF(B10="Staff",Settings!$B$9,IF(B10="Management",Settings!$B$10,Settings!$B$11))+D10*Settings!$B$11,"") -> 84000 | K10: =IF(G10="Ready",J10+E10,"") -> 84000
A11: C005 | B11: Specialist | C11: 500 | D11: 300 | E11: 0 | F11: Original example 5; annual hours retained from source. Not measured. | G11: =IF(AND(COUNT(C11:E11)=3,MIN(C11:E11)>=0,OR(B11="Staff",B11="Management",B11="Specialist"),LEN(TRIM(F11))>0,COUNT(Settings!$B$9:$B$11)=3,MIN(Settings!$B$9:$B$11)>=0),"Ready","Complete blue inputs") -> Ready | H11: =IF(G11="Ready",IF(B11="Specialist",0,C11),"") -> 0 | I11: =IF(G11="Ready",D11+IF(B11="Specialist",C11,0),"") -> 800 | J11: =IF(G11="Ready",C11*IF(B11="Staff",Settings!$B$9,IF(B11="Management",Settings!$B$10,Settings!$B$11))+D11*Settings!$B$11,"") -> 60000 | K11: =IF(G11="Ready",J11+E11,"") -> 60000
A12: C006 | B12: Specialist | C12: 1000 | D12: 400 | E12: 0 | F12: Original example 6; annual hours retained from source. Not measured. | G12: =IF(AND(COUNT(C12:E12)=3,MIN(C12:E12)>=0,OR(B12="Staff",B12="Management",B12="Specialist"),LEN(TRIM(F12))>0,COUNT(Settings!$B$9:$B$11)=3,MIN(Settings!$B$9:$B$11)>=0),"Ready","Complete blue inputs") -> Ready | H12: =IF(G12="Ready",IF(B12="Specialist",0,C12),"") -> 0 | I12: =IF(G12="Ready",D12+IF(B12="Specialist",C12,0),"") -> 1400 | J12: =IF(G12="Ready",C12*IF(B12="Staff",Settings!$B$9,IF(B12="Management",Settings!$B$10,Settings!$B$11))+D12*Settings!$B$11,"") -> 105000 | K12: =IF(G12="Ready",J12+E12,"") -> 105000
A13: C007 | B13: Staff | C13: 3300 | D13: 100 | E13: 0 | F13: Original example 7; annual hours retained from source. Not measured. | G13: =IF(AND(COUNT(C13:E13)=3,MIN(C13:E13)>=0,OR(B13="Staff",B13="Management",B13="Specialist"),LEN(TRIM(F13))>0,COUNT(Settings!$B$9:$B$11)=3,MIN(Settings!$B$9:$B$11)>=0),"Ready","Complete blue inputs") -> Ready | H13: =IF(G13="Ready",IF(B13="Specialist",0,C13),"") -> 3300 | I13: =IF(G13="Ready",D13+IF(B13="Specialist",C13,0),"") -> 100 | J13: =IF(G13="Ready",C13*IF(B13="Staff",Settings!$B$9,IF(B13="Management",Settings!$B$10,Settings!$B$11))+D13*Settings!$B$11,"") -> 205500 | K13: =IF(G13="Ready",J13+E13,"") -> 205500
A14: C008 | B14: Management | C14: 600 | D14: 120 | E14: 0 | F14: Original example 8; annual hours retained from source. Not measured. | G14: =IF(AND(COUNT(C14:E14)=3,MIN(C14:E14)>=0,OR(B14="Staff",B14="Management",B14="Specialist"),LEN(TRIM(F14))>0,COUNT(Settings!$B$9:$B$11)=3,MIN(Settings!$B$9:$B$11)>=0),"Ready","Complete blue inputs") -> Ready | H14: =IF(G14="Ready",IF(B14="Specialist",0,C14),"") -> 600 | I14: =IF(G14="Ready",D14+IF(B14="Specialist",C14,0),"") -> 120 | J14: =IF(G14="Ready",C14*IF(B14="Staff",Settings!$B$9,IF(B14="Management",Settings!$B$10,Settings!$B$11))+D14*Settings!$B$11,"") -> 63000 | K14: =IF(G14="Ready",J14+E14,"") -> 63000
A15: C009 | B15: Staff | C15: 1100 | D15: 80 | E15: 4000 | F15: Original example 9; annual hours retained from source. Not measured. | G15: =IF(AND(COUNT(C15:E15)=3,MIN(C15:E15)>=0,OR(B15="Staff",B15="Management",B15="Specialist"),LEN(TRIM(F15))>0,COUNT(Settings!$B$9:$B$11)=3,MIN(Settings!$B$9:$B$11)>=0),"Ready","Complete blue inputs") -> Ready | H15: =IF(G15="Ready",IF(B15="Specialist",0,C15),"") -> 1100 | I15: =IF(G15="Ready",D15+IF(B15="Specialist",C15,0),"") -> 80 | J15: =IF(G15="Ready",C15*IF(B15="Staff",Settings!$B$9,IF(B15="Management",Settings!$B$10,Settings!$B$11))+D15*Settings!$B$11,"") -> 72000 | K15: =IF(G15="Ready",J15+E15,"") -> 76000
A16: C010 | B16: Specialist | C16: 0 | D16: 300 | E16: 90000 | F16: Original example 10; annual hours retained from source. Not measured. | G16: =IF(AND(COUNT(C16:E16)=3,MIN(C16:E16)>=0,OR(B16="Staff",B16="Management",B16="Specialist"),LEN(TRIM(F16))>0,COUNT(Settings!$B$9:$B$11)=3,MIN(Settings!$B$9:$B$11)>=0),"Ready","Complete blue inputs") -> Ready | H16: =IF(G16="Ready",IF(B16="Specialist",0,C16),"") -> 0 | I16: =IF(G16="Ready",D16+IF(B16="Specialist",C16,0),"") -> 300 | J16: =IF(G16="Ready",C16*IF(B16="Staff",Settings!$B$9,IF(B16="Management",Settings!$B$10,Settings!$B$11))+D16*Settings!$B$11,"") -> 22500 | K16: =IF(G16="Ready",J16+E16,"") -> 112500
A17: C011 | B17: Specialist | C17: 0 | D17: 120 | E17: 0 | F17: Original example 11; annual hours retained from source. Not measured. | G17: =IF(AND(COUNT(C17:E17)=3,MIN(C17:E17)>=0,OR(B17="Staff",B17="Management",B17="Specialist"),LEN(TRIM(F17))>0,COUNT(Settings!$B$9:$B$11)=3,MIN(Settings!$B$9:$B$11)>=0),"Ready","Complete blue inputs") -> Ready | H17: =IF(G17="Ready",IF(B17="Specialist",0,C17),"") -> 0 | I17: =IF(G17="Ready",D17+IF(B17="Specialist",C17,0),"") -> 120 | J17: =IF(G17="Ready",C17*IF(B17="Staff",Settings!$B$9,IF(B17="Management",Settings!$B$10,Settings!$B$11))+D17*Settings!$B$11,"") -> 9000 | K17: =IF(G17="Ready",J17+E17,"") -> 9000
A18: C012 | G18: =IF(AND(COUNT(C18:E18)=3,MIN(C18:E18)>=0,OR(B18="Staff",B18="Management",B18="Specialist"),LEN(TRIM(F18))>0,COUNT(Settings!$B$9:$B$11)=3,MIN(Settings!$B$9:$B$11)>=0),"Ready","Complete blue inputs") -> Complete blue inputs | H18: =IF(G18="Ready",IF(B18="Specialist",0,C18),"") | I18: =IF(G18="Ready",D18+IF(B18="Specialist",C18,0),"") | J18: =IF(G18="Ready",C18*IF(B18="Staff",Settings!$B$9,IF(B18="Management",Settings!$B$10,Settings!$B$11))+D18*Settings!$B$11,"") | K18: =IF(G18="Ready",J18+E18,"")
A19: C013 | G19: =IF(AND(COUNT(C19:E19)=3,MIN(C19:E19)>=0,OR(B19="Staff",B19="Management",B19="Specialist"),LEN(TRIM(F19))>0,COUNT(Settings!$B$9:$B$11)=3,MIN(Settings!$B$9:$B$11)>=0),"Ready","Complete blue inputs") -> Complete blue inputs | H19: =IF(G19="Ready",IF(B19="Specialist",0,C19),"") | I19: =IF(G19="Ready",D19+IF(B19="Specialist",C19,0),"") | J19: =IF(G19="Ready",C19*IF(B19="Staff",Settings!$B$9,IF(B19="Management",Settings!$B$10,Settings!$B$11))+D19*Settings!$B$11,"") | K19: =IF(G19="Ready",J19+E19,"")
A20: C014 | G20: =IF(AND(COUNT(C20:E20)=3,MIN(C20:E20)>=0,OR(B20="Staff",B20="Management",B20="Specialist"),LEN(TRIM(F20))>0,COUNT(Settings!$B$9:$B$11)=3,MIN(Settings!$B$9:$B$11)>=0),"Ready","Complete blue inputs") -> Complete blue inputs | H20: =IF(G20="Ready",IF(B20="Specialist",0,C20),"") | I20: =IF(G20="Ready",D20+IF(B20="Specialist",C20,0),"") | J20: =IF(G20="Ready",C20*IF(B20="Staff",Settings!$B$9,IF(B20="Management",Settings!$B$10,Settings!$B$11))+D20*Settings!$B$11,"") | K20: =IF(G20="Ready",J20+E20,"")
A21: C015 | G21: =IF(AND(COUNT(C21:E21)=3,MIN(C21:E21)>=0,OR(B21="Staff",B21="Management",B21="Specialist"),LEN(TRIM(F21))>0,COUNT(Settings!$B$9:$B$11)=3,MIN(Settings!$B$9:$B$11)>=0),"Ready","Complete blue inputs") -> Complete blue inputs | H21: =IF(G21="Ready",IF(B21="Specialist",0,C21),"") | I21: =IF(G21="Ready",D21+IF(B21="Specialist",C21,0),"") | J21: =IF(G21="Ready",C21*IF(B21="Staff",Settings!$B$9,IF(B21="Management",Settings!$B$10,Settings!$B$11))+D21*Settings!$B$11,"") | K21: =IF(G21="Ready",J21+E21,"")
A22: C016 | G22: =IF(AND(COUNT(C22:E22)=3,MIN(C22:E22)>=0,OR(B22="Staff",B22="Management",B22="Specialist"),LEN(TRIM(F22))>0,COUNT(Settings!$B$9:$B$11)=3,MIN(Settings!$B$9:$B$11)>=0),"Ready","Complete blue inputs") -> Complete blue inputs | H22: =IF(G22="Ready",IF(B22="Specialist",0,C22),"") | I22: =IF(G22="Ready",D22+IF(B22="Specialist",C22,0),"") | J22: =IF(G22="Ready",C22*IF(B22="Staff",Settings!$B$9,IF(B22="Management",Settings!$B$10,Settings!$B$11))+D22*Settings!$B$11,"") | K22: =IF(G22="Ready",J22+E22,"")
A23: C017 | G23: =IF(AND(COUNT(C23:E23)=3,MIN(C23:E23)>=0,OR(B23="Staff",B23="Management",B23="Specialist"),LEN(TRIM(F23))>0,COUNT(Settings!$B$9:$B$11)=3,MIN(Settings!$B$9:$B$11)>=0),"Ready","Complete blue inputs") -> Complete blue inputs | H23: =IF(G23="Ready",IF(B23="Specialist",0,C23),"") | I23: =IF(G23="Ready",D23+IF(B23="Specialist",C23,0),"") | J23: =IF(G23="Ready",C23*IF(B23="Staff",Settings!$B$9,IF(B23="Management",Settings!$B$10,Settings!$B$11))+D23*Settings!$B$11,"") | K23: =IF(G23="Ready",J23+E23,"")
A24: C018 | G24: =IF(AND(COUNT(C24:E24)=3,MIN(C24:E24)>=0,OR(B24="Staff",B24="Management",B24="Specialist"),LEN(TRIM(F24))>0,COUNT(Settings!$B$9:$B$11)=3,MIN(Settings!$B$9:$B$11)>=0),"Ready","Complete blue inputs") -> Complete blue inputs | H24: =IF(G24="Ready",IF(B24="Specialist",0,C24),"") | I24: =IF(G24="Ready",D24+IF(B24="Specialist",C24,0),"") | J24: =IF(G24="Ready",C24*IF(B24="Staff",Settings!$B$9,IF(B24="Management",Settings!$B$10,Settings!$B$11))+D24*Settings!$B$11,"") | K24: =IF(G24="Ready",J24+E24,"")
A25: C019 | G25: =IF(AND(COUNT(C25:E25)=3,MIN(C25:E25)>=0,OR(B25="Staff",B25="Management",B25="Specialist"),LEN(TRIM(F25))>0,COUNT(Settings!$B$9:$B$11)=3,MIN(Settings!$B$9:$B$11)>=0),"Ready","Complete blue inputs") -> Complete blue inputs | H25: =IF(G25="Ready",IF(B25="Specialist",0,C25),"") | I25: =IF(G25="Ready",D25+IF(B25="Specialist",C25,0),"") | J25: =IF(G25="Ready",C25*IF(B25="Staff",Settings!$B$9,IF(B25="Management",Settings!$B$10,Settings!$B$11))+D25*Settings!$B$11,"") | K25: =IF(G25="Ready",J25+E25,"")
A26: C020 | G26: =IF(AND(COUNT(C26:E26)=3,MIN(C26:E26)>=0,OR(B26="Staff",B26="Management",B26="Specialist"),LEN(TRIM(F26))>0,COUNT(Settings!$B$9:$B$11)=3,MIN(Settings!$B$9:$B$11)>=0),"Ready","Complete blue inputs") -> Complete blue inputs | H26: =IF(G26="Ready",IF(B26="Specialist",0,C26),"") | I26: =IF(G26="Ready",D26+IF(B26="Specialist",C26,0),"") | J26: =IF(G26="Ready",C26*IF(B26="Staff",Settings!$B$9,IF(B26="Management",Settings!$B$10,Settings!$B$11))+D26*Settings!$B$11,"") | K26: =IF(G26="Ready",J26+E26,"")
A27: C021 | G27: =IF(AND(COUNT(C27:E27)=3,MIN(C27:E27)>=0,OR(B27="Staff",B27="Management",B27="Specialist"),LEN(TRIM(F27))>0,COUNT(Settings!$B$9:$B$11)=3,MIN(Settings!$B$9:$B$11)>=0),"Ready","Complete blue inputs") -> Complete blue inputs | H27: =IF(G27="Ready",IF(B27="Specialist",0,C27),"") | I27: =IF(G27="Ready",D27+IF(B27="Specialist",C27,0),"") | J27: =IF(G27="Ready",C27*IF(B27="Staff",Settings!$B$9,IF(B27="Management",Settings!$B$10,Settings!$B$11))+D27*Settings!$B$11,"") | K27: =IF(G27="Ready",J27+E27,"")
A28: C022 | G28: =IF(AND(COUNT(C28:E28)=3,MIN(C28:E28)>=0,OR(B28="Staff",B28="Management",B28="Specialist"),LEN(TRIM(F28))>0,COUNT(Settings!$B$9:$B$11)=3,MIN(Settings!$B$9:$B$11)>=0),"Ready","Complete blue inputs") -> Complete blue inputs | H28: =IF(G28="Ready",IF(B28="Specialist",0,C28),"") | I28: =IF(G28="Ready",D28+IF(B28="Specialist",C28,0),"") | J28: =IF(G28="Ready",C28*IF(B28="Staff",Settings!$B$9,IF(B28="Management",Settings!$B$10,Settings!$B$11))+D28*Settings!$B$11,"") | K28: =IF(G28="Ready",J28+E28,"")
A29: C023 | G29: =IF(AND(COUNT(C29:E29)=3,MIN(C29:E29)>=0,OR(B29="Staff",B29="Management",B29="Specialist"),LEN(TRIM(F29))>0,COUNT(Settings!$B$9:$B$11)=3,MIN(Settings!$B$9:$B$11)>=0),"Ready","Complete blue inputs") -> Complete blue inputs | H29: =IF(G29="Ready",IF(B29="Specialist",0,C29),"") | I29: =IF(G29="Ready",D29+IF(B29="Specialist",C29,0),"") | J29: =IF(G29="Ready",C29*IF(B29="Staff",Settings!$B$9,IF(B29="Management",Settings!$B$10,Settings!$B$11))+D29*Settings!$B$11,"") | K29: =IF(G29="Ready",J29+E29,"")
... A56: C050 | G56: =IF(AND(COUNT(C56:E56)=3,MIN(C56:E56)>=0,OR(B56="Staff",B56="Management",B56="Specialist"),LEN(TRIM(F56))>0,COUNT(Settings!$B$9:$B$11)=3,MIN(Settings!$B$9:$B$11)>=0),"Ready","Complete blue inputs") -> Complete blue inputs | H56: =IF(G56="Ready",IF(B56="Specialist",0,C56),"") | I56: =IF(G56="Ready",D56+IF(B56="Specialist",C56,0),"") | J56: =IF(G56="Ready",C56*IF(B56="Staff",Settings!$B$9,IF(B56="Management",Settings!$B$10,Settings!$B$11))+D56*Settings!$B$11,"") | K56: =IF(G56="Ready",J56+E56,"")

Sheet Proposed
A1: 02b Proposed annual workload and cost
A3: Enter the full post-change profile: unchanged work, fixed costs and transition effort. Cash means non-labor spend, not employment cost already valued through hours. No relevance score chooses the scenario.
A5: =IFERROR(HYPERLINK("#'Start'!A1","← Start"),"← Start") -> ← Start
A6: Case ID | B6: Execution group | C6: Execution h/year | D6: Additional specialist h/year | E6: Recurring cash €/year | F6: One-time cost € | G6: Estimate / measurement source | H6: Input status | I6: Business h/year | J6: Specialist h/year | K6: Time cost €/year | L6: Total cost €/year
A7: C001 | B7: Staff | C7: 300 | D7: 80 | E7: 60000 | F7: 40000 | G7: Original proposed example 1; assumed full annual profile. Not validated. | H7: =IF(AND(COUNT(C7:F7)=4,MIN(C7:F7)>=0,OR(B7="Staff",B7="Management",B7="Specialist"),LEN(TRIM(G7))>0,COUNT(Settings!$B$9:$B$11)=3,MIN(Settings!$B$9:$B$11)>=0),"Ready","Complete blue inputs") -> Ready | I7: =IF(H7="Ready",IF(B7="Specialist",0,C7),"") -> 300 | J7: =IF(H7="Ready",D7+IF(B7="Specialist",C7,0),"") -> 80 | K7: =IF(H7="Ready",C7*IF(B7="Staff",Settings!$B$9,IF(B7="Management",Settings!$B$10,Settings!$B$11))+D7*Settings!$B$11,"") -> 24000 | L7: =IF(H7="Ready",K7+E7,"") -> 84000
A8: C002 | B8: Staff | C8: 0 | D8: 10 | E8: 0 | F8: 5000 | G8: Original proposed example 2; assumed full annual profile. Not validated. | H8: =IF(AND(COUNT(C8:F8)=4,MIN(C8:F8)>=0,OR(B8="Staff",B8="Management",B8="Specialist"),LEN(TRIM(G8))>0,COUNT(Settings!$B$9:$B$11)=3,MIN(Settings!$B$9:$B$11)>=0),"Ready","Complete blue inputs") -> Ready | I8: =IF(H8="Ready",IF(B8="Specialist",0,C8),"") -> 0 | J8: =IF(H8="Ready",D8+IF(B8="Specialist",C8,0),"") -> 10 | K8: =IF(H8="Ready",C8*IF(B8="Staff",Settings!$B$9,IF(B8="Management",Settings!$B$10,Settings!$B$11))+D8*Settings!$B$11,"") -> 750 | L8: =IF(H8="Ready",K8+E8,"") -> 750
A9: C003 | B9: Staff | C9: 400 | D9: 60 | E9: 0 | F9: 5000 | G9: Original proposed example 3; assumed full annual profile. Not validated. | H9: =IF(AND(COUNT(C9:F9)=4,MIN(C9:F9)>=0,OR(B9="Staff",B9="Management",B9="Specialist"),LEN(TRIM(G9))>0,COUNT(Settings!$B$9:$B$11)=3,MIN(Settings!$B$9:$B$11)>=0),"Ready","Complete blue inputs") -> Ready | I9: =IF(H9="Ready",IF(B9="Specialist",0,C9),"") -> 400 | J9: =IF(H9="Ready",D9+IF(B9="Specialist",C9,0),"") -> 60 | K9: =IF(H9="Ready",C9*IF(B9="Staff",Settings!$B$9,IF(B9="Management",Settings!$B$10,Settings!$B$11))+D9*Settings!$B$11,"") -> 28500 | L9: =IF(H9="Ready",K9+E9,"") -> 28500
A10: C004 | B10: Management | C10: 100 | D10: 40 | E10: 15000 | F10: 25000 | G10: Original proposed example 4; assumed full annual profile. Not validated. | H10: =IF(AND(COUNT(C10:F10)=4,MIN(C10:F10)>=0,OR(B10="Staff",B10="Management",B10="Specialist"),LEN(TRIM(G10))>0,COUNT(Settings!$B$9:$B$11)=3,MIN(Settings!$B$9:$B$11)>=0),"Ready","Complete blue inputs") -> Ready | I10: =IF(H10="Ready",IF(B10="Specialist",0,C10),"") -> 100 | J10: =IF(H10="Ready",D10+IF(B10="Specialist",C10,0),"") -> 40 | K10: =IF(H10="Ready",C10*IF(B10="Staff",Settings!$B$9,IF(B10="Management",Settings!$B$10,Settings!$B$11))+D10*Settings!$B$11,"") -> 12000 | L10: =IF(H10="Ready",K10+E10,"") -> 27000
A11: C005 | B11: Specialist | C11: 50 | D11: 120 | E11: 10000 | F11: 8000 | G11: Original proposed example 5; assumed full annual profile. Not validated. | H11: =IF(AND(COUNT(C11:F11)=4,MIN(C11:F11)>=0,OR(B11="Staff",B11="Management",B11="Specialist"),LEN(TRIM(G11))>0,COUNT(Settings!$B$9:$B$11)=3,MIN(Settings!$B$9:$B$11)>=0),"Ready","Complete blue inputs") -> Ready | I11: =IF(H11="Ready",IF(B11="Specialist",0,C11),"") -> 0 | J11: =IF(H11="Ready",D11+IF(B11="Specialist",C11,0),"") -> 170 | K11: =IF(H11="Ready",C11*IF(B11="Staff",Settings!$B$9,IF(B11="Management",Settings!$B$10,Settings!$B$11))+D11*Settings!$B$11,"") -> 12750 | L11: =IF(H11="Ready",K11+E11,"") -> 22750
A12: C006 | B12: Specialist | C12: 800 | D12: 300 | E12: 0 | F12: 5000 | G12: Original proposed example 6; assumed full annual profile. Not validated. | H12: =IF(AND(COUNT(C12:F12)=4,MIN(C12:F12)>=0,OR(B12="Staff",B12="Management",B12="Specialist"),LEN(TRIM(G12))>0,COUNT(Settings!$B$9:$B$11)=3,MIN(Settings!$B$9:$B$11)>=0),"Ready","Complete blue inputs") -> Ready | I12: =IF(H12="Ready",IF(B12="Specialist",0,C12),"") -> 0 | J12: =IF(H12="Ready",D12+IF(B12="Specialist",C12,0),"") -> 1100 | K12: =IF(H12="Ready",C12*IF(B12="Staff",Settings!$B$9,IF(B12="Management",Settings!$B$10,Settings!$B$11))+D12*Settings!$B$11,"") -> 82500 | L12: =IF(H12="Ready",K12+E12,"") -> 82500
A13: C007 | B13: Staff | C13: 800 | D13: 60 | E13: 12000 | F13: 15000 | G13: Original proposed example 7; assumed full annual profile. Not validated. | H13: =IF(AND(COUNT(C13:F13)=4,MIN(C13:F13)>=0,OR(B13="Staff",B13="Management",B13="Specialist"),LEN(TRIM(G13))>0,COUNT(Settings!$B$9:$B$11)=3,MIN(Settings!$B$9:$B$11)>=0),"Ready","Complete blue inputs") -> Ready | I13: =IF(H13="Ready",IF(B13="Specialist",0,C13),"") -> 800 | J13: =IF(H13="Ready",D13+IF(B13="Specialist",C13,0),"") -> 60 | K13: =IF(H13="Ready",C13*IF(B13="Staff",Settings!$B$9,IF(B13="Management",Settings!$B$10,Settings!$B$11))+D13*Settings!$B$11,"") -> 52500 | L13: =IF(H13="Ready",K13+E13,"") -> 64500
A14: C008 | B14: Management | C14: 150 | D14: 40 | E14: 0 | F14: 2000 | G14: Original proposed example 8; assumed full annual profile. Not validated. | H14: =IF(AND(COUNT(C14:F14)=4,MIN(C14:F14)>=0,OR(B14="Staff",B14="Management",B14="Specialist"),LEN(TRIM(G14))>0,COUNT(Settings!$B$9:$B$11)=3,MIN(Settings!$B$9:$B$11)>=0),"Ready","Complete blue inputs") -> Ready | I14: =IF(H14="Ready",IF(B14="Specialist",0,C14),"") -> 150 | J14: =IF(H14="Ready",D14+IF(B14="Specialist",C14,0),"") -> 40 | K14: =IF(H14="Ready",C14*IF(B14="Staff",Settings!$B$9,IF(B14="Management",Settings!$B$10,Settings!$B$11))+D14*Settings!$B$11,"") -> 16500 | L14: =IF(H14="Ready",K14+E14,"") -> 16500
A15: C009 | B15: Staff | C15: 1100 | D15: 80 | E15: 4000 | F15: 0 | G15: Retain proposal: current annual profile carried forward; no assumed release. | H15: =IF(AND(COUNT(C15:F15)=4,MIN(C15:F15)>=0,OR(B15="Staff",B15="Management",B15="Specialist"),LEN(TRIM(G15))>0,COUNT(Settings!$B$9:$B$11)=3,MIN(Settings!$B$9:$B$11)>=0),"Ready","Complete blue inputs") -> Ready | I15: =IF(H15="Ready",IF(B15="Specialist",0,C15),"") -> 1100 | J15: =IF(H15="Ready",D15+IF(B15="Specialist",C15,0),"") -> 80 | K15: =IF(H15="Ready",C15*IF(B15="Staff",Settings!$B$9,IF(B15="Management",Settings!$B$10,Settings!$B$11))+D15*Settings!$B$11,"") -> 72000 | L15: =IF(H15="Ready",K15+E15,"") -> 76000
A16: C010 | B16: Specialist | C16: 0 | D16: 300 | E16: 90000 | F16: 0 | G16: Retain proposal: current annual profile carried forward; no assumed release. | H16: =IF(AND(COUNT(C16:F16)=4,MIN(C16:F16)>=0,OR(B16="Staff",B16="Management",B16="Specialist"),LEN(TRIM(G16))>0,COUNT(Settings!$B$9:$B$11)=3,MIN(Settings!$B$9:$B$11)>=0),"Ready","Complete blue inputs") -> Ready | I16: =IF(H16="Ready",IF(B16="Specialist",0,C16),"") -> 0 | J16: =IF(H16="Ready",D16+IF(B16="Specialist",C16,0),"") -> 300 | K16: =IF(H16="Ready",C16*IF(B16="Staff",Settings!$B$9,IF(B16="Management",Settings!$B$10,Settings!$B$11))+D16*Settings!$B$11,"") -> 22500 | L16: =IF(H16="Ready",K16+E16,"") -> 112500
A17: C011 | B17: Specialist | C17: 0 | D17: 120 | E17: 0 | F17: 0 | G17: Retain proposal: current annual profile carried forward; no assumed release. | H17: =IF(AND(COUNT(C17:F17)=4,MIN(C17:F17)>=0,OR(B17="Staff",B17="Management",B17="Specialist"),LEN(TRIM(G17))>0,COUNT(Settings!$B$9:$B$11)=3,MIN(Settings!$B$9:$B$11)>=0),"Ready","Complete blue inputs") -> Ready | I17: =IF(H17="Ready",IF(B17="Specialist",0,C17),"") -> 0 | J17: =IF(H17="Ready",D17+IF(B17="Specialist",C17,0),"") -> 120 | K17: =IF(H17="Ready",C17*IF(B17="Staff",Settings!$B$9,IF(B17="Management",Settings!$B$10,Settings!$B$11))+D17*Settings!$B$11,"") -> 9000 | L17: =IF(H17="Ready",K17+E17,"") -> 9000
A18: C012 | H18: =IF(AND(COUNT(C18:F18)=4,MIN(C18:F18)>=0,OR(B18="Staff",B18="Management",B18="Specialist"),LEN(TRIM(G18))>0,COUNT(Settings!$B$9:$B$11)=3,MIN(Settings!$B$9:$B$11)>=0),"Ready","Complete blue inputs") -> Complete blue inputs | I18: =IF(H18="Ready",IF(B18="Specialist",0,C18),"") | J18: =IF(H18="Ready",D18+IF(B18="Specialist",C18,0),"") | K18: =IF(H18="Ready",C18*IF(B18="Staff",Settings!$B$9,IF(B18="Management",Settings!$B$10,Settings!$B$11))+D18*Settings!$B$11,"") | L18: =IF(H18="Ready",K18+E18,"")
A19: C013 | H19: =IF(AND(COUNT(C19:F19)=4,MIN(C19:F19)>=0,OR(B19="Staff",B19="Management",B19="Specialist"),LEN(TRIM(G19))>0,COUNT(Settings!$B$9:$B$11)=3,MIN(Settings!$B$9:$B$11)>=0),"Ready","Complete blue inputs") -> Complete blue inputs | I19: =IF(H19="Ready",IF(B19="Specialist",0,C19),"") | J19: =IF(H19="Ready",D19+IF(B19="Specialist",C19,0),"") | K19: =IF(H19="Ready",C19*IF(B19="Staff",Settings!$B$9,IF(B19="Management",Settings!$B$10,Settings!$B$11))+D19*Settings!$B$11,"") | L19: =IF(H19="Ready",K19+E19,"")
A20: C014 | H20: =IF(AND(COUNT(C20:F20)=4,MIN(C20:F20)>=0,OR(B20="Staff",B20="Management",B20="Specialist"),LEN(TRIM(G20))>0,COUNT(Settings!$B$9:$B$11)=3,MIN(Settings!$B$9:$B$11)>=0),"Ready","Complete blue inputs") -> Complete blue inputs | I20: =IF(H20="Ready",IF(B20="Specialist",0,C20),"") | J20: =IF(H20="Ready",D20+IF(B20="Specialist",C20,0),"") | K20: =IF(H20="Ready",C20*IF(B20="Staff",Settings!$B$9,IF(B20="Management",Settings!$B$10,Settings!$B$11))+D20*Settings!$B$11,"") | L20: =IF(H20="Ready",K20+E20,"")
A21: C015 | H21: =IF(AND(COUNT(C21:F21)=4,MIN(C21:F21)>=0,OR(B21="Staff",B21="Management",B21="Specialist"),LEN(TRIM(G21))>0,COUNT(Settings!$B$9:$B$11)=3,MIN(Settings!$B$9:$B$11)>=0),"Ready","Complete blue inputs") -> Complete blue inputs | I21: =IF(H21="Ready",IF(B21="Specialist",0,C21),"") | J21: =IF(H21="Ready",D21+IF(B21="Specialist",C21,0),"") | K21: =IF(H21="Ready",C21*IF(B21="Staff",Settings!$B$9,IF(B21="Management",Settings!$B$10,Settings!$B$11))+D21*Settings!$B$11,"") | L21: =IF(H21="Ready",K21+E21,"")
A22: C016 | H22: =IF(AND(COUNT(C22:F22)=4,MIN(C22:F22)>=0,OR(B22="Staff",B22="Management",B22="Specialist"),LEN(TRIM(G22))>0,COUNT(Settings!$B$9:$B$11)=3,MIN(Settings!$B$9:$B$11)>=0),"Ready","Complete blue inputs") -> Complete blue inputs | I22: =IF(H22="Ready",IF(B22="Specialist",0,C22),"") | J22: =IF(H22="Ready",D22+IF(B22="Specialist",C22,0),"") | K22: =IF(H22="Ready",C22*IF(B22="Staff",Settings!$B$9,IF(B22="Management",Settings!$B$10,Settings!$B$11))+D22*Settings!$B$11,"") | L22: =IF(H22="Ready",K22+E22,"")
A23: C017 | H23: =IF(AND(COUNT(C23:F23)=4,MIN(C23:F23)>=0,OR(B23="Staff",B23="Management",B23="Specialist"),LEN(TRIM(G23))>0,COUNT(Settings!$B$9:$B$11)=3,MIN(Settings!$B$9:$B$11)>=0),"Ready","Complete blue inputs") -> Complete blue inputs | I23: =IF(H23="Ready",IF(B23="Specialist",0,C23),"") | J23: =IF(H23="Ready",D23+IF(B23="Specialist",C23,0),"") | K23: =IF(H23="Ready",C23*IF(B23="Staff",Settings!$B$9,IF(B23="Management",Settings!$B$10,Settings!$B$11))+D23*Settings!$B$11,"") | L23: =IF(H23="Ready",K23+E23,"")
A24: C018 | H24: =IF(AND(COUNT(C24:F24)=4,MIN(C24:F24)>=0,OR(B24="Staff",B24="Management",B24="Specialist"),LEN(TRIM(G24))>0,COUNT(Settings!$B$9:$B$11)=3,MIN(Settings!$B$9:$B$11)>=0),"Ready","Complete blue inputs") -> Complete blue inputs | I24: =IF(H24="Ready",IF(B24="Specialist",0,C24),"") | J24: =IF(H24="Ready",D24+IF(B24="Specialist",C24,0),"") | K24: =IF(H24="Ready",C24*IF(B24="Staff",Settings!$B$9,IF(B24="Management",Settings!$B$10,Settings!$B$11))+D24*Settings!$B$11,"") | L24: =IF(H24="Ready",K24+E24,"")
A25: C019 | H25: =IF(AND(COUNT(C25:F25)=4,MIN(C25:F25)>=0,OR(B25="Staff",B25="Management",B25="Specialist"),LEN(TRIM(G25))>0,COUNT(Settings!$B$9:$B$11)=3,MIN(Settings!$B$9:$B$11)>=0),"Ready","Complete blue inputs") -> Complete blue inputs | I25: =IF(H25="Ready",IF(B25="Specialist",0,C25),"") | J25: =IF(H25="Ready",D25+IF(B25="Specialist",C25,0),"") | K25: =IF(H25="Ready",C25*IF(B25="Staff",Settings!$B$9,IF(B25="Management",Settings!$B$10,Settings!$B$11))+D25*Settings!$B$11,"") | L25: =IF(H25="Ready",K25+E25,"")
A26: C020 | H26: =IF(AND(COUNT(C26:F26)=4,MIN(C26:F26)>=0,OR(B26="Staff",B26="Management",B26="Specialist"),LEN(TRIM(G26))>0,COUNT(Settings!$B$9:$B$11)=3,MIN(Settings!$B$9:$B$11)>=0),"Ready","Complete blue inputs") -> Complete blue inputs | I26: =IF(H26="Ready",IF(B26="Specialist",0,C26),"") | J26: =IF(H26="Ready",D26+IF(B26="Specialist",C26,0),"") | K26: =IF(H26="Ready",C26*IF(B26="Staff",Settings!$B$9,IF(B26="Management",Settings!$B$10,Settings!$B$11))+D26*Settings!$B$11,"") | L26: =IF(H26="Ready",K26+E26,"")
A27: C021 | H27: =IF(AND(COUNT(C27:F27)=4,MIN(C27:F27)>=0,OR(B27="Staff",B27="Management",B27="Specialist"),LEN(TRIM(G27))>0,COUNT(Settings!$B$9:$B$11)=3,MIN(Settings!$B$9:$B$11)>=0),"Ready","Complete blue inputs") -> Complete blue inputs | I27: =IF(H27="Ready",IF(B27="Specialist",0,C27),"") | J27: =IF(H27="Ready",D27+IF(B27="Specialist",C27,0),"") | K27: =IF(H27="Ready",C27*IF(B27="Staff",Settings!$B$9,IF(B27="Management",Settings!$B$10,Settings!$B$11))+D27*Settings!$B$11,"") | L27: =IF(H27="Ready",K27+E27,"")
A28: C022 | H28: =IF(AND(COUNT(C28:F28)=4,MIN(C28:F28)>=0,OR(B28="Staff",B28="Management",B28="Specialist"),LEN(TRIM(G28))>0,COUNT(Settings!$B$9:$B$11)=3,MIN(Settings!$B$9:$B$11)>=0),"Ready","Complete blue inputs") -> Complete blue inputs | I28: =IF(H28="Ready",IF(B28="Specialist",0,C28),"") | J28: =IF(H28="Ready",D28+IF(B28="Specialist",C28,0),"") | K28: =IF(H28="Ready",C28*IF(B28="Staff",Settings!$B$9,IF(B28="Management",Settings!$B$10,Settings!$B$11))+D28*Settings!$B$11,"") | L28: =IF(H28="Ready",K28+E28,"")
A29: C023 | H29: =IF(AND(COUNT(C29:F29)=4,MIN(C29:F29)>=0,OR(B29="Staff",B29="Management",B29="Specialist"),LEN(TRIM(G29))>0,COUNT(Settings!$B$9:$B$11)=3,MIN(Settings!$B$9:$B$11)>=0),"Ready","Complete blue inputs") -> Complete blue inputs | I29: =IF(H29="Ready",IF(B29="Specialist",0,C29),"") | J29: =IF(H29="Ready",D29+IF(B29="Specialist",C29,0),"") | K29: =IF(H29="Ready",C29*IF(B29="Staff",Settings!$B$9,IF(B29="Management",Settings!$B$10,Settings!$B$11))+D29*Settings!$B$11,"") | L29: =IF(H29="Ready",K29+E29,"")
... A56: C050 | H56: =IF(AND(COUNT(C56:F56)=4,MIN(C56:F56)>=0,OR(B56="Staff",B56="Management",B56="Specialist"),LEN(TRIM(G56))>0,COUNT(Settings!$B$9:$B$11)=3,MIN(Settings!$B$9:$B$11)>=0),"Ready","Complete blue inputs") -> Complete blue inputs | I56: =IF(H56="Ready",IF(B56="Specialist",0,C56),"") | J56: =IF(H56="Ready",D56+IF(B56="Specialist",C56,0),"") | K56: =IF(H56="Ready",C56*IF(B56="Staff",Settings!$B$9,IF(B56="Management",Settings!$B$10,Settings!$B$11))+D56*Settings!$B$11,"") | L56: =IF(H56="Ready",K56+E56,"")

Sheet Review & Decision
A1: 03 Review evidence and record the decision
A3: Planning needs positive approval, a cleared challenge review, local evidence and an effective date. A modeled hypothesis is not an allocatable resource.
A5: =IFERROR(HYPERLINK("#'Start'!A1","← Start"),"← Start") -> ← Start
A6: Case ID | B6: Confidence in local evidence | C6: Protection outcome | D6: Evidence / pilot reference | E6: Human decision | F6: Approver | G6: Decision date | H6: Benefit stage | I6: Effective / available from | J6: Usable business time % | K6: Usable specialist time % | L6: Risk acceptance reference | M6: Next action • calculated
A7: C001 | B7: Hypothesis | C7: Not assessed | D7: Illustrative scenario; no local validation. | E7: Open | H7: Modeled | J7: 0 | K7: 0 | M7: =IF(COUNTIFS(Checks!$A$7:$A$56,$A7,Checks!$J$7:$J$56,"<>")=1,IFERROR(INDEX(Checks!$J$7:$J$56,MATCH($A7,Checks!$A$7:$A$56,0)),""),"") -> Example only — never in live planning
A8: C002 | B8: Hypothesis | C8: Not assessed | D8: Illustrative scenario; no local validation. | E8: Open | H8: Modeled | J8: 0 | K8: 0 | M8: =IF(COUNTIFS(Checks!$A$7:$A$56,$A8,Checks!$J$7:$J$56,"<>")=1,IFERROR(INDEX(Checks!$J$7:$J$56,MATCH($A8,Checks!$A$7:$A$56,0)),""),"") -> Example only — never in live planning
A9: C003 | B9: Hypothesis | C9: Not assessed | D9: Illustrative scenario; no local validation. | E9: Open | H9: Modeled | J9: 0 | K9: 0 | M9: =IF(COUNTIFS(Checks!$A$7:$A$56,$A9,Checks!$J$7:$J$56,"<>")=1,IFERROR(INDEX(Checks!$J$7:$J$56,MATCH($A9,Checks!$A$7:$A$56,0)),""),"") -> Example only — never in live planning
A10: C004 | B10: Hypothesis | C10: Not assessed | D10: Illustrative scenario; no local validation. | E10: Open | H10: Modeled | J10: 0 | K10: 0 | M10: =IF(COUNTIFS(Checks!$A$7:$A$56,$A10,Checks!$J$7:$J$56,"<>")=1,IFERROR(INDEX(Checks!$J$7:$J$56,MATCH($A10,Checks!$A$7:$A$56,0)),""),"") -> Example only — never in live planning
A11: C005 | B11: Hypothesis | C11: Not assessed | D11: Illustrative scenario; no local validation. | E11: Open | H11: Modeled | J11: 0 | K11: 0 | M11: =IF(COUNTIFS(Checks!$A$7:$A$56,$A11,Checks!$J$7:$J$56,"<>")=1,IFERROR(INDEX(Checks!$J$7:$J$56,MATCH($A11,Checks!$A$7:$A$56,0)),""),"") -> Example only — never in live planning
A12: C006 | B12: Hypothesis | C12: Not assessed | D12: Illustrative scenario; no local validation. | E12: Open | H12: Modeled | J12: 0 | K12: 0 | M12: =IF(COUNTIFS(Checks!$A$7:$A$56,$A12,Checks!$J$7:$J$56,"<>")=1,IFERROR(INDEX(Checks!$J$7:$J$56,MATCH($A12,Checks!$A$7:$A$56,0)),""),"") -> Example only — never in live planning
A13: C007 | B13: Hypothesis | C13: Not assessed | D13: Illustrative scenario; no local validation. | E13: Open | H13: Modeled | J13: 0 | K13: 0 | M13: =IF(COUNTIFS(Checks!$A$7:$A$56,$A13,Checks!$J$7:$J$56,"<>")=1,IFERROR(INDEX(Checks!$J$7:$J$56,MATCH($A13,Checks!$A$7:$A$56,0)),""),"") -> Example only — never in live planning
A14: C008 | B14: Hypothesis | C14: Not assessed | D14: Illustrative scenario; no local validation. | E14: Open | H14: Modeled | J14: 0 | K14: 0 | M14: =IF(COUNTIFS(Checks!$A$7:$A$56,$A14,Checks!$J$7:$J$56,"<>")=1,IFERROR(INDEX(Checks!$J$7:$J$56,MATCH($A14,Checks!$A$7:$A$56,0)),""),"") -> Example only — never in live planning
A15: C009 | B15: Hypothesis | C15: Not assessed | D15: Illustrative scenario; no local validation. | E15: Open | H15: Modeled | J15: 0 | K15: 0 | M15: =IF(COUNTIFS(Checks!$A$7:$A$56,$A15,Checks!$J$7:$J$56,"<>")=1,IFERROR(INDEX(Checks!$J$7:$J$56,MATCH($A15,Checks!$A$7:$A$56,0)),""),"") -> Example only — never in live planning
A16: C010 | B16: Hypothesis | C16: Not assessed | D16: Illustrative scenario; no local validation. | E16: Open | H16: Modeled | J16: 0 | K16: 0 | M16: =IF(COUNTIFS(Checks!$A$7:$A$56,$A16,Checks!$J$7:$J$56,"<>")=1,IFERROR(INDEX(Checks!$J$7:$J$56,MATCH($A16,Checks!$A$7:$A$56,0)),""),"") -> Example only — never in live planning
A17: C011 | B17: Hypothesis | C17: Not assessed | D17: Illustrative scenario; no local validation. | E17: Open | H17: Modeled | J17: 0 | K17: 0 | M17: =IF(COUNTIFS(Checks!$A$7:$A$56,$A17,Checks!$J$7:$J$56,"<>")=1,IFERROR(INDEX(Checks!$J$7:$J$56,MATCH($A17,Checks!$A$7:$A$56,0)),""),"") -> Example only — never in live planning
A18: C012 | M18: =IF(COUNTIFS(Checks!$A$7:$A$56,$A18,Checks!$J$7:$J$56,"<>")=1,IFERROR(INDEX(Checks!$J$7:$J$56,MATCH($A18,Checks!$A$7:$A$56,0)),""),"") -> Unused slot
A19: C013 | M19: =IF(COUNTIFS(Checks!$A$7:$A$56,$A19,Checks!$J$7:$J$56,"<>")=1,IFERROR(INDEX(Checks!$J$7:$J$56,MATCH($A19,Checks!$A$7:$A$56,0)),""),"") -> Unused slot
A20: C014 | M20: =IF(COUNTIFS(Checks!$A$7:$A$56,$A20,Checks!$J$7:$J$56,"<>")=1,IFERROR(INDEX(Checks!$J$7:$J$56,MATCH($A20,Checks!$A$7:$A$56,0)),""),"") -> Unused slot
A21: C015 | M21: =IF(COUNTIFS(Checks!$A$7:$A$56,$A21,Checks!$J$7:$J$56,"<>")=1,IFERROR(INDEX(Checks!$J$7:$J$56,MATCH($A21,Checks!$A$7:$A$56,0)),""),"") -> Unused slot
A22: C016 | M22: =IF(COUNTIFS(Checks!$A$7:$A$56,$A22,Checks!$J$7:$J$56,"<>")=1,IFERROR(INDEX(Checks!$J$7:$J$56,MATCH($A22,Checks!$A$7:$A$56,0)),""),"") -> Unused slot
A23: C017 | M23: =IF(COUNTIFS(Checks!$A$7:$A$56,$A23,Checks!$J$7:$J$56,"<>")=1,IFERROR(INDEX(Checks!$J$7:$J$56,MATCH($A23,Checks!$A$7:$A$56,0)),""),"") -> Unused slot
A24: C018 | M24: =IF(COUNTIFS(Checks!$A$7:$A$56,$A24,Checks!$J$7:$J$56,"<>")=1,IFERROR(INDEX(Checks!$J$7:$J$56,MATCH($A24,Checks!$A$7:$A$56,0)),""),"") -> Unused slot
A25: C019 | M25: =IF(COUNTIFS(Checks!$A$7:$A$56,$A25,Checks!$J$7:$J$56,"<>")=1,IFERROR(INDEX(Checks!$J$7:$J$56,MATCH($A25,Checks!$A$7:$A$56,0)),""),"") -> Unused slot
A26: C020 | M26: =IF(COUNTIFS(Checks!$A$7:$A$56,$A26,Checks!$J$7:$J$56,"<>")=1,IFERROR(INDEX(Checks!$J$7:$J$56,MATCH($A26,Checks!$A$7:$A$56,0)),""),"") -> Unused slot
A27: C021 | M27: =IF(COUNTIFS(Checks!$A$7:$A$56,$A27,Checks!$J$7:$J$56,"<>")=1,IFERROR(INDEX(Checks!$J$7:$J$56,MATCH($A27,Checks!$A$7:$A$56,0)),""),"") -> Unused slot
A28: C022 | M28: =IF(COUNTIFS(Checks!$A$7:$A$56,$A28,Checks!$J$7:$J$56,"<>")=1,IFERROR(INDEX(Checks!$J$7:$J$56,MATCH($A28,Checks!$A$7:$A$56,0)),""),"") -> Unused slot
A29: C023 | M29: =IF(COUNTIFS(Checks!$A$7:$A$56,$A29,Checks!$J$7:$J$56,"<>")=1,IFERROR(INDEX(Checks!$J$7:$J$56,MATCH($A29,Checks!$A$7:$A$56,0)),""),"") -> Unused slot
... A56: C050 | M56: =IF(COUNTIFS(Checks!$A$7:$A$56,$A56,Checks!$J$7:$J$56,"<>")=1,IFERROR(INDEX(Checks!$J$7:$J$56,MATCH($A56,Checks!$A$7:$A$56,0)),""),"") -> Unused slot

Sheet Challenge Review
A1: 03b Challenge the proposal
A3: Answer Yes only after checking. No or an unresolved concern blocks planning. Unchecked is not approval. Review the purpose, rare failures and skills—not just the arithmetic.
A5: =IFERROR(HYPERLINK("#'Start'!A1","← Start"),"← Start") -> ← Start
A6: Case ID | B6: Reviewer | C6: Review date | D6: Protection purpose checked | E6: Full alternative cost checked | F6: Binding requirements checked | G6: Rare failures / defense depth checked | H6: Overlap / double count checked | I6: Capacity skills and timing checked | J6: Unresolved concern | K6: Review result
A7: C001 | D7: Unchecked | E7: Unchecked | F7: Unchecked | G7: Unchecked | H7: Unchecked | I7: Unchecked | K7: =IF(OR(COUNTIF(D7:I7,"No")>0,LEN(TRIM(J7))>0),"Blocked",IF(AND(COUNTIF(D7:I7,"Yes")=6,LEN(TRIM(B7))>0,ISNUMBER(C7),C7>0,C7<=Settings!$B$7),"Clear","Unchecked")) -> Unchecked
A8: C002 | D8: Unchecked | E8: Unchecked | F8: Unchecked | G8: Unchecked | H8: Unchecked | I8: Unchecked | K8: =IF(OR(COUNTIF(D8:I8,"No")>0,LEN(TRIM(J8))>0),"Blocked",IF(AND(COUNTIF(D8:I8,"Yes")=6,LEN(TRIM(B8))>0,ISNUMBER(C8),C8>0,C8<=Settings!$B$7),"Clear","Unchecked")) -> Unchecked
A9: C003 | D9: Unchecked | E9: Unchecked | F9: Unchecked | G9: Unchecked | H9: Unchecked | I9: Unchecked | K9: =IF(OR(COUNTIF(D9:I9,"No")>0,LEN(TRIM(J9))>0),"Blocked",IF(AND(COUNTIF(D9:I9,"Yes")=6,LEN(TRIM(B9))>0,ISNUMBER(C9),C9>0,C9<=Settings!$B$7),"Clear","Unchecked")) -> Unchecked
A10: C004 | D10: Unchecked | E10: Unchecked | F10: Unchecked | G10: Unchecked | H10: Unchecked | I10: Unchecked | K10: =IF(OR(COUNTIF(D10:I10,"No")>0,LEN(TRIM(J10))>0),"Blocked",IF(AND(COUNTIF(D10:I10,"Yes")=6,LEN(TRIM(B10))>0,ISNUMBER(C10),C10>0,C10<=Settings!$B$7),"Clear","Unchecked")) -> Unchecked
A11: C005 | D11: Unchecked | E11: Unchecked | F11: Unchecked | G11: Unchecked | H11: Unchecked | I11: Unchecked | K11: =IF(OR(COUNTIF(D11:I11,"No")>0,LEN(TRIM(J11))>0),"Blocked",IF(AND(COUNTIF(D11:I11,"Yes")=6,LEN(TRIM(B11))>0,ISNUMBER(C11),C11>0,C11<=Settings!$B$7),"Clear","Unchecked")) -> Unchecked
A12: C006 | D12: Unchecked | E12: Unchecked | F12: Unchecked | G12: Unchecked | H12: Unchecked | I12: Unchecked | K12: =IF(OR(COUNTIF(D12:I12,"No")>0,LEN(TRIM(J12))>0),"Blocked",IF(AND(COUNTIF(D12:I12,"Yes")=6,LEN(TRIM(B12))>0,ISNUMBER(C12),C12>0,C12<=Settings!$B$7),"Clear","Unchecked")) -> Unchecked
A13: C007 | D13: Unchecked | E13: Unchecked | F13: Unchecked | G13: Unchecked | H13: Unchecked | I13: Unchecked | K13: =IF(OR(COUNTIF(D13:I13,"No")>0,LEN(TRIM(J13))>0),"Blocked",IF(AND(COUNTIF(D13:I13,"Yes")=6,LEN(TRIM(B13))>0,ISNUMBER(C13),C13>0,C13<=Settings!$B$7),"Clear","Unchecked")) -> Unchecked
A14: C008 | D14: Unchecked | E14: Unchecked | F14: Unchecked | G14: Unchecked | H14: Unchecked | I14: Unchecked | K14: =IF(OR(COUNTIF(D14:I14,"No")>0,LEN(TRIM(J14))>0),"Blocked",IF(AND(COUNTIF(D14:I14,"Yes")=6,LEN(TRIM(B14))>0,ISNUMBER(C14),C14>0,C14<=Settings!$B$7),"Clear","Unchecked")) -> Unchecked
A15: C009 | D15: Unchecked | E15: Unchecked | F15: Unchecked | G15: Unchecked | H15: Unchecked | I15: Unchecked | K15: =IF(OR(COUNTIF(D15:I15,"No")>0,LEN(TRIM(J15))>0),"Blocked",IF(AND(COUNTIF(D15:I15,"Yes")=6,LEN(TRIM(B15))>0,ISNUMBER(C15),C15>0,C15<=Settings!$B$7),"Clear","Unchecked")) -> Unchecked
A16: C010 | D16: Unchecked | E16: Unchecked | F16: Unchecked | G16: Unchecked | H16: Unchecked | I16: Unchecked | K16: =IF(OR(COUNTIF(D16:I16,"No")>0,LEN(TRIM(J16))>0),"Blocked",IF(AND(COUNTIF(D16:I16,"Yes")=6,LEN(TRIM(B16))>0,ISNUMBER(C16),C16>0,C16<=Settings!$B$7),"Clear","Unchecked")) -> Unchecked
A17: C011 | D17: Unchecked | E17: Unchecked | F17: Unchecked | G17: Unchecked | H17: Unchecked | I17: Unchecked | K17: =IF(OR(COUNTIF(D17:I17,"No")>0,LEN(TRIM(J17))>0),"Blocked",IF(AND(COUNTIF(D17:I17,"Yes")=6,LEN(TRIM(B17))>0,ISNUMBER(C17),C17>0,C17<=Settings!$B$7),"Clear","Unchecked")) -> Unchecked
A18: C012 | D18: Unchecked | E18: Unchecked | F18: Unchecked | G18: Unchecked | H18: Unchecked | I18: Unchecked | K18: =IF(OR(COUNTIF(D18:I18,"No")>0,LEN(TRIM(J18))>0),"Blocked",IF(AND(COUNTIF(D18:I18,"Yes")=6,LEN(TRIM(B18))>0,ISNUMBER(C18),C18>0,C18<=Settings!$B$7),"Clear","Unchecked")) -> Unchecked
... A56: C050 | D56: Unchecked | E56: Unchecked | F56: Unchecked | G56: Unchecked | H56: Unchecked | I56: Unchecked | K56: =IF(OR(COUNTIF(D56:I56,"No")>0,LEN(TRIM(J56))>0),"Blocked",IF(AND(COUNTIF(D56:I56,"Yes")=6,LEN(TRIM(B56))>0,ISNUMBER(C56),C56>0,C56<=Settings!$B$7),"Clear","Unchecked")) -> Unchecked

Sheet Actuals
A1: 04 Record measured results
A3: Enter signed annual changes, not forecast values. Positive means released time / lower cash spend. Store fixed measurements, a period, evidence and verification; forecasts never overwrite these.
A5: =IFERROR(HYPERLINK("#'Start'!A1","← Start"),"← Start") -> ← Start
A6: Case ID | B6: Measurement basis | C6: Period start | D6: Period end | E6: Business hours saved / year | F6: Specialist hours saved / year | G6: Recurring cash change €/year | H6: Labor-value change €/year • excludes cash | I6: Measurement evidence | J6: Verified by | K6: Verification date | L6: Normalization / comparison basis | M6: Measurement status
A7: C001 | M7: =IF(AND(OR(B7="Full-year actual",B7="Annualized measurement"),COUNT(C7:H7)=6,C7>0,D7>=C7,D7<=Settings!$B$7,OR(B7="Annualized measurement",D7-C7+1>=365),LEN(TRIM(I7))>0,LEN(TRIM(J7))>0,ISNUMBER(K7),K7>=D7,K7<=Settings!$B$7,LEN(TRIM(L7))>0),"Ready","Measurements incomplete") -> Measurements incomplete
A8: C002 | M8: =IF(AND(OR(B8="Full-year actual",B8="Annualized measurement"),COUNT(C8:H8)=6,C8>0,D8>=C8,D8<=Settings!$B$7,OR(B8="Annualized measurement",D8-C8+1>=365),LEN(TRIM(I8))>0,LEN(TRIM(J8))>0,ISNUMBER(K8),K8>=D8,K8<=Settings!$B$7,LEN(TRIM(L8))>0),"Ready","Measurements incomplete") -> Measurements incomplete
A9: C003 | M9: =IF(AND(OR(B9="Full-year actual",B9="Annualized measurement"),COUNT(C9:H9)=6,C9>0,D9>=C9,D9<=Settings!$B$7,OR(B9="Annualized measurement",D9-C9+1>=365),LEN(TRIM(I9))>0,LEN(TRIM(J9))>0,ISNUMBER(K9),K9>=D9,K9<=Settings!$B$7,LEN(TRIM(L9))>0),"Ready","Measurements incomplete") -> Measurements incomplete
A10: C004 | M10: =IF(AND(OR(B10="Full-year actual",B10="Annualized measurement"),COUNT(C10:H10)=6,C10>0,D10>=C10,D10<=Settings!$B$7,OR(B10="Annualized measurement",D10-C10+1>=365),LEN(TRIM(I10))>0,LEN(TRIM(J10))>0,ISNUMBER(K10),K10>=D10,K10<=Settings!$B$7,LEN(TRIM(L10))>0),"Ready","Measurements incomplete") -> Measurements incomplete
A11: C005 | M11: =IF(AND(OR(B11="Full-year actual",B11="Annualized measurement"),COUNT(C11:H11)=6,C11>0,D11>=C11,D11<=Settings!$B$7,OR(B11="Annualized measurement",D11-C11+1>=365),LEN(TRIM(I11))>0,LEN(TRIM(J11))>0,ISNUMBER(K11),K11>=D11,K11<=Settings!$B$7,LEN(TRIM(L11))>0),"Ready","Measurements incomplete") -> Measurements incomplete
A12: C006 | M12: =IF(AND(OR(B12="Full-year actual",B12="Annualized measurement"),COUNT(C12:H12)=6,C12>0,D12>=C12,D12<=Settings!$B$7,OR(B12="Annualized measurement",D12-C12+1>=365),LEN(TRIM(I12))>0,LEN(TRIM(J12))>0,ISNUMBER(K12),K12>=D12,K12<=Settings!$B$7,LEN(TRIM(L12))>0),"Ready","Measurements incomplete") -> Measurements incomplete
A13: C007 | M13: =IF(AND(OR(B13="Full-year actual",B13="Annualized measurement"),COUNT(C13:H13)=6,C13>0,D13>=C13,D13<=Settings!$B$7,OR(B13="Annualized measurement",D13-C13+1>=365),LEN(TRIM(I13))>0,LEN(TRIM(J13))>0,ISNUMBER(K13),K13>=D13,K13<=Settings!$B$7,LEN(TRIM(L13))>0),"Ready","Measurements incomplete") -> Measurements incomplete
A14: C008 | M14: =IF(AND(OR(B14="Full-year actual",B14="Annualized measurement"),COUNT(C14:H14)=6,C14>0,D14>=C14,D14<=Settings!$B$7,OR(B14="Annualized measurement",D14-C14+1>=365),LEN(TRIM(I14))>0,LEN(TRIM(J14))>0,ISNUMBER(K14),K14>=D14,K14<=Settings!$B$7,LEN(TRIM(L14))>0),"Ready","Measurements incomplete") -> Measurements incomplete
A15: C009 | M15: =IF(AND(OR(B15="Full-year actual",B15="Annualized measurement"),COUNT(C15:H15)=6,C15>0,D15>=C15,D15<=Settings!$B$7,OR(B15="Annualized measurement",D15-C15+1>=365),LEN(TRIM(I15))>0,LEN(TRIM(J15))>0,ISNUMBER(K15),K15>=D15,K15<=Settings!$B$7,LEN(TRIM(L15))>0),"Ready","Measurements incomplete") -> Measurements incomplete
A16: C010 | M16: =IF(AND(OR(B16="Full-year actual",B16="Annualized measurement"),COUNT(C16:H16)=6,C16>0,D16>=C16,D16<=Settings!$B$7,OR(B16="Annualized measurement",D16-C16+1>=365),LEN(TRIM(I16))>0,LEN(TRIM(J16))>0,ISNUMBER(K16),K16>=D16,K16<=Settings!$B$7,LEN(TRIM(L16))>0),"Ready","Measurements incomplete") -> Measurements incomplete
A17: C011 | M17: =IF(AND(OR(B17="Full-year actual",B17="Annualized measurement"),COUNT(C17:H17)=6,C17>0,D17>=C17,D17<=Settings!$B$7,OR(B17="Annualized measurement",D17-C17+1>=365),LEN(TRIM(I17))>0,LEN(TRIM(J17))>0,ISNUMBER(K17),K17>=D17,K17<=Settings!$B$7,LEN(TRIM(L17))>0),"Ready","Measurements incomplete") -> Measurements incomplete
A18: C012 | M18: =IF(AND(OR(B18="Full-year actual",B18="Annualized measurement"),COUNT(C18:H18)=6,C18>0,D18>=C18,D18<=Settings!$B$7,OR(B18="Annualized measurement",D18-C18+1>=365),LEN(TRIM(I18))>0,LEN(TRIM(J18))>0,ISNUMBER(K18),K18>=D18,K18<=Settings!$B$7,LEN(TRIM(L18))>0),"Ready","Measurements incomplete") -> Measurements incomplete
... A56: C050 | M56: =IF(AND(OR(B56="Full-year actual",B56="Annualized measurement"),COUNT(C56:H56)=6,C56>0,D56>=C56,D56<=Settings!$B$7,OR(B56="Annualized measurement",D56-C56+1>=365),LEN(TRIM(I56))>0,LEN(TRIM(J56))>0,ISNUMBER(K56),K56>=D56,K56<=Settings!$B$7,LEN(TRIM(L56))>0),"Ready","Measurements incomplete") -> Measurements incomplete

Sheet Reinvestment
A1: 05 Reinvestment and funding
A3: Planning supply is live, approved and gated. Cash is never substituted by the euro value of time. Positive hours must match the destination's skills and timing.
A5: =IFERROR(HYPERLINK("#'Start'!A1","← Start"),"← Start") -> ← Start
A7: Selected planning basis and resource balance
A8: Planning basis | C8: =Settings!B8 -> Approved + measured
A10: Resource | E10: Eligible supply | G10: Additional demand | I10: Balance / funding need
A11: Business hours / year | E11: =SUM(Checks!AA7:AA56) -> 0 | G11: =SUM(M31:M50) -> 0 | I11: =E11-G11 -> 0
A12: Specialist-team hours / year | E12: =SUM(Checks!AB7:AB56) -> 0 | G12: =SUM(N31:N50) -> 0 | I12: =E12-G12 -> 0
A13: Recurring cash / year | E13: =SUM(Checks!AC7:AC56) -> 0 | G13: =SUM(O31:O50) -> 0 | I13: =E13-G13 -> 0
A14: One-time funding required | E14: =SUM(Checks!AD7:AD56) -> 0 | G14: =SUM(P31:P50) -> 0 | I14: =E14+G14 -> 0
A16: =IF(OR(COUNTIF(L31:L50,"Complete approved demand")>0,COUNTIF(L31:L50,"Duplicate overlap — counted")>0,COUNTIF(L31:L50,"Fix demand type")>0),"Resolve incomplete demands or duplicate overlap claims before relying on coverage.",IF(AND(SUM(Checks!M7:M56)=0,COUNTIF(L31:L50,"Count as extra demand")=0),"No eligible live supply or approved live demand. Examples do not fund the plan.",IF(AND(I11>=0,I12>=0,I13>=0),"Recurring resource totals balance. Confirm skill, timing and separate one-time funding.","Resource gap: inspect business hours, specialist hours and cash separately."))) -> No eligible live supply or approved live demand. Examples do not fund the plan.
A20: Cash balance is recurring cash only. A positive time-valued benefit cannot finance a negative cash balance. One-time funding is separate. Forecast hours are not already released capacity; even measured hours require a realistic redeployment plan. A linked overlap is counted as extra demand until its source case enters this planning view.
A25: =IFERROR(HYPERLINK("#'Reinvestment'!A30","Enter / review demands below ↓"),"Enter / review demands below ↓") -> Enter / review demands below ↓
A30: Demand ID | B30: Demand type | C30: Initiative | D30: Decision | E30: Business h/year | F30: Specialist h/year | G30: Recurring cash €/year | H30: One-time cost € | I30: Linked case ID | J30: Already in case estimate? | K30: Cost / overlap / resource-fit reference | L30: Treatment • calculated | M30: Extra business h | N30: Extra specialist h | O30: Extra cash €/year | P30: Extra one-time €
A31: R001 | B31: Example | C31: Critical-service recovery rehearsal | D31: Draft | E31: 0 | F31: 240 | G31: 5000 | H31: 5000 | J31: No | K31: Example demand. Match recovery engineering capacity; not live funding. | L31: =IF(B31="Inactive","Unused",IF(B31="Example","Example only",IF(B31<>"Live","Fix demand type",IF(D31<>"Approved","Not approved",IF(NOT(AND(LEN(TRIM(C31))>0,COUNT(E31:H31)=4,MIN(E31:H31)>=0,OR(J31="Yes",J31="No"),LEN(TRIM(K31))>0,COUNTIF($A$31:$A$50,A31)=1)),"Complete approved demand",IF(AND(J31="Yes",COUNTIFS($I$31:$I$50,I31,$J$31:$J$50,"Yes",$B$31:$B$50,"Live",$D$31:$D$50,"Approved")>1),"Duplicate overlap — counted",IF(AND(J31="Yes",AND(LEN(TRIM(I31))>0,COUNTIF(Checks!$A$7:$A$56,$I31)=1,IFERROR(INDEX(Checks!$M$7:$M$56,MATCH($I31,Checks!$A$7:$A$56,0)),"")=1)),"Included in eligible case","Count as extra demand"))))))) -> Example only | M31: =IF(OR(L31="Count as extra demand",L31="Duplicate overlap — counted"),E31,0) -> 0 | N31: =IF(OR(L31="Count as extra demand",L31="Duplicate overlap — counted"),F31,0) -> 0 | O31: =IF(OR(L31="Count as extra demand",L31="Duplicate overlap — counted"),G31,0) -> 0 | P31: =IF(OR(L31="Count as extra demand",L31="Duplicate overlap — counted"),H31,0) -> 0
A32: R002 | B32: Example | C32: Identity hardening and privileged access | D32: Draft | E32: 100 | F32: 240 | G32: 20000 | H32: 10000 | J32: No | K32: Example demand. Confirm identity engineering availability. | L32: =IF(B32="Inactive","Unused",IF(B32="Example","Example only",IF(B32<>"Live","Fix demand type",IF(D32<>"Approved","Not approved",IF(NOT(AND(LEN(TRIM(C32))>0,COUNT(E32:H32)=4,MIN(E32:H32)>=0,OR(J32="Yes",J32="No"),LEN(TRIM(K32))>0,COUNTIF($A$31:$A$50,A32)=1)),"Complete approved demand",IF(AND(J32="Yes",COUNTIFS($I$31:$I$50,I32,$J$31:$J$50,"Yes",$B$31:$B$50,"Live",$D$31:$D$50,"Approved")>1),"Duplicate overlap — counted",IF(AND(J32="Yes",AND(LEN(TRIM(I32))>0,COUNTIF(Checks!$A$7:$A$56,$I32)=1,IFERROR(INDEX(Checks!$M$7:$M$56,MATCH($I32,Checks!$A$7:$A$56,0)),"")=1)),"Included in eligible case","Count as extra demand"))))))) -> Example only | M32: =IF(OR(L32="Count as extra demand",L32="Duplicate overlap — counted"),E32,0) -> 0 | N32: =IF(OR(L32="Count as extra demand",L32="Duplicate overlap — counted"),F32,0) -> 0 | O32: =IF(OR(L32="Count as extra demand",L32="Duplicate overlap — counted"),G32,0) -> 0 | P32: =IF(OR(L32="Count as extra demand",L32="Duplicate overlap — counted"),H32,0) -> 0
A33: R003 | B33: Example | C33: Supplier access and dependency review | D33: Draft | E33: 0 | F33: 160 | G33: 10000 | H33: 3000 | J33: No | K33: Example demand. Confirm procurement and security ownership. | L33: =IF(B33="Inactive","Unused",IF(B33="Example","Example only",IF(B33<>"Live","Fix demand type",IF(D33<>"Approved","Not approved",IF(NOT(AND(LEN(TRIM(C33))>0,COUNT(E33:H33)=4,MIN(E33:H33)>=0,OR(J33="Yes",J33="No"),LEN(TRIM(K33))>0,COUNTIF($A$31:$A$50,A33)=1)),"Complete approved demand",IF(AND(J33="Yes",COUNTIFS($I$31:$I$50,I33,$J$31:$J$50,"Yes",$B$31:$B$50,"Live",$D$31:$D$50,"Approved")>1),"Duplicate overlap — counted",IF(AND(J33="Yes",AND(LEN(TRIM(I33))>0,COUNTIF(Checks!$A$7:$A$56,$I33)=1,IFERROR(INDEX(Checks!$M$7:$M$56,MATCH($I33,Checks!$A$7:$A$56,0)),"")=1)),"Included in eligible case","Count as extra demand"))))))) -> Example only | M33: =IF(OR(L33="Count as extra demand",L33="Duplicate overlap — counted"),E33,0) -> 0 | N33: =IF(OR(L33="Count as extra demand",L33="Duplicate overlap — counted"),F33,0) -> 0 | O33: =IF(OR(L33="Count as extra demand",L33="Duplicate overlap — counted"),G33,0) -> 0 | P33: =IF(OR(L33="Count as extra demand",L33="Duplicate overlap — counted"),H33,0) -> 0
A34: R004 | B34: Example | C34: Joiner / mover / leaver automation | D34: Draft | E34: 0 | F34: 40 | G34: 15000 | H34: 25000 | I34: C004 | J34: Yes | K34: Example bundled overlap with access-review replacement. Exclusion needs eligible live C004. | L34: =IF(B34="Inactive","Unused",IF(B34="Example","Example only",IF(B34<>"Live","Fix demand type",IF(D34<>"Approved","Not approved",IF(NOT(AND(LEN(TRIM(C34))>0,COUNT(E34:H34)=4,MIN(E34:H34)>=0,OR(J34="Yes",J34="No"),LEN(TRIM(K34))>0,COUNTIF($A$31:$A$50,A34)=1)),"Complete approved demand",IF(AND(J34="Yes",COUNTIFS($I$31:$I$50,I34,$J$31:$J$50,"Yes",$B$31:$B$50,"Live",$D$31:$D$50,"Approved")>1),"Duplicate overlap — counted",IF(AND(J34="Yes",AND(LEN(TRIM(I34))>0,COUNTIF(Checks!$A$7:$A$56,$I34)=1,IFERROR(INDEX(Checks!$M$7:$M$56,MATCH($I34,Checks!$A$7:$A$56,0)),"")=1)),"Included in eligible case","Count as extra demand"))))))) -> Example only | M34: =IF(OR(L34="Count as extra demand",L34="Duplicate overlap — counted"),E34,0) -> 0 | N34: =IF(OR(L34="Count as extra demand",L34="Duplicate overlap — counted"),F34,0) -> 0 | O34: =IF(OR(L34="Count as extra demand",L34="Duplicate overlap — counted"),G34,0) -> 0 | P34: =IF(OR(L34="Count as extra demand",L34="Duplicate overlap — counted"),H34,0) -> 0
A35: R005 | B35: Example | C35: Detection and response improvement | D35: Draft | E35: 100 | F35: 220 | G35: 17000 | H35: 5000 | J35: No | K35: Example demand. Confirm analyst skill and operating coverage. | L35: =IF(B35="Inactive","Unused",IF(B35="Example","Example only",IF(B35<>"Live","Fix demand type",IF(D35<>"Approved","Not approved",IF(NOT(AND(LEN(TRIM(C35))>0,COUNT(E35:H35)=4,MIN(E35:H35)>=0,OR(J35="Yes",J35="No"),LEN(TRIM(K35))>0,COUNTIF($A$31:$A$50,A35)=1)),"Complete approved demand",IF(AND(J35="Yes",COUNTIFS($I$31:$I$50,I35,$J$31:$J$50,"Yes",$B$31:$B$50,"Live",$D$31:$D$50,"Approved")>1),"Duplicate overlap — counted",IF(AND(J35="Yes",AND(LEN(TRIM(I35))>0,COUNTIF(Checks!$A$7:$A$56,$I35)=1,IFERROR(INDEX(Checks!$M$7:$M$56,MATCH($I35,Checks!$A$7:$A$56,0)),"")=1)),"Included in eligible case","Count as extra demand"))))))) -> Example only | M35: =IF(OR(L35="Count as extra demand",L35="Duplicate overlap — counted"),E35,0) -> 0 | N35: =IF(OR(L35="Count as extra demand",L35="Duplicate overlap — counted"),F35,0) -> 0 | O35: =IF(OR(L35="Count as extra demand",L35="Duplicate overlap — counted"),G35,0) -> 0 | P35: =IF(OR(L35="Count as extra demand",L35="Duplicate overlap — counted"),H35,0) -> 0
A36: R006 | B36: Inactive | L36: =IF(B36="Inactive","Unused",IF(B36="Example","Example only",IF(B36<>"Live","Fix demand type",IF(D36<>"Approved","Not approved",IF(NOT(AND(LEN(TRIM(C36))>0,COUNT(E36:H36)=4,MIN(E36:H36)>=0,OR(J36="Yes",J36="No"),LEN(TRIM(K36))>0,COUNTIF($A$31:$A$50,A36)=1)),"Complete approved demand",IF(AND(J36="Yes",COUNTIFS($I$31:$I$50,I36,$J$31:$J$50,"Yes",$B$31:$B$50,"Live",$D$31:$D$50,"Approved")>1),"Duplicate overlap — counted",IF(AND(J36="Yes",AND(LEN(TRIM(I36))>0,COUNTIF(Checks!$A$7:$A$56,$I36)=1,IFERROR(INDEX(Checks!$M$7:$M$56,MATCH($I36,Checks!$A$7:$A$56,0)),"")=1)),"Included in eligible case","Count as extra demand"))))))) -> Unused | M36: =IF(OR(L36="Count as extra demand",L36="Duplicate overlap — counted"),E36,0) -> 0 | N36: =IF(OR(L36="Count as extra demand",L36="Duplicate overlap — counted"),F36,0) -> 0 | O36: =IF(OR(L36="Count as extra demand",L36="Duplicate overlap — counted"),G36,0) -> 0 | P36: =IF(OR(L36="Count as extra demand",L36="Duplicate overlap — counted"),H36,0) -> 0
A37: R007 | B37: Inactive | L37: =IF(B37="Inactive","Unused",IF(B37="Example","Example only",IF(B37<>"Live","Fix demand type",IF(D37<>"Approved","Not approved",IF(NOT(AND(LEN(TRIM(C37))>0,COUNT(E37:H37)=4,MIN(E37:H37)>=0,OR(J37="Yes",J37="No"),LEN(TRIM(K37))>0,COUNTIF($A$31:$A$50,A37)=1)),"Complete approved demand",IF(AND(J37="Yes",COUNTIFS($I$31:$I$50,I37,$J$31:$J$50,"Yes",$B$31:$B$50,"Live",$D$31:$D$50,"Approved")>1),"Duplicate overlap — counted",IF(AND(J37="Yes",AND(LEN(TRIM(I37))>0,COUNTIF(Checks!$A$7:$A$56,$I37)=1,IFERROR(INDEX(Checks!$M$7:$M$56,MATCH($I37,Checks!$A$7:$A$56,0)),"")=1)),"Included in eligible case","Count as extra demand"))))))) -> Unused | M37: =IF(OR(L37="Count as extra demand",L37="Duplicate overlap — counted"),E37,0) -> 0 | N37: =IF(OR(L37="Count as extra demand",L37="Duplicate overlap — counted"),F37,0) -> 0 | O37: =IF(OR(L37="Count as extra demand",L37="Duplicate overlap — counted"),G37,0) -> 0 | P37: =IF(OR(L37="Count as extra demand",L37="Duplicate overlap — counted"),H37,0) -> 0
A38: R008 | B38: Inactive | L38: =IF(B38="Inactive","Unused",IF(B38="Example","Example only",IF(B38<>"Live","Fix demand type",IF(D38<>"Approved","Not approved",IF(NOT(AND(LEN(TRIM(C38))>0,COUNT(E38:H38)=4,MIN(E38:H38)>=0,OR(J38="Yes",J38="No"),LEN(TRIM(K38))>0,COUNTIF($A$31:$A$50,A38)=1)),"Complete approved demand",IF(AND(J38="Yes",COUNTIFS($I$31:$I$50,I38,$J$31:$J$50,"Yes",$B$31:$B$50,"Live",$D$31:$D$50,"Approved")>1),"Duplicate overlap — counted",IF(AND(J38="Yes",AND(LEN(TRIM(I38))>0,COUNTIF(Checks!$A$7:$A$56,$I38)=1,IFERROR(INDEX(Checks!$M$7:$M$56,MATCH($I38,Checks!$A$7:$A$56,0)),"")=1)),"Included in eligible case","Count as extra demand"))))))) -> Unused | M38: =IF(OR(L38="Count as extra demand",L38="Duplicate overlap — counted"),E38,0) -> 0 | N38: =IF(OR(L38="Count as extra demand",L38="Duplicate overlap — counted"),F38,0) -> 0 | O38: =IF(OR(L38="Count as extra demand",L38="Duplicate overlap — counted"),G38,0) -> 0 | P38: =IF(OR(L38="Count as extra demand",L38="Duplicate overlap — counted"),H38,0) -> 0
A39: R009 | B39: Inactive | L39: =IF(B39="Inactive","Unused",IF(B39="Example","Example only",IF(B39<>"Live","Fix demand type",IF(D39<>"Approved","Not approved",IF(NOT(AND(LEN(TRIM(C39))>0,COUNT(E39:H39)=4,MIN(E39:H39)>=0,OR(J39="Yes",J39="No"),LEN(TRIM(K39))>0,COUNTIF($A$31:$A$50,A39)=1)),"Complete approved demand",IF(AND(J39="Yes",COUNTIFS($I$31:$I$50,I39,$J$31:$J$50,"Yes",$B$31:$B$50,"Live",$D$31:$D$50,"Approved")>1),"Duplicate overlap — counted",IF(AND(J39="Yes",AND(LEN(TRIM(I39))>0,COUNTIF(Checks!$A$7:$A$56,$I39)=1,IFERROR(INDEX(Checks!$M$7:$M$56,MATCH($I39,Checks!$A$7:$A$56,0)),"")=1)),"Included in eligible case","Count as extra demand"))))))) -> Unused | M39: =IF(OR(L39="Count as extra demand",L39="Duplicate overlap — counted"),E39,0) -> 0 | N39: =IF(OR(L39="Count as extra demand",L39="Duplicate overlap — counted"),F39,0) -> 0 | O39: =IF(OR(L39="Count as extra demand",L39="Duplicate overlap — counted"),G39,0) -> 0 | P39: =IF(OR(L39="Count as extra demand",L39="Duplicate overlap — counted"),H39,0) -> 0
A40: R010 | B40: Inactive | L40: =IF(B40="Inactive","Unused",IF(B40="Example","Example only",IF(B40<>"Live","Fix demand type",IF(D40<>"Approved","Not approved",IF(NOT(AND(LEN(TRIM(C40))>0,COUNT(E40:H40)=4,MIN(E40:H40)>=0,OR(J40="Yes",J40="No"),LEN(TRIM(K40))>0,COUNTIF($A$31:$A$50,A40)=1)),"Complete approved demand",IF(AND(J40="Yes",COUNTIFS($I$31:$I$50,I40,$J$31:$J$50,"Yes",$B$31:$B$50,"Live",$D$31:$D$50,"Approved")>1),"Duplicate overlap — counted",IF(AND(J40="Yes",AND(LEN(TRIM(I40))>0,COUNTIF(Checks!$A$7:$A$56,$I40)=1,IFERROR(INDEX(Checks!$M$7:$M$56,MATCH($I40,Checks!$A$7:$A$56,0)),"")=1)),"Included in eligible case","Count as extra demand"))))))) -> Unused | M40: =IF(OR(L40="Count as extra demand",L40="Duplicate overlap — counted"),E40,0) -> 0 | N40: =IF(OR(L40="Count as extra demand",L40="Duplicate overlap — counted"),F40,0) -> 0 | O40: =IF(OR(L40="Count as extra demand",L40="Duplicate overlap — counted"),G40,0) -> 0 | P40: =IF(OR(L40="Count as extra demand",L40="Duplicate overlap — counted"),H40,0) -> 0
A41: R011 | B41: Inactive | L41: =IF(B41="Inactive","Unused",IF(B41="Example","Example only",IF(B41<>"Live","Fix demand type",IF(D41<>"Approved","Not approved",IF(NOT(AND(LEN(TRIM(C41))>0,COUNT(E41:H41)=4,MIN(E41:H41)>=0,OR(J41="Yes",J41="No"),LEN(TRIM(K41))>0,COUNTIF($A$31:$A$50,A41)=1)),"Complete approved demand",IF(AND(J41="Yes",COUNTIFS($I$31:$I$50,I41,$J$31:$J$50,"Yes",$B$31:$B$50,"Live",$D$31:$D$50,"Approved")>1),"Duplicate overlap — counted",IF(AND(J41="Yes",AND(LEN(TRIM(I41))>0,COUNTIF(Checks!$A$7:$A$56,$I41)=1,IFERROR(INDEX(Checks!$M$7:$M$56,MATCH($I41,Checks!$A$7:$A$56,0)),"")=1)),"Included in eligible case","Count as extra demand"))))))) -> Unused | M41: =IF(OR(L41="Count as extra demand",L41="Duplicate overlap — counted"),E41,0) -> 0 | N41: =IF(OR(L41="Count as extra demand",L41="Duplicate overlap — counted"),F41,0) -> 0 | O41: =IF(OR(L41="Count as extra demand",L41="Duplicate overlap — counted"),G41,0) -> 0 | P41: =IF(OR(L41="Count as extra demand",L41="Duplicate overlap — counted"),H41,0) -> 0
A42: R012 | B42: Inactive | L42: =IF(B42="Inactive","Unused",IF(B42="Example","Example only",IF(B42<>"Live","Fix demand type",IF(D42<>"Approved","Not approved",IF(NOT(AND(LEN(TRIM(C42))>0,COUNT(E42:H42)=4,MIN(E42:H42)>=0,OR(J42="Yes",J42="No"),LEN(TRIM(K42))>0,COUNTIF($A$31:$A$50,A42)=1)),"Complete approved demand",IF(AND(J42="Yes",COUNTIFS($I$31:$I$50,I42,$J$31:$J$50,"Yes",$B$31:$B$50,"Live",$D$31:$D$50,"Approved")>1),"Duplicate overlap — counted",IF(AND(J42="Yes",AND(LEN(TRIM(I42))>0,COUNTIF(Checks!$A$7:$A$56,$I42)=1,IFERROR(INDEX(Checks!$M$7:$M$56,MATCH($I42,Checks!$A$7:$A$56,0)),"")=1)),"Included in eligible case","Count as extra demand"))))))) -> Unused | M42: =IF(OR(L42="Count as extra demand",L42="Duplicate overlap — counted"),E42,0) -> 0 | N42: =IF(OR(L42="Count as extra demand",L42="Duplicate overlap — counted"),F42,0) -> 0 | O42: =IF(OR(L42="Count as extra demand",L42="Duplicate overlap — counted"),G42,0) -> 0 | P42: =IF(OR(L42="Count as extra demand",L42="Duplicate overlap — counted"),H42,0) -> 0
A43: R013 | B43: Inactive | L43: =IF(B43="Inactive","Unused",IF(B43="Example","Example only",IF(B43<>"Live","Fix demand type",IF(D43<>"Approved","Not approved",IF(NOT(AND(LEN(TRIM(C43))>0,COUNT(E43:H43)=4,MIN(E43:H43)>=0,OR(J43="Yes",J43="No"),LEN(TRIM(K43))>0,COUNTIF($A$31:$A$50,A43)=1)),"Complete approved demand",IF(AND(J43="Yes",COUNTIFS($I$31:$I$50,I43,$J$31:$J$50,"Yes",$B$31:$B$50,"Live",$D$31:$D$50,"Approved")>1),"Duplicate overlap — counted",IF(AND(J43="Yes",AND(LEN(TRIM(I43))>0,COUNTIF(Checks!$A$7:$A$56,$I43)=1,IFERROR(INDEX(Checks!$M$7:$M$56,MATCH($I43,Checks!$A$7:$A$56,0)),"")=1)),"Included in eligible case","Count as extra demand"))))))) -> Unused | M43: =IF(OR(L43="Count as extra demand",L43="Duplicate overlap — counted"),E43,0) -> 0 | N43: =IF(OR(L43="Count as extra demand",L43="Duplicate overlap — counted"),F43,0) -> 0 | O43: =IF(OR(L43="Count as extra demand",L43="Duplicate overlap — counted"),G43,0) -> 0 | P43: =IF(OR(L43="Count as extra demand",L43="Duplicate overlap — counted"),H43,0) -> 0
A44: R014 | B44: Inactive | L44: =IF(B44="Inactive","Unused",IF(B44="Example","Example only",IF(B44<>"Live","Fix demand type",IF(D44<>"Approved","Not approved",IF(NOT(AND(LEN(TRIM(C44))>0,COUNT(E44:H44)=4,MIN(E44:H44)>=0,OR(J44="Yes",J44="No"),LEN(TRIM(K44))>0,COUNTIF($A$31:$A$50,A44)=1)),"Complete approved demand",IF(AND(J44="Yes",COUNTIFS($I$31:$I$50,I44,$J$31:$J$50,"Yes",$B$31:$B$50,"Live",$D$31:$D$50,"Approved")>1),"Duplicate overlap — counted",IF(AND(J44="Yes",AND(LEN(TRIM(I44))>0,COUNTIF(Checks!$A$7:$A$56,$I44)=1,IFERROR(INDEX(Checks!$M$7:$M$56,MATCH($I44,Checks!$A$7:$A$56,0)),"")=1)),"Included in eligible case","Count as extra demand"))))))) -> Unused | M44: =IF(OR(L44="Count as extra demand",L44="Duplicate overlap — counted"),E44,0) -> 0 | N44: =IF(OR(L44="Count as extra demand",L44="Duplicate overlap — counted"),F44,0) -> 0 | O44: =IF(OR(L44="Count as extra demand",L44="Duplicate overlap — counted"),G44,0) -> 0 | P44: =IF(OR(L44="Count as extra demand",L44="Duplicate overlap — counted"),H44,0) -> 0
A45: R015 | B45: Inactive | L45: =IF(B45="Inactive","Unused",IF(B45="Example","Example only",IF(B45<>"Live","Fix demand type",IF(D45<>"Approved","Not approved",IF(NOT(AND(LEN(TRIM(C45))>0,COUNT(E45:H45)=4,MIN(E45:H45)>=0,OR(J45="Yes",J45="No"),LEN(TRIM(K45))>0,COUNTIF($A$31:$A$50,A45)=1)),"Complete approved demand",IF(AND(J45="Yes",COUNTIFS($I$31:$I$50,I45,$J$31:$J$50,"Yes",$B$31:$B$50,"Live",$D$31:$D$50,"Approved")>1),"Duplicate overlap — counted",IF(AND(J45="Yes",AND(LEN(TRIM(I45))>0,COUNTIF(Checks!$A$7:$A$56,$I45)=1,IFERROR(INDEX(Checks!$M$7:$M$56,MATCH($I45,Checks!$A$7:$A$56,0)),"")=1)),"Included in eligible case","Count as extra demand"))))))) -> Unused | M45: =IF(OR(L45="Count as extra demand",L45="Duplicate overlap — counted"),E45,0) -> 0 | N45: =IF(OR(L45="Count as extra demand",L45="Duplicate overlap — counted"),F45,0) -> 0 | O45: =IF(OR(L45="Count as extra demand",L45="Duplicate overlap — counted"),G45,0) -> 0 | P45: =IF(OR(L45="Count as extra demand",L45="Duplicate overlap — counted"),H45,0) -> 0
A46: R016 | B46: Inactive | L46: =IF(B46="Inactive","Unused",IF(B46="Example","Example only",IF(B46<>"Live","Fix demand type",IF(D46<>"Approved","Not approved",IF(NOT(AND(LEN(TRIM(C46))>0,COUNT(E46:H46)=4,MIN(E46:H46)>=0,OR(J46="Yes",J46="No"),LEN(TRIM(K46))>0,COUNTIF($A$31:$A$50,A46)=1)),"Complete approved demand",IF(AND(J46="Yes",COUNTIFS($I$31:$I$50,I46,$J$31:$J$50,"Yes",$B$31:$B$50,"Live",$D$31:$D$50,"Approved")>1),"Duplicate overlap — counted",IF(AND(J46="Yes",AND(LEN(TRIM(I46))>0,COUNTIF(Checks!$A$7:$A$56,$I46)=1,IFERROR(INDEX(Checks!$M$7:$M$56,MATCH($I46,Checks!$A$7:$A$56,0)),"")=1)),"Included in eligible case","Count as extra demand"))))))) -> Unused | M46: =IF(OR(L46="Count as extra demand",L46="Duplicate overlap — counted"),E46,0) -> 0 | N46: =IF(OR(L46="Count as extra demand",L46="Duplicate overlap — counted"),F46,0) -> 0 | O46: =IF(OR(L46="Count as extra demand",L46="Duplicate overlap — counted"),G46,0) -> 0 | P46: =IF(OR(L46="Count as extra demand",L46="Duplicate overlap — counted"),H46,0) -> 0
A47: R017 | B47: Inactive | L47: =IF(B47="Inactive","Unused",IF(B47="Example","Example only",IF(B47<>"Live","Fix demand type",IF(D47<>"Approved","Not approved",IF(NOT(AND(LEN(TRIM(C47))>0,COUNT(E47:H47)=4,MIN(E47:H47)>=0,OR(J47="Yes",J47="No"),LEN(TRIM(K47))>0,COUNTIF($A$31:$A$50,A47)=1)),"Complete approved demand",IF(AND(J47="Yes",COUNTIFS($I$31:$I$50,I47,$J$31:$J$50,"Yes",$B$31:$B$50,"Live",$D$31:$D$50,"Approved")>1),"Duplicate overlap — counted",IF(AND(J47="Yes",AND(LEN(TRIM(I47))>0,COUNTIF(Checks!$A$7:$A$56,$I47)=1,IFERROR(INDEX(Checks!$M$7:$M$56,MATCH($I47,Checks!$A$7:$A$56,0)),"")=1)),"Included in eligible case","Count as extra demand"))))))) -> Unused | M47: =IF(OR(L47="Count as extra demand",L47="Duplicate overlap — counted"),E47,0) -> 0 | N47: =IF(OR(L47="Count as extra demand",L47="Duplicate overlap — counted"),F47,0) -> 0 | O47: =IF(OR(L47="Count as extra demand",L47="Duplicate overlap — counted"),G47,0) -> 0 | P47: =IF(OR(L47="Count as extra demand",L47="Duplicate overlap — counted"),H47,0) -> 0
... A50: R020 | B50: Inactive | L50: =IF(B50="Inactive","Unused",IF(B50="Example","Example only",IF(B50<>"Live","Fix demand type",IF(D50<>"Approved","Not approved",IF(NOT(AND(LEN(TRIM(C50))>0,COUNT(E50:H50)=4,MIN(E50:H50)>=0,OR(J50="Yes",J50="No"),LEN(TRIM(K50))>0,COUNTIF($A$31:$A$50,A50)=1)),"Complete approved demand",IF(AND(J50="Yes",COUNTIFS($I$31:$I$50,I50,$J$31:$J$50,"Yes",$B$31:$B$50,"Live",$D$31:$D$50,"Approved")>1),"Duplicate overlap — counted",IF(AND(J50="Yes",AND(LEN(TRIM(I50))>0,COUNTIF(Checks!$A$7:$A$56,$I50)=1,IFERROR(INDEX(Checks!$M$7:$M$56,MATCH($I50,Checks!$A$7:$A$56,0)),"")=1)),"Included in eligible case","Count as extra demand"))))))) -> Unused | M50: =IF(OR(L50="Count as extra demand",L50="Duplicate overlap — counted"),E50,0) -> 0 | N50: =IF(OR(L50="Count as extra demand",L50="Duplicate overlap — counted"),F50,0) -> 0 | O50: =IF(OR(L50="Count as extra demand",L50="Duplicate overlap — counted"),G50,0) -> 0 | P50: =IF(OR(L50="Count as extra demand",L50="Duplicate overlap — counted"),H50,0) -> 0

Sheet Classification
A1: Optional Classification diagnostic
A3: Ratios flag questions; they do not prove a control is useless. Rare high-impact cases, exports and obligations must still be examined in the main review.
A5: =IFERROR(HYPERLINK("#'Start'!A1","← Start"),"← Start") -> ← Start
A6: Case ID | B6: Dominant label share | C6: Label-dependent DLP share | D6: Default changed share | E6: Important exception / boundary | F6: Test evidence reference | G6: Next test / action | H6: Interpretation • calculated
A7: C001 | B7: 0.95 | C7: 0.05 | D7: 0.02 | E7: Test rare sensitive exports and changing recipients. | F7: Illustrative assumptions, not observed data. | G7: Compare manual vs context-based decisions on an independently reviewed sample. | H7: =IF(COUNT(B7:D7)=0,"Optional diagnostic",IF(OR(COUNT(B7:D7)<>3,MIN(B7:D7)<0,MAX(B7:D7)>1),"Complete valid ratios","Inspect marginal decisions and rare cases; ratios alone do not prove effectiveness.")) -> Inspect marginal decisions and rare cases; ratios alone do not prove effectiveness.
A8: C002 | H8: =IF(COUNT(B8:D8)=0,"Optional diagnostic",IF(OR(COUNT(B8:D8)<>3,MIN(B8:D8)<0,MAX(B8:D8)>1),"Complete valid ratios","Inspect marginal decisions and rare cases; ratios alone do not prove effectiveness.")) -> Optional diagnostic
A9: C003 | H9: =IF(COUNT(B9:D9)=0,"Optional diagnostic",IF(OR(COUNT(B9:D9)<>3,MIN(B9:D9)<0,MAX(B9:D9)>1),"Complete valid ratios","Inspect marginal decisions and rare cases; ratios alone do not prove effectiveness.")) -> Optional diagnostic
A10: C004 | H10: =IF(COUNT(B10:D10)=0,"Optional diagnostic",IF(OR(COUNT(B10:D10)<>3,MIN(B10:D10)<0,MAX(B10:D10)>1),"Complete valid ratios","Inspect marginal decisions and rare cases; ratios alone do not prove effectiveness.")) -> Optional diagnostic
A11: C005 | H11: =IF(COUNT(B11:D11)=0,"Optional diagnostic",IF(OR(COUNT(B11:D11)<>3,MIN(B11:D11)<0,MAX(B11:D11)>1),"Complete valid ratios","Inspect marginal decisions and rare cases; ratios alone do not prove effectiveness.")) -> Optional diagnostic
A12: C006 | H12: =IF(COUNT(B12:D12)=0,"Optional diagnostic",IF(OR(COUNT(B12:D12)<>3,MIN(B12:D12)<0,MAX(B12:D12)>1),"Complete valid ratios","Inspect marginal decisions and rare cases; ratios alone do not prove effectiveness.")) -> Optional diagnostic
A13: C007 | H13: =IF(COUNT(B13:D13)=0,"Optional diagnostic",IF(OR(COUNT(B13:D13)<>3,MIN(B13:D13)<0,MAX(B13:D13)>1),"Complete valid ratios","Inspect marginal decisions and rare cases; ratios alone do not prove effectiveness.")) -> Optional diagnostic
A14: C008 | H14: =IF(COUNT(B14:D14)=0,"Optional diagnostic",IF(OR(COUNT(B14:D14)<>3,MIN(B14:D14)<0,MAX(B14:D14)>1),"Complete valid ratios","Inspect marginal decisions and rare cases; ratios alone do not prove effectiveness.")) -> Optional diagnostic
A15: C009 | H15: =IF(COUNT(B15:D15)=0,"Optional diagnostic",IF(OR(COUNT(B15:D15)<>3,MIN(B15:D15)<0,MAX(B15:D15)>1),"Complete valid ratios","Inspect marginal decisions and rare cases; ratios alone do not prove effectiveness.")) -> Optional diagnostic
A16: C010 | H16: =IF(COUNT(B16:D16)=0,"Optional diagnostic",IF(OR(COUNT(B16:D16)<>3,MIN(B16:D16)<0,MAX(B16:D16)>1),"Complete valid ratios","Inspect marginal decisions and rare cases; ratios alone do not prove effectiveness.")) -> Optional diagnostic
A17: C011 | H17: =IF(COUNT(B17:D17)=0,"Optional diagnostic",IF(OR(COUNT(B17:D17)<>3,MIN(B17:D17)<0,MAX(B17:D17)>1),"Complete valid ratios","Inspect marginal decisions and rare cases; ratios alone do not prove effectiveness.")) -> Optional diagnostic
A18: C012 | H18: =IF(COUNT(B18:D18)=0,"Optional diagnostic",IF(OR(COUNT(B18:D18)<>3,MIN(B18:D18)<0,MAX(B18:D18)>1),"Complete valid ratios","Inspect marginal decisions and rare cases; ratios alone do not prove effectiveness.")) -> Optional diagnostic
A19: C013 | H19: =IF(COUNT(B19:D19)=0,"Optional diagnostic",IF(OR(COUNT(B19:D19)<>3,MIN(B19:D19)<0,MAX(B19:D19)>1),"Complete valid ratios","Inspect marginal decisions and rare cases; ratios alone do not prove effectiveness.")) -> Optional diagnostic
... A56: C050 | H56: =IF(COUNT(B56:D56)=0,"Optional diagnostic",IF(OR(COUNT(B56:D56)<>3,MIN(B56:D56)<0,MAX(B56:D56)>1),"Complete valid ratios","Inspect marginal decisions and rare cases; ratios alone do not prove effectiveness.")) -> Optional diagnostic

Sheet Settings
A1: Model settings
A3: Forecast assumptions only. Actual measurements are stored independently. Rate changes never rewrite measured results.
A5: =IFERROR(HYPERLINK("#'Start'!A1","← Start"),"← Start") -> ← Start
A6: Setting | B6: Value | C6: Units | D6: Meaning
A7: Planning as-of date | B7: 46318 | C7: date | D7: Cases dated later do not contribute to this planning view.
A8: Planning basis | B8: Approved + measured | C8: selection | D8: Approved forecasts are estimates, not already released capacity.
A9: Staff rate | B9: 60 | C9: €/hour | D9: Illustrative fully loaded rate; replace with a documented local assumption.
A10: Management rate | B10: 90 | C10: €/hour | D10: Illustrative fully loaded rate; replace with a documented local assumption.
A11: Specialist-team rate | B11: 75 | C11: €/hour | D11: Illustrative fully loaded rate; capacity still needs a matching skill profile.
A12: Supported case slots | B12: 50 | C12: cases | D12: 50 prepared IDs, including 11 examples. Do not append rows beyond the prepared capacity.
A15: Optional workload calculator — copy the result as a documented estimate
A17: Affected people | B17: 2000
A18: Events per person per year | B18: 1100
A19: Minutes per event | B19: 0.15
A20: Share requiring follow-up | B20: 0.01
A21: Extra minutes per follow-up | B21: 5
A22: Hours per year | B22: =IF(AND(COUNT(B17:B21)=5,MIN(B17:B21)>=0,B20<=1),B17*B18*(B19+B20*B21)/60,"") -> 7333.3333
A23: Example source | B23: Original classification assumptions
A25: Frequency is per person, not the organization-wide count. Example: 100 people × 4 events × 15 minutes = 100 hours/year. For daily events, multiply by working days first. Copy the calculated hours into Current or Proposed and record this basis. The helper is not linked to a case.

Sheet Guide
A1: User guide
A3: Begin with a small, concrete comparison. The objective is a better decision—not a larger assessment exercise.
A5: =IFERROR(HYPERLINK("#'Start'!A1","← Start"),"← Start") -> ← Start
A7: 1 Choose one case
A8: Open Case View and select C012, then use its edit links. In Cases, set Case type to Live. Define one activity in one process, its owner, the protection purpose and the exact proposal. Keep the ID unchanged. To try a worked example, change its inputs while retaining Case type = Example.
A13: 2 Estimate the current and proposed annual profiles
A14: Current and Proposed ask whose time is required, annual execution hours, extra specialist hours, recurring cash and the basis of the estimate. All numeric fields are required, even when the answer is zero. Specialist execution is counted as team time, not business time. Proposed means the full operating profile after the change: include unchanged work, fixed licenses, new operating effort and transition costs. Partial scope is described explicitly; do not multiply every cost by a remaining-share percentage. Use the optional Settings calculator when events are easier to estimate than annual hours.
A21: 3 Separate what you expect from what you know
A22: Confidence refers to local evidence supporting the proposed protection outcome, not the prestige of a source. Modeled potential can be shown before approval; it is not a resource supply. Record a reference to a comparison, pilot or other evidence. Accepted reductions in protection require an explicit risk acceptance reference. No score selects removal or bypasses the review. Retain means an unchanged annual profile and no released resource.
A29: 4 Clear challenges and make the human decision
A30: Complete all six Challenge Review questions, name the reviewer and record the review date. No or an unresolved concern means Blocked; missing answers mean Unchecked. Planning requires Clear, Evidence-backed, an Approved or Implemented decision, an approver, evidence, decision date, effective date and explicit usable-time shares. A decision that is Open, Pilot approved or Rejected does not qualify. Future-effective changes remain excluded until the planning as-of date.
A37: 5 Record actual results without rewriting history
A38: For Realized, record signed annual changes from a like-for-like measured comparison. Enter the observation start/end, evidence, verifier/date and normalization method. Annualized measurement is a measured run-rate estimate, not a full-year observation. Record the change in labor value separately from cash using the period's fixed rates and mix; never multiply net hours by a current global rate when groups changed. These input snapshots are independent of forecast rate changes. The decision must be Implemented. Realized labels without measurements are visibly flagged and excluded.
A46: 6 Use three resources, not one attractive euro number
A47: Business hours, specialist-team hours and recurring cash stay separate. Cash inputs in this model are non-labor spend; employment cost is already valued through hours. Positive hours use the documented usable-time share; extra work counts in full. Choose Approved + measured or Measured only in Settings. One-time costs need separate funding. Exclude an overlap only when its linked Live case is included under the same planning basis and the mapping is documented. Until then, count it in full. Aggregate hours still need real skill, team and timing matches.
... A64: All example figures are assumptions from the supplied workbook, not measured organizational savings. Hypotheses about security effectiveness need local validation and must not be generalized from a narrow study. No result authorizes noncompliance or disregards rare, severe events. The workbook uses annualized steady-state comparisons, not a monthly cash-flow model, a statistical confidence interval or an audit trail. Preserve dated versions and supporting evidence outside the workbook. Numeric estimates and positive gates aid a decision; they do not establish that the protection outcome is safe.

Sheet Sources
A1: Sources and provenance
A3: Bibliography carried over from the supplied workbook. Numeric examples are local assumptions; external references have not been re-verified for this rebuild.
A5: =IFERROR(HYPERLINK("#'Start'!A1","← Start"),"← Start") -> ← Start
A6: Source ID | B6: Reference | C6: URL / supplied file | D6: Use in this model | E6: Limit / scope | F6: Review status
A7: 1 | B7: Cormac Herley: So Long, and No Thanks for the Externalities (2009) | C7: https://www.microsoft.com/en-us/research/publication/so-long-and-no-thanks-for-the-externalities-the-rational-rejection-of-security-advice-by-users/ | D7: Background reading for the original example catalog. | E7: Read the original scope; establish local applicability separately. | F7: Carried over; not freshly verified
A8: 2 | B8: Beautement, Sasse, Wonham: The Compliance Budget (2008) | C8: https://discovery.ucl.ac.uk/id/eprint/24207/ | D8: Background reading for the original example catalog. | E8: Read the original scope; establish local applicability separately. | F8: Carried over; not freshly verified
A9: 3 | B9: Adams & Sasse: Users Are Not the Enemy (1999) | C9: https://dl.acm.org/doi/10.1145/322796.322806 | D9: Background reading for the original example catalog. | E9: Read the original scope; establish local applicability separately. | F9: Carried over; not freshly verified
A10: 4 | B10: NIST SP 800-63B-4 | C10: https://pages.nist.gov/800-63-4/sp800-63b.html | D10: Background reading for the original example catalog. | E10: Read the original scope; establish local applicability separately. | F10: Carried over; not freshly verified
A11: 5 | B11: NIST: Security Fatigue (2016) | C11: https://csrc.nist.gov/pubs/journal/2016/09/security-fatigue/final | D11: Background reading for the original example catalog. | E11: Read the original scope; establish local applicability separately. | F11: Carried over; not freshly verified
A12: 6 | B12: Ho et al.: Understanding the Efficacy of Phishing Training in Practice, IEEE S&P 2025 | C12: https://par.nsf.gov/biblio/10600744 | D12: Background reading for the original example catalog. | E12: Read the original scope; establish local applicability separately. | F12: Carried over; not freshly verified
A13: 7 | B13: Lain, Kostiainen, Capkun: Phishing in Organizations, IEEE S&P 2022 | C13: https://ieeexplore.ieee.org/document/9833621 | D13: Background reading for the original example catalog. | E13: Read the original scope; establish local applicability separately. | F13: Carried over; not freshly verified
A14: 8 | B14: Verizon DBIR 2025, version-pinned link | C14: https://www.verizon.com/business/resources/reports/2025-dbir-data-breach-investigations-report.pdf | D14: Background reading for the original example catalog. | E14: Read the original scope; establish local applicability separately. | F14: Carried over; not freshly verified
A15: 9 | B15: Microsoft Learn: Sensitivity labels for Teams/groups/sites | C15: https://learn.microsoft.com/en-us/purview/sensitivity-labels-teams-groups-sites | D15: Background reading for the original example catalog. | E15: Read the original scope; establish local applicability separately. | F15: Carried over; not freshly verified
A16: 10 | B16: ISO/IEC 27002:2022, controls 5.12 and 5.13 | C16: https://www.iso.org/standard/75652.html | D16: Background reading for the original example catalog. | E16: Read the original scope; establish local applicability separately. | F16: Carried over; not freshly verified
A17: 11 | B17: German Trade Secrets Act (GeschGehG), § 2 | C17: https://www.gesetze-im-internet.de/geschgehg/ | D17: Background reading for the original example catalog. | E17: Read the original scope; establish local applicability separately. | F17: Carried over; not freshly verified
A18: 12 | B18: CISA Known Exploited Vulnerabilities Catalog | C18: https://www.cisa.gov/known-exploited-vulnerabilities-catalog | D18: Background reading for the original example catalog. | E18: Read the original scope; establish local applicability separately. | F18: Carried over; not freshly verified
... A23: 17 | B23: CISA #StopRansomware Guide | C23: https://www.cisa.gov/stopransomware/ransomware-guide | D23: Background reading for the original example catalog. | E23: Read the original scope; establish local applicability separately. | F23: Carried over; not freshly verified
A24: INPUT | B24: Attached English workbook | C24: Opportunity-Cost-Security-Model.xlsx | D24: Source of eleven numeric example profiles and indicative rates. | E24: Earlier v5 file: nine sheets; 376 formula definitions in the supplied file. | F24: Migrated / recalculated
A25: REVIEW | B25: Prior review and usability blueprint | C25: Opportunity_Cost_Security_Review_and_UX_Blueprint.md | D25: Design and regression requirements. | E25: Prior findings are not evidence about a real organization's savings. | F25: Implemented / tested in release notes
A26: LATEST | B26: User-provided later regression report | C26: Current conversation | D26: Readiness, key integrity, missing inputs, example isolation, measurements and overlap tests. | E26: The later 636-formula workbook itself was not attached; its baseline is not silently imposed on this source. | F26: Acceptance criteria
A27: ASSUMPTIONS | B27: Numeric values and rates in example records | C27: Current / Proposed / Settings | D27: Illustrative cost and workload calculations. | E27: Not measurements, guaranteed savings or product pricing. | F27: Replace and document before live approval

Sheet Checks
A1: Calculation and readiness ledger
A3: Calculated outputs only. Do not edit or append rows. Every case key must occur once in every input table. Start detects missing readiness outputs.
A5: =IFERROR(HYPERLINK("#'Start'!A1","← Start"),"← Start") -> ← Start
A6: Case ID | B6: Case type | C6: Activity | D6: Case complete | E6: Current ready | F6: Proposed ready | G6: Challenge state | H6: Review complete | I6: Actuals ready | J6: Next action | K6: Forecast eligible | L6: Measured eligible | M6: Selected plan eligible | N6: Current business h | O6: Proposed business h | P6: Net business h | Q6: Current specialist h | R6: Proposed specialist h | S6: Net specialist h | T6: Current cash € | U6: Proposed cash € | V6: Cash change € | W6: Current total € | X6: Proposed total € | Y6: Time-valued benefit € | Z6: One-time € | AA6: Planning business h | AB6: Planning specialist h | AC6: Planning cash € | AD6: Planning one-time € | AE6: Declared realized | AF6: Measurement warning | AG6: Identity valid | AH6: Estimate ready | AI6: Benefit stage | AJ6: Human decision | AK6: Confidence | AL6: Actual business h | AM6: Actual specialist h | AN6: Actual cash € | AO6: Actual time-valued benefit € | AP6: Proposal
A7: C001 | B7: =IF(COUNTIFS(Cases!$A$7:$A$56,$A7,Cases!$B$7:$B$56,"<>")=1,IFERROR(INDEX(Cases!$B$7:$B$56,MATCH($A7,Cases!$A$7:$A$56,0)),""),"") -> Example | C7: =IF(COUNTIFS(Cases!$A$7:$A$56,$A7,Cases!$C$7:$C$56,"<>")=1,IFERROR(INDEX(Cases!$C$7:$C$56,MATCH($A7,Cases!$A$7:$A$56,0)),""),"") -> Document classification prompts | D7: =IF(AND(AG7=1,OR(B7="Example",B7="Live"),OR(AP7="Simplify",AP7="Replace",AP7="Reduce scope",AP7="Retire",AP7="Retain"),COUNTIFS(Cases!$A$7:$A$56,$A7,Cases!$C$7:$C$56,"<>")=1,COUNTIFS(Cases!$A$7:$A$56,$A7,Cases!$D$7:$D$56,"<>")=1,COUNTIFS(Cases!$A$7:$A$56,$A7,Cases!$E$7:$E$56,"<>")=1,COUNTIFS(Cases!$A$7:$A$56,$A7,Cases!$F$7:$F$56,"<>")=1,COUNTIFS(Cases!$A$7:$A$56,$A7,Cases!$H$7:$H$56,"<>")=1,COUNTIFS(Cases!$A$7:$A$56,$A7,Cases!$I$7:$I$56,"<>")=1,LEN(TRIM(IF(COUNTIFS(Cases!$A$7:$A$56,$A7,Cases!$C$7:$C$56,"<>")=1,IFERROR(INDEX(Cases!$C$7:$C$56,MATCH($A7,Cases!$A$7:$A$56,0)),""),"")))>0,LEN(TRIM(IF(COUNTIFS(Cases!$A$7:$A$56,$A7,Cases!$D$7:$D$56,"<>")=1,IFERROR(INDEX(Cases!$D$7:$D$56,MATCH($A7,Cases!$A$7:$A$56,0)),""),"")))>0,LEN(TRIM(IF(COUNTIFS(Cases!$A$7:$A$56,$A7,Cases!$E$7:$E$56,"<>")=1,IFERROR(INDEX(Cases!$E$7:$E$56,MATCH($A7,Cases!$A$7:$A$56,0)),""),"")))>0,LEN(TRIM(IF(COUNTIFS(Cases!$A$7:$A$56,$A7,Cases!$F$7:$F$56,"<>")=1,IFERROR(INDEX(Cases!$F$7:$F$56,MATCH($A7,Cases!$A$7:$A$56,0)),""),"")))>0,LEN(TRIM(IF(COUNTIFS(Cases!$A$7:$A$56,$A7,Cases!$H$7:$H$56,"<>")=1,IFERROR(INDEX(Cases!$H$7:$H$56,MATCH($A7,Cases!$A$7:$A$56,0)),""),"")))>0,LEN(TRIM(IF(COUNTIFS(Cases!$A$7:$A$56,$A7,Cases!$I$7:$I$56,"<>")=1,IFERROR(INDEX(Cases!$I$7:$I$56,MATCH($A7,Cases!$A$7:$A$56,0)),""),"")))>0),1,0) -> 1 | E7: =IF(AND(AG7=1,IFERROR(INDEX(Current!$G$7:$G$56,MATCH($A7,Current!$A$7:$A$56,0)),"")="Ready"),1,0) -> 1 | F7: =IF(AND(AG7=1,IFERROR(INDEX(Proposed!$H$7:$H$56,MATCH($A7,Proposed!$A$7:$A$56,0)),"")="Ready",OR(AP7<>"Retain",AND(IFERROR(INDEX(Current!$B$7:$B$56,MATCH($A7,Current!$A$7:$A$56,0)),"")=IFERROR(INDEX(Proposed!$B$7:$B$56,MATCH($A7,Proposed!$A$7:$A$56,0)),""),IFERROR(INDEX(Current!$C$7:$C$56,MATCH($A7,Current!$A$7:$A$56,0)),"")=IFERROR(INDEX(Proposed!$C$7:$C$56,MATCH($A7,Proposed!$A$7:$A$56,0)),""),IFERROR(INDEX(Current!$D$7:$D$56,MATCH($A7,Current!$A$7:$A$56,0)),"")=IFERROR(INDEX(Proposed!$D$7:$D$56,MATCH($A7,Proposed!$A$7:$A$56,0)),""),IFERROR(INDEX(Current!$E$7:$E$56,MATCH($A7,Current!$A$7:$A$56,0)),"")=IFERROR(INDEX(Proposed!$E$7:$E$56,MATCH($A7,Proposed!$A$7:$A$56,0)),"")))),1,0) -> 1 | G7: =IF(COUNTIFS('Challenge Review'!$A$7:$A$56,$A7,'Challenge Review'!$K$7:$K$56,"<>")=1,IFERROR(INDEX('Challenge Review'!$K$7:$K$56,MATCH($A7,'Challenge Review'!$A$7:$A$56,0)),""),"") -> Unchecked | H7: =IF(AND(AG7=1,IFERROR(INDEX('Review & Decision'!$B$7:$B$56,MATCH($A7,'Review & Decision'!$A$7:$A$56,0)),"")="Evidence-backed",OR(IFERROR(INDEX('Review & Decision'!$C$7:$C$56,MATCH($A7,'Review & Decision'!$A$7:$A$56,0)),"")="Equivalent or better",AND(IFERROR(INDEX('Review & Decision'!$C$7:$C$56,MATCH($A7,'Review & Decision'!$A$7:$A$56,0)),"")="Accepted reduction",COUNTIFS('Review & Decision'!$A$7:$A$56,$A7,'Review & Decision'!$L$7:$L$56,"<>")=1)),COUNTIFS('Review & Decision'!$A$7:$A$56,$A7,'Review & Decision'!$D$7:$D$56,"<>")=1,COUNTIFS('Review & Decision'!$A$7:$A$56,$A7,'Review & Decision'!$F$7:$F$56,"<>")=1,OR(IFERROR(INDEX('Review & Decision'!$E$7:$E$56,MATCH($A7,'Review & Decision'!$A$7:$A$56,0)),"")="Approved",IFERROR(INDEX('Review & Decision'!$E$7:$E$56,MATCH($A7,'Review & Decision'!$A$7:$A$56,0)),"")="Implemented"),ISNUMBER(IFERROR(INDEX('Review & Decision'!$G$7:$G$56,MATCH($A7,'Review & Decision'!$A$7:$A$56,0)),"")),IFERROR(INDEX('Review & Decision'!$G$7:$G$56,MATCH($A7,'Review & Decision'!$A$7:$A$56,0)),"")>0,IFERROR(INDEX('Review & Decision'!$G$7:$G$56,MATCH($A7,'Review & Decision'!$A$7:$A$56,0)),"")<=Settings!$B$7,ISNUMBER(IFERROR(INDEX('Review & Decision'!$I$7:$I$56,MATCH($A7,'Review & Decision'!$A$7:$A$56,0)),"")),IFERROR(INDEX('Review & Decision'!$I$7:$I$56,MATCH($A7,'Review & Decision'!$A$7:$A$56,0)),"")>0,IFERROR(INDEX('Review & Decision'!$I$7:$I$56,MATCH($A7,'Review & Decision'!$A$7:$A$56,0)),"")<=Settings!$B$7,IFERROR(INDEX('Review & Decision'!$I$7:$I$56,MATCH($A7,'Review & Decision'!$A$7:$A$56,0)),"")>=IFERROR(INDEX('Review & Decision'!$G$7:$G$56,MATCH($A7,'Review & Decision'!$A$7:$A$56,0)),""),COUNTIFS('Review & Decision'!$A$7:$A$56,$A7,'Review & Decision'!$J$7:$J$56,"<>")=1,COUNTIFS('Review & Decision'!$A$7:$A$56,$A7,'Review & Decision'!$K$7:$K$56,"<>")=1,ISNUMBER(IFERROR(INDEX('Review & Decision'!$J$7:$J$56,MATCH($A7,'Review & Decision'!$A$7:$A$56,0)),"")),IFERROR(INDEX('Review & Decision'!$J$7:$J$56,MATCH($A7,'Review & Decision'!$A$7:$A$56,0)),"")>=0,IFERROR(INDEX('Review & Decision'!$J$7:$J$56,MATCH($A7,'Review & Decision'!$A$7:$A$56,0)),"")<=1,ISNUMBER(IFERROR(INDEX('Review & Decision'!$K$7:$K$56,MATCH($A7,'Review & Decision'!$A$7:$A$56,0)),"")),IFERROR(INDEX('Review & Decision'!$K$7:$K$56,MATCH($A7,'Review & Decision'!$A$7:$A$56,0)),"")>=0,IFERROR(INDEX('Review & Decision'!$K$7:$K$56,MATCH($A7,'Review & Decision'!$A$7:$A$56,0)),"")<=1,ISNUMBER(Settings!$B$7),Settings!$B$7>0,OR(Settings!$B$8="Approved + measured",Settings!$B$8="Measured only"),LEN(TRIM(IF(COUNTIFS('Review & Decision'!$A$7:$A$56,$A7,'Review & Decision'!$D$7:$D$56,"<>")=1,IFERROR(INDEX('Review & Decision'!$D$7:$D$56,MATCH($A7,'Review & Decision'!$A$7:$A$56,0)),""),"")))>0,LEN(TRIM(IF(COUNTIFS('Review & Decision'!$A$7:$A$56,$A7,'Review & Decision'!$F$7:$F$56,"<>")=1,IFERROR(INDEX('Review & Decision'!$F$7:$F$56,MATCH($A7,'Review & Decision'!$A$7:$A$56,0)),""),"")))>0,OR(IFERROR(INDEX('Review & Decision'!$C$7:$C$56,MATCH($A7,'Review & Decision'!$A$7:$A$56,0)),"")<>"Accepted reduction",LEN(TRIM(IF(COUNTIFS('Review & Decision'!$A$7:$A$56,$A7,'Review & Decision'!$L$7:$L$56,"<>")=1,IFERROR(INDEX('Review & Decision'!$L$7:$L$56,MATCH($A7,'Review & Decision'!$A$7:$A$56,0)),""),"")))>0)),1,0) -> 0 | I7: =IF(AND(AG7=1,IFERROR(INDEX(Actuals!$M$7:$M$56,MATCH($A7,Actuals!$A$7:$A$56,0)),"")="Ready",IFERROR(INDEX(Actuals!$D$7:$D$56,MATCH($A7,Actuals!$A$7:$A$56,0)),"")>=IFERROR(INDEX('Review & Decision'!$I$7:$I$56,MATCH($A7,'Review & Decision'!$A$7:$A$56,0)),"")),1,0) -> 0 | J7: =IF(AG7=0,"Fix duplicate / missing case ID",IF(B7="Inactive","Unused slot",IF(B7="Example","Example only — never in live planning",IF(D7=0,"Complete case scope and proposal",IF(E7=0,"Complete current inputs; confirm zeros",IF(F7=0,"Complete full proposed profile",IF(G7="Blocked","Blocked — resolve challenge concern",IF(AJ7="Rejected","Rejected — excluded from planning",IF(AND(AI7="Realized",I7=0),"Add measurements, period and evidence",IF(G7<>"Clear","Complete and sign challenge review",IF(H7=0,"Approve evidence, dates and usable shares",IF(AP7="Retain","Retained — no released resource",IF(L7=1,"Measured result eligible",IF(K7=1,"Approved forecast eligible","Modeled only — not allocatable")))))))))))))) -> Example only — never in live planning | K7: =IF(AND(B7="Live",AH7=1,G7="Clear",H7=1,AI7="Validated",AP7<>"Retain"),1,0) -> 0 | L7: =IF(AND(B7="Live",AH7=1,G7="Clear",H7=1,I7=1,AI7="Realized",AJ7="Implemented",AP7<>"Retain"),1,0) -> 0 | M7: =IF(OR(L7=1,AND(K7=1,Settings!$B$8="Approved + measured")),1,0) -> 0 | N7: =IF(E7=1,IFERROR(INDEX(Current!$H$7:$H$56,MATCH($A7,Current!$A$7:$A$56,0)),""),"") -> 7333.3333 | O7: =IF(F7=1,IFERROR(INDEX(Proposed!$I$7:$I$56,MATCH($A7,Proposed!$A$7:$A$56,0)),""),"") -> 300 | P7: =IF(AH7=1,N7-O7,"") -> 7033.3333 | Q7: =IF(E7=1,IFERROR(INDEX(Current!$I$7:$I$56,MATCH($A7,Current!$A$7:$A$56,0)),""),"") -> 150 | R7: =IF(F7=1,IFERROR(INDEX(Proposed!$J$7:$J$56,MATCH($A7,Proposed!$A$7:$A$56,0)),""),"") -> 80 | S7: =IF(AH7=1,Q7-R7,"") -> 70 | T7: =IF(E7=1,IFERROR(INDEX(Current!$E$7:$E$56,MATCH($A7,Current!$A$7:$A$56,0)),""),"") -> 0 | U7: =IF(F7=1,IFERROR(INDEX(Proposed!$E$7:$E$56,MATCH($A7,Proposed!$A$7:$A$56,0)),""),"") -> 60000 | V7: =IF(AH7=1,T7-U7,"") -> -60000 | W7: =IF(E7=1,IFERROR(INDEX(Current!$K$7:$K$56,MATCH($A7,Current!$A$7:$A$56,0)),""),"") -> 451250 | X7: =IF(F7=1,IFERROR(INDEX(Proposed!$L$7:$L$56,MATCH($A7,Proposed!$A$7:$A$56,0)),""),"") -> 84000 | Y7: =IF(AH7=1,W7-X7,"") -> 367250 | Z7: =IF(F7=1,IFERROR(INDEX(Proposed!$F$7:$F$56,MATCH($A7,Proposed!$A$7:$A$56,0)),""),"") -> 40000 | AA7: =IF(M7=1,IF(IF(L7=1,AL7,P7)>0,IF(L7=1,AL7,P7)*IFERROR(INDEX('Review & Decision'!$J$7:$J$56,MATCH($A7,'Review & Decision'!$A$7:$A$56,0)),""),IF(L7=1,AL7,P7)),0) -> 0 | AB7: =IF(M7=1,IF(IF(L7=1,AM7,S7)>0,IF(L7=1,AM7,S7)*IFERROR(INDEX('Review & Decision'!$K$7:$K$56,MATCH($A7,'Review & Decision'!$A$7:$A$56,0)),""),IF(L7=1,AM7,S7)),0) -> 0 | AC7: =IF(M7=1,IF(L7=1,AN7,V7),0) -> 0 | AD7: =IF(AND(M7=1,L7=0),Z7,0) -> 0 | AE7: =IF(AND(B7="Live",AI7="Realized"),1,0) -> 0 | AF7: =IF(AND(AE7=1,I7=0),"Missing measured evidence","No measurement warning") -> No measurement warning | AG7: =IF(AND(COUNTIF(Cases!$A$7:$A$56,$A7)=1,COUNTIF(Current!$A$7:$A$56,$A7)=1,COUNTIF(Proposed!$A$7:$A$56,$A7)=1,COUNTIF('Review & Decision'!$A$7:$A$56,$A7)=1,COUNTIF('Challenge Review'!$A$7:$A$56,$A7)=1,COUNTIF(Actuals!$A$7:$A$56,$A7)=1,COUNTIF(Classification!$A$7:$A$56,$A7)=1),1,0) -> 1 | AH7: =IF(AND(D7=1,E7=1,F7=1),1,0) -> 1 | AI7: =IF(COUNTIFS('Review & Decision'!$A$7:$A$56,$A7,'Review & Decision'!$H$7:$H$56,"<>")=1,IFERROR(INDEX('Review & Decision'!$H$7:$H$56,MATCH($A7,'Review & Decision'!$A$7:$A$56,0)),""),"") -> Modeled | AJ7: =IF(COUNTIFS('Review & Decision'!$A$7:$A$56,$A7,'Review & Decision'!$E$7:$E$56,"<>")=1,IFERROR(INDEX('Review & Decision'!$E$7:$E$56,MATCH($A7,'Review & Decision'!$A$7:$A$56,0)),""),"") -> Open | AK7: =IF(COUNTIFS('Review & Decision'!$A$7:$A$56,$A7,'Review & Decision'!$B$7:$B$56,"<>")=1,IFERROR(INDEX('Review & Decision'!$B$7:$B$56,MATCH($A7,'Review & Decision'!$A$7:$A$56,0)),""),"") -> Hypothesis | AL7: =IF(I7=1,IFERROR(INDEX(Actuals!$E$7:$E$56,MATCH($A7,Actuals!$A$7:$A$56,0)),""),"") | AM7: =IF(I7=1,IFERROR(INDEX(Actuals!$F$7:$F$56,MATCH($A7,Actuals!$A$7:$A$56,0)),""),"") | AN7: =IF(I7=1,IFERROR(INDEX(Actuals!$G$7:$G$56,MATCH($A7,Actuals!$A$7:$A$56,0)),""),"") | AO7: =IF(I7=1,IFERROR(INDEX(Actuals!$G$7:$G$56,MATCH($A7,Actuals!$A$7:$A$56,0)),"")+IFERROR(INDEX(Actuals!$H$7:$H$56,MATCH($A7,Actuals!$A$7:$A$56,0)),""),"") | AP7: =IF(COUNTIFS(Cases!$A$7:$A$56,$A7,Cases!$G$7:$G$56,"<>")=1,IFERROR(INDEX(Cases!$G$7:$G$56,MATCH($A7,Cases!$A$7:$A$56,0)),""),"") -> Replace
A8: C002 | B8: =IF(COUNTIFS(Cases!$A$7:$A$56,$A8,Cases!$B$7:$B$56,"<>")=1,IFERROR(INDEX(Cases!$B$7:$B$56,MATCH($A8,Cases!$A$7:$A$56,0)),""),"") -> Example | C8: =IF(COUNTIFS(Cases!$A$7:$A$56,$A8,Cases!$C$7:$C$56,"<>")=1,IFERROR(INDEX(Cases!$C$7:$C$56,MATCH($A8,Cases!$A$7:$A$56,0)),""),"") -> Periodic password changes | D8: =IF(AND(AG8=1,OR(B8="Example",B8="Live"),OR(AP8="Simplify",AP8="Replace",AP8="Reduce scope",AP8="Retire",AP8="Retain"),COUNTIFS(Cases!$A$7:$A$56,$A8,Cases!$C$7:$C$56,"<>")=1,COUNTIFS(Cases!$A$7:$A$56,$A8,Cases!$D$7:$D$56,"<>")=1,COUNTIFS(Cases!$A$7:$A$56,$A8,Cases!$E$7:$E$56,"<>")=1,COUNTIFS(Cases!$A$7:$A$56,$A8,Cases!$F$7:$F$56,"<>")=1,COUNTIFS(Cases!$A$7:$A$56,$A8,Cases!$H$7:$H$56,"<>")=1,COUNTIFS(Cases!$A$7:$A$56,$A8,Cases!$I$7:$I$56,"<>")=1,LEN(TRIM(IF(COUNTIFS(Cases!$A$7:$A$56,$A8,Cases!$C$7:$C$56,"<>")=1,IFERROR(INDEX(Cases!$C$7:$C$56,MATCH($A8,Cases!$A$7:$A$56,0)),""),"")))>0,LEN(TRIM(IF(COUNTIFS(Cases!$A$7:$A$56,$A8,Cases!$D$7:$D$56,"<>")=1,IFERROR(INDEX(Cases!$D$7:$D$56,MATCH($A8,Cases!$A$7:$A$56,0)),""),"")))>0,LEN(TRIM(IF(COUNTIFS(Cases!$A$7:$A$56,$A8,Cases!$E$7:$E$56,"<>")=1,IFERROR(INDEX(Cases!$E$7:$E$56,MATCH($A8,Cases!$A$7:$A$56,0)),""),"")))>0,LEN(TRIM(IF(COUNTIFS(Cases!$A$7:$A$56,$A8,Cases!$F$7:$F$56,"<>")=1,IFERROR(INDEX(Cases!$F$7:$F$56,MATCH($A8,Cases!$A$7:$A$56,0)),""),"")))>0,LEN(TRIM(IF(COUNTIFS(Cases!$A$7:$A$56,$A8,Cases!$H$7:$H$56,"<>")=1,IFERROR(INDEX(Cases!$H$7:$H$56,MATCH($A8,Cases!$A$7:$A$56,0)),""),"")))>0,LEN(TRIM(IF(COUNTIFS(Cases!$A$7:$A$56,$A8,Cases!$I$7:$I$56,"<>")=1,IFERROR(INDEX(Cases!$I$7:$I$56,MATCH($A8,Cases!$A$7:$A$56,0)),""),"")))>0),1,0) -> 1 | E8: =IF(AND(AG8=1,IFERROR(INDEX(Current!$G$7:$G$56,MATCH($A8,Current!$A$7:$A$56,0)),"")="Ready"),1,0) -> 1 | F8: =IF(AND(AG8=1,IFERROR(INDEX(Proposed!$H$7:$H$56,MATCH($A8,Proposed!$A$7:$A$56,0)),"")="Ready",OR(AP8<>"Retain",AND(IFERROR(INDEX(Current!$B$7:$B$56,MATCH($A8,Current!$A$7:$A$56,0)),"")=IFERROR(INDEX(Proposed!$B$7:$B$56,MATCH($A8,Proposed!$A$7:$A$56,0)),""),IFERROR(INDEX(Current!$C$7:$C$56,MATCH($A8,Current!$A$7:$A$56,0)),"")=IFERROR(INDEX(Proposed!$C$7:$C$56,MATCH($A8,Proposed!$A$7:$A$56,0)),""),IFERROR(INDEX(Current!$D$7:$D$56,MATCH($A8,Current!$A$7:$A$56,0)),"")=IFERROR(INDEX(Proposed!$D$7:$D$56,MATCH($A8,Proposed!$A$7:$A$56,0)),""),IFERROR(INDEX(Current!$E$7:$E$56,MATCH($A8,Current!$A$7:$A$56,0)),"")=IFERROR(INDEX(Proposed!$E$7:$E$56,MATCH($A8,Proposed!$A$7:$A$56,0)),"")))),1,0) -> 1 | G8: =IF(COUNTIFS('Challenge Review'!$A$7:$A$56,$A8,'Challenge Review'!$K$7:$K$56,"<>")=1,IFERROR(INDEX('Challenge Review'!$K$7:$K$56,MATCH($A8,'Challenge Review'!$A$7:$A$56,0)),""),"") -> Unchecked | H8: =IF(AND(AG8=1,IFERROR(INDEX('Review & Decision'!$B$7:$B$56,MATCH($A8,'Review & Decision'!$A$7:$A$56,0)),"")="Evidence-backed",OR(IFERROR(INDEX('Review & Decision'!$C$7:$C$56,MATCH($A8,'Review & Decision'!$A$7:$A$56,0)),"")="Equivalent or better",AND(IFERROR(INDEX('Review & Decision'!$C$7:$C$56,MATCH($A8,'Review & Decision'!$A$7:$A$56,0)),"")="Accepted reduction",COUNTIFS('Review & Decision'!$A$7:$A$56,$A8,'Review & Decision'!$L$7:$L$56,"<>")=1)),COUNTIFS('Review & Decision'!$A$7:$A$56,$A8,'Review & Decision'!$D$7:$D$56,"<>")=1,COUNTIFS('Review & Decision'!$A$7:$A$56,$A8,'Review & Decision'!$F$7:$F$56,"<>")=1,OR(IFERROR(INDEX('Review & Decision'!$E$7:$E$56,MATCH($A8,'Review & Decision'!$A$7:$A$56,0)),"")="Approved",IFERROR(INDEX('Review & Decision'!$E$7:$E$56,MATCH($A8,'Review & Decision'!$A$7:$A$56,0)),"")="Implemented"),ISNUMBER(IFERROR(INDEX('Review & Decision'!$G$7:$G$56,MATCH($A8,'Review & Decision'!$A$7:$A$56,0)),"")),IFERROR(INDEX('Review & Decision'!$G$7:$G$56,MATCH($A8,'Review & Decision'!$A$7:$A$56,0)),"")>0,IFERROR(INDEX('Review & Decision'!$G$7:$G$56,MATCH($A8,'Review & Decision'!$A$7:$A$56,0)),"")<=Settings!$B$7,ISNUMBER(IFERROR(INDEX('Review & Decision'!$I$7:$I$56,MATCH($A8,'Review & Decision'!$A$7:$A$56,0)),"")),IFERROR(INDEX('Review & Decision'!$I$7:$I$56,MATCH($A8,'Review & Decision'!$A$7:$A$56,0)),"")>0,IFERROR(INDEX('Review & Decision'!$I$7:$I$56,MATCH($A8,'Review & Decision'!$A$7:$A$56,0)),"")<=Settings!$B$7,IFERROR(INDEX('Review & Decision'!$I$7:$I$56,MATCH($A8,'Review & Decision'!$A$7:$A$56,0)),"")>=IFERROR(INDEX('Review & Decision'!$G$7:$G$56,MATCH($A8,'Review & Decision'!$A$7:$A$56,0)),""),COUNTIFS('Review & Decision'!$A$7:$A$56,$A8,'Review & Decision'!$J$7:$J$56,"<>")=1,COUNTIFS('Review & Decision'!$A$7:$A$56,$A8,'Review & Decision'!$K$7:$K$56,"<>")=1,ISNUMBER(IFERROR(INDEX('Review & Decision'!$J$7:$J$56,MATCH($A8,'Review & Decision'!$A$7:$A$56,0)),"")),IFERROR(INDEX('Review & Decision'!$J$7:$J$56,MATCH($A8,'Review & Decision'!$A$7:$A$56,0)),"")>=0,IFERROR(INDEX('Review & Decision'!$J$7:$J$56,MATCH($A8,'Review & Decision'!$A$7:$A$56,0)),"")<=1,ISNUMBER(IFERROR(INDEX('Review & Decision'!$K$7:$K$56,MATCH($A8,'Review & Decision'!$A$7:$A$56,0)),"")),IFERROR(INDEX('Review & Decision'!$K$7:$K$56,MATCH($A8,'Review & Decision'!$A$7:$A$56,0)),"")>=0,IFERROR(INDEX('Review & Decision'!$K$7:$K$56,MATCH($A8,'Review & Decision'!$A$7:$A$56,0)),"")<=1,ISNUMBER(Settings!$B$7),Settings!$B$7>0,OR(Settings!$B$8="Approved + measured",Settings!$B$8="Measured only"),LEN(TRIM(IF(COUNTIFS('Review & Decision'!$A$7:$A$56,$A8,'Review & Decision'!$D$7:$D$56,"<>")=1,IFERROR(INDEX('Review & Decision'!$D$7:$D$56,MATCH($A8,'Review & Decision'!$A$7:$A$56,0)),""),"")))>0,LEN(TRIM(IF(COUNTIFS('Review & Decision'!$A$7:$A$56,$A8,'Review & Decision'!$F$7:$F$56,"<>")=1,IFERROR(INDEX('Review & Decision'!$F$7:$F$56,MATCH($A8,'Review & Decision'!$A$7:$A$56,0)),""),"")))>0,OR(IFERROR(INDEX('Review & Decision'!$C$7:$C$56,MATCH($A8,'Review & Decision'!$A$7:$A$56,0)),"")<>"Accepted reduction",LEN(TRIM(IF(COUNTIFS('Review & Decision'!$A$7:$A$56,$A8,'Review & Decision'!$L$7:$L$56,"<>")=1,IFERROR(INDEX('Review & Decision'!$L$7:$L$56,MATCH($A8,'Review & Decision'!$A$7:$A$56,0)),""),"")))>0)),1,0) -> 0 | I8: =IF(AND(AG8=1,IFERROR(INDEX(Actuals!$M$7:$M$56,MATCH($A8,Actuals!$A$7:$A$56,0)),"")="Ready",IFERROR(INDEX(Actuals!$D$7:$D$56,MATCH($A8,Actuals!$A$7:$A$56,0)),"")>=IFERROR(INDEX('Review & Decision'!$I$7:$I$56,MATCH($A8,'Review & Decision'!$A$7:$A$56,0)),"")),1,0) -> 0 | J8: =IF(AG8=0,"Fix duplicate / missing case ID",IF(B8="Inactive","Unused slot",IF(B8="Example","Example only — never in live planning",IF(D8=0,"Complete case scope and proposal",IF(E8=0,"Complete current inputs; confirm zeros",IF(F8=0,"Complete full proposed profile",IF(G8="Blocked","Blocked — resolve challenge concern",IF(AJ8="Rejected","Rejected — excluded from planning",IF(AND(AI8="Realized",I8=0),"Add measurements, period and evidence",IF(G8<>"Clear","Complete and sign challenge review",IF(H8=0,"Approve evidence, dates and usable shares",IF(AP8="Retain","Retained — no released resource",IF(L8=1,"Measured result eligible",IF(K8=1,"Approved forecast eligible","Modeled only — not allocatable")))))))))))))) -> Example only — never in live planning | K8: =IF(AND(B8="Live",AH8=1,G8="Clear",H8=1,AI8="Validated",AP8<>"Retain"),1,0) -> 0 | L8: =IF(AND(B8="Live",AH8=1,G8="Clear",H8=1,I8=1,AI8="Realized",AJ8="Implemented",AP8<>"Retain"),1,0) -> 0 | M8: =IF(OR(L8=1,AND(K8=1,Settings!$B$8="Approved + measured")),1,0) -> 0 | N8: =IF(E8=1,IFERROR(INDEX(Current!$H$7:$H$56,MATCH($A8,Current!$A$7:$A$56,0)),""),"") -> 1733.3333 | O8: =IF(F8=1,IFERROR(INDEX(Proposed!$I$7:$I$56,MATCH($A8,Proposed!$A$7:$A$56,0)),""),"") -> 0 | P8: =IF(AH8=1,N8-O8,"") -> 1733.3333 | Q8: =IF(E8=1,IFERROR(INDEX(Current!$I$7:$I$56,MATCH($A8,Current!$A$7:$A$56,0)),""),"") -> 0 | R8: =IF(F8=1,IFERROR(INDEX(Proposed!$J$7:$J$56,MATCH($A8,Proposed!$A$7:$A$56,0)),""),"") -> 10 | S8: =IF(AH8=1,Q8-R8,"") -> -10 | T8: =IF(E8=1,IFERROR(INDEX(Current!$E$7:$E$56,MATCH($A8,Current!$A$7:$A$56,0)),""),"") -> 0 | U8: =IF(F8=1,IFERROR(INDEX(Proposed!$E$7:$E$56,MATCH($A8,Proposed!$A$7:$A$56,0)),""),"") -> 0 | V8: =IF(AH8=1,T8-U8,"") -> 0 | W8: =IF(E8=1,IFERROR(INDEX(Current!$K$7:$K$56,MATCH($A8,Current!$A$7:$A$56,0)),""),"") -> 104000 | X8: =IF(F8=1,IFERROR(INDEX(Proposed!$L$7:$L$56,MATCH($A8,Proposed!$A$7:$A$56,0)),""),"") -> 750 | Y8: =IF(AH8=1,W8-X8,"") -> 103250 | Z8: =IF(F8=1,IFERROR(INDEX(Proposed!$F$7:$F$56,MATCH($A8,Proposed!$A$7:$A$56,0)),""),"") -> 5000 | AA8: =IF(M8=1,IF(IF(L8=1,AL8,P8)>0,IF(L8=1,AL8,P8)*IFERROR(INDEX('Review & Decision'!$J$7:$J$56,MATCH($A8,'Review & Decision'!$A$7:$A$56,0)),""),IF(L8=1,AL8,P8)),0) -> 0 | AB8: =IF(M8=1,IF(IF(L8=1,AM8,S8)>0,IF(L8=1,AM8,S8)*IFERROR(INDEX('Review & Decision'!$K$7:$K$56,MATCH($A8,'Review & Decision'!$A$7:$A$56,0)),""),IF(L8=1,AM8,S8)),0) -> 0 | AC8: =IF(M8=1,IF(L8=1,AN8,V8),0) -> 0 | AD8: =IF(AND(M8=1,L8=0),Z8,0) -> 0 | AE8: =IF(AND(B8="Live",AI8="Realized"),1,0) -> 0 | AF8: =IF(AND(AE8=1,I8=0),"Missing measured evidence","No measurement warning") -> No measurement warning | AG8: =IF(AND(COUNTIF(Cases!$A$7:$A$56,$A8)=1,COUNTIF(Current!$A$7:$A$56,$A8)=1,COUNTIF(Proposed!$A$7:$A$56,$A8)=1,COUNTIF('Review & Decision'!$A$7:$A$56,$A8)=1,COUNTIF('Challenge Review'!$A$7:$A$56,$A8)=1,COUNTIF(Actuals!$A$7:$A$56,$A8)=1,COUNTIF(Classification!$A$7:$A$56,$A8)=1),1,0) -> 1 | AH8: =IF(AND(D8=1,E8=1,F8=1),1,0) -> 1 | AI8: =IF(COUNTIFS('Review & Decision'!$A$7:$A$56,$A8,'Review & Decision'!$H$7:$H$56,"<>")=1,IFERROR(INDEX('Review & Decision'!$H$7:$H$56,MATCH($A8,'Review & Decision'!$A$7:$A$56,0)),""),"") -> Modeled | AJ8: =IF(COUNTIFS('Review & Decision'!$A$7:$A$56,$A8,'Review & Decision'!$E$7:$E$56,"<>")=1,IFERROR(INDEX('Review & Decision'!$E$7:$E$56,MATCH($A8,'Review & Decision'!$A$7:$A$56,0)),""),"") -> Open | AK8: =IF(COUNTIFS('Review & Decision'!$A$7:$A$56,$A8,'Review & Decision'!$B$7:$B$56,"<>")=1,IFERROR(INDEX('Review & Decision'!$B$7:$B$56,MATCH($A8,'Review & Decision'!$A$7:$A$56,0)),""),"") -> Hypothesis | AL8: =IF(I8=1,IFERROR(INDEX(Actuals!$E$7:$E$56,MATCH($A8,Actuals!$A$7:$A$56,0)),""),"") | AM8: =IF(I8=1,IFERROR(INDEX(Actuals!$F$7:$F$56,MATCH($A8,Actuals!$A$7:$A$56,0)),""),"") | AN8: =IF(I8=1,IFERROR(INDEX(Actuals!$G$7:$G$56,MATCH($A8,Actuals!$A$7:$A$56,0)),""),"") | AO8: =IF(I8=1,IFERROR(INDEX(Actuals!$G$7:$G$56,MATCH($A8,Actuals!$A$7:$A$56,0)),"")+IFERROR(INDEX(Actuals!$H$7:$H$56,MATCH($A8,Actuals!$A$7:$A$56,0)),""),"") | AP8: =IF(COUNTIFS(Cases!$A$7:$A$56,$A8,Cases!$G$7:$G$56,"<>")=1,IFERROR(INDEX(Cases!$G$7:$G$56,MATCH($A8,Cases!$A$7:$A$56,0)),""),"") -> Replace
A9: C003 | B9: =IF(COUNTIFS(Cases!$A$7:$A$56,$A9,Cases!$B$7:$B$56,"<>")=1,IFERROR(INDEX(Cases!$B$7:$B$56,MATCH($A9,Cases!$A$7:$A$56,0)),""),"") -> Example | C9: =IF(COUNTIFS(Cases!$A$7:$A$56,$A9,Cases!$C$7:$C$56,"<>")=1,IFERROR(INDEX(Cases!$C$7:$C$56,MATCH($A9,Cases!$A$7:$A$56,0)),""),"") -> Awareness training and phishing exercises | D9: =IF(AND(AG9=1,OR(B9="Example",B9="Live"),OR(AP9="Simplify",AP9="Replace",AP9="Reduce scope",AP9="Retire",AP9="Retain"),COUNTIFS(Cases!$A$7:$A$56,$A9,Cases!$C$7:$C$56,"<>")=1,COUNTIFS(Cases!$A$7:$A$56,$A9,Cases!$D$7:$D$56,"<>")=1,COUNTIFS(Cases!$A$7:$A$56,$A9,Cases!$E$7:$E$56,"<>")=1,COUNTIFS(Cases!$A$7:$A$56,$A9,Cases!$F$7:$F$56,"<>")=1,COUNTIFS(Cases!$A$7:$A$56,$A9,Cases!$H$7:$H$56,"<>")=1,COUNTIFS(Cases!$A$7:$A$56,$A9,Cases!$I$7:$I$56,"<>")=1,LEN(TRIM(IF(COUNTIFS(Cases!$A$7:$A$56,$A9,Cases!$C$7:$C$56,"<>")=1,IFERROR(INDEX(Cases!$C$7:$C$56,MATCH($A9,Cases!$A$7:$A$56,0)),""),"")))>0,LEN(TRIM(IF(COUNTIFS(Cases!$A$7:$A$56,$A9,Cases!$D$7:$D$56,"<>")=1,IFERROR(INDEX(Cases!$D$7:$D$56,MATCH($A9,Cases!$A$7:$A$56,0)),""),"")))>0,LEN(TRIM(IF(COUNTIFS(Cases!$A$7:$A$56,$A9,Cases!$E$7:$E$56,"<>")=1,IFERROR(INDEX(Cases!$E$7:$E$56,MATCH($A9,Cases!$A$7:$A$56,0)),""),"")))>0,LEN(TRIM(IF(COUNTIFS(Cases!$A$7:$A$56,$A9,Cases!$F$7:$F$56,"<>")=1,IFERROR(INDEX(Cases!$F$7:$F$56,MATCH($A9,Cases!$A$7:$A$56,0)),""),"")))>0,LEN(TRIM(IF(COUNTIFS(Cases!$A$7:$A$56,$A9,Cases!$H$7:$H$56,"<>")=1,IFERROR(INDEX(Cases!$H$7:$H$56,MATCH($A9,Cases!$A$7:$A$56,0)),""),"")))>0,LEN(TRIM(IF(COUNTIFS(Cases!$A$7:$A$56,$A9,Cases!$I$7:$I$56,"<>")=1,IFERROR(INDEX(Cases!$I$7:$I$56,MATCH($A9,Cases!$A$7:$A$56,0)),""),"")))>0),1,0) -> 1 | E9: =IF(AND(AG9=1,IFERROR(INDEX(Current!$G$7:$G$56,MATCH($A9,Current!$A$7:$A$56,0)),"")="Ready"),1,0) -> 1 | F9: =IF(AND(AG9=1,IFERROR(INDEX(Proposed!$H$7:$H$56,MATCH($A9,Proposed!$A$7:$A$56,0)),"")="Ready",OR(AP9<>"Retain",AND(IFERROR(INDEX(Current!$B$7:$B$56,MATCH($A9,Current!$A$7:$A$56,0)),"")=IFERROR(INDEX(Proposed!$B$7:$B$56,MATCH($A9,Proposed!$A$7:$A$56,0)),""),IFERROR(INDEX(Current!$C$7:$C$56,MATCH($A9,Current!$A$7:$A$56,0)),"")=IFERROR(INDEX(Proposed!$C$7:$C$56,MATCH($A9,Proposed!$A$7:$A$56,0)),""),IFERROR(INDEX(Current!$D$7:$D$56,MATCH($A9,Current!$A$7:$A$56,0)),"")=IFERROR(INDEX(Proposed!$D$7:$D$56,MATCH($A9,Proposed!$A$7:$A$56,0)),""),IFERROR(INDEX(Current!$E$7:$E$56,MATCH($A9,Current!$A$7:$A$56,0)),"")=IFERROR(INDEX(Proposed!$E$7:$E$56,MATCH($A9,Proposed!$A$7:$A$56,0)),"")))),1,0) -> 1 | G9: =IF(COUNTIFS('Challenge Review'!$A$7:$A$56,$A9,'Challenge Review'!$K$7:$K$56,"<>")=1,IFERROR(INDEX('Challenge Review'!$K$7:$K$56,MATCH($A9,'Challenge Review'!$A$7:$A$56,0)),""),"") -> Unchecked | H9: =IF(AND(AG9=1,IFERROR(INDEX('Review & Decision'!$B$7:$B$56,MATCH($A9,'Review & Decision'!$A$7:$A$56,0)),"")="Evidence-backed",OR(IFERROR(INDEX('Review & Decision'!$C$7:$C$56,MATCH($A9,'Review & Decision'!$A$7:$A$56,0)),"")="Equivalent or better",AND(IFERROR(INDEX('Review & Decision'!$C$7:$C$56,MATCH($A9,'Review & Decision'!$A$7:$A$56,0)),"")="Accepted reduction",COUNTIFS('Review & Decision'!$A$7:$A$56,$A9,'Review & Decision'!$L$7:$L$56,"<>")=1)),COUNTIFS('Review & Decision'!$A$7:$A$56,$A9,'Review & Decision'!$D$7:$D$56,"<>")=1,COUNTIFS('Review & Decision'!$A$7:$A$56,$A9,'Review & Decision'!$F$7:$F$56,"<>")=1,OR(IFERROR(INDEX('Review & Decision'!$E$7:$E$56,MATCH($A9,'Review & Decision'!$A$7:$A$56,0)),"")="Approved",IFERROR(INDEX('Review & Decision'!$E$7:$E$56,MATCH($A9,'Review & Decision'!$A$7:$A$56,0)),"")="Implemented"),ISNUMBER(IFERROR(INDEX('Review & Decision'!$G$7:$G$56,MATCH($A9,'Review & Decision'!$A$7:$A$56,0)),"")),IFERROR(INDEX('Review & Decision'!$G$7:$G$56,MATCH($A9,'Review & Decision'!$A$7:$A$56,0)),"")>0,IFERROR(INDEX('Review & Decision'!$G$7:$G$56,MATCH($A9,'Review & Decision'!$A$7:$A$56,0)),"")<=Settings!$B$7,ISNUMBER(IFERROR(INDEX('Review & Decision'!$I$7:$I$56,MATCH($A9,'Review & Decision'!$A$7:$A$56,0)),"")),IFERROR(INDEX('Review & Decision'!$I$7:$I$56,MATCH($A9,'Review & Decision'!$A$7:$A$56,0)),"")>0,IFERROR(INDEX('Review & Decision'!$I$7:$I$56,MATCH($A9,'Review & Decision'!$A$7:$A$56,0)),"")<=Settings!$B$7,IFERROR(INDEX('Review & Decision'!$I$7:$I$56,MATCH($A9,'Review & Decision'!$A$7:$A$56,0)),"")>=IFERROR(INDEX('Review & Decision'!$G$7:$G$56,MATCH($A9,'Review & Decision'!$A$7:$A$56,0)),""),COUNTIFS('Review & Decision'!$A$7:$A$56,$A9,'Review & Decision'!$J$7:$J$56,"<>")=1,COUNTIFS('Review & Decision'!$A$7:$A$56,$A9,'Review & Decision'!$K$7:$K$56,"<>")=1,ISNUMBER(IFERROR(INDEX('Review & Decision'!$J$7:$J$56,MATCH($A9,'Review & Decision'!$A$7:$A$56,0)),"")),IFERROR(INDEX('Review & Decision'!$J$7:$J$56,MATCH($A9,'Review & Decision'!$A$7:$A$56,0)),"")>=0,IFERROR(INDEX('Review & Decision'!$J$7:$J$56,MATCH($A9,'Review & Decision'!$A$7:$A$56,0)),"")<=1,ISNUMBER(IFERROR(INDEX('Review & Decision'!$K$7:$K$56,MATCH($A9,'Review & Decision'!$A$7:$A$56,0)),"")),IFERROR(INDEX('Review & Decision'!$K$7:$K$56,MATCH($A9,'Review & Decision'!$A$7:$A$56,0)),"")>=0,IFERROR(INDEX('Review & Decision'!$K$7:$K$56,MATCH($A9,'Review & Decision'!$A$7:$A$56,0)),"")<=1,ISNUMBER(Settings!$B$7),Settings!$B$7>0,OR(Settings!$B$8="Approved + measured",Settings!$B$8="Measured only"),LEN(TRIM(IF(COUNTIFS('Review & Decision'!$A$7:$A$56,$A9,'Review & Decision'!$D$7:$D$56,"<>")=1,IFERROR(INDEX('Review & Decision'!$D$7:$D$56,MATCH($A9,'Review & Decision'!$A$7:$A$56,0)),""),"")))>0,LEN(TRIM(IF(COUNTIFS('Review & Decision'!$A$7:$A$56,$A9,'Review & Decision'!$F$7:$F$56,"<>")=1,IFERROR(INDEX('Review & Decision'!$F$7:$F$56,MATCH($A9,'Review & Decision'!$A$7:$A$56,0)),""),"")))>0,OR(IFERROR(INDEX('Review & Decision'!$C$7:$C$56,MATCH($A9,'Review & Decision'!$A$7:$A$56,0)),"")<>"Accepted reduction",LEN(TRIM(IF(COUNTIFS('Review & Decision'!$A$7:$A$56,$A9,'Review & Decision'!$L$7:$L$56,"<>")=1,IFERROR(INDEX('Review & Decision'!$L$7:$L$56,MATCH($A9,'Review & Decision'!$A$7:$A$56,0)),""),"")))>0)),1,0) -> 0 | I9: =IF(AND(AG9=1,IFERROR(INDEX(Actuals!$M$7:$M$56,MATCH($A9,Actuals!$A$7:$A$56,0)),"")="Ready",IFERROR(INDEX(Actuals!$D$7:$D$56,MATCH($A9,Actuals!$A$7:$A$56,0)),"")>=IFERROR(INDEX('Review & Decision'!$I$7:$I$56,MATCH($A9,'Review & Decision'!$A$7:$A$56,0)),"")),1,0) -> 0 | J9: =IF(AG9=0,"Fix duplicate / missing case ID",IF(B9="Inactive","Unused slot",IF(B9="Example","Example only — never in live planning",IF(D9=0,"Complete case scope and proposal",IF(E9=0,"Complete current inputs; confirm zeros",IF(F9=0,"Complete full proposed profile",IF(G9="Blocked","Blocked — resolve challenge concern",IF(AJ9="Rejected","Rejected — excluded from planning",IF(AND(AI9="Realized",I9=0),"Add measurements, period and evidence",IF(G9<>"Clear","Complete and sign challenge review",IF(H9=0,"Approve evidence, dates and usable shares",IF(AP9="Retain","Retained — no released resource",IF(L9=1,"Measured result eligible",IF(K9=1,"Approved forecast eligible","Modeled only — not allocatable")))))))))))))) -> Example only — never in live planning | K9: =IF(AND(B9="Live",AH9=1,G9="Clear",H9=1,AI9="Validated",AP9<>"Retain"),1,0) -> 0 | L9: =IF(AND(B9="Live",AH9=1,G9="Clear",H9=1,I9=1,AI9="Realized",AJ9="Implemented",AP9<>"Retain"),1,0) -> 0 | M9: =IF(OR(L9=1,AND(K9=1,Settings!$B$8="Approved + measured")),1,0) -> 0 | N9: =IF(E9=1,IFERROR(INDEX(Current!$H$7:$H$56,MATCH($A9,Current!$A$7:$A$56,0)),""),"") -> 2296.6667 | O9: =IF(F9=1,IFERROR(INDEX(Proposed!$I$7:$I$56,MATCH($A9,Proposed!$A$7:$A$56,0)),""),"") -> 400 | P9: =IF(AH9=1,N9-O9,"") -> 1896.6667 | Q9: =IF(E9=1,IFERROR(INDEX(Current!$I$7:$I$56,MATCH($A9,Current!$A$7:$A$56,0)),""),"") -> 200 | R9: =IF(F9=1,IFERROR(INDEX(Proposed!$J$7:$J$56,MATCH($A9,Proposed!$A$7:$A$56,0)),""),"") -> 60 | S9: =IF(AH9=1,Q9-R9,"") -> 140 | T9: =IF(E9=1,IFERROR(INDEX(Current!$E$7:$E$56,MATCH($A9,Current!$A$7:$A$56,0)),""),"") -> 0 | U9: =IF(F9=1,IFERROR(INDEX(Proposed!$E$7:$E$56,MATCH($A9,Proposed!$A$7:$A$56,0)),""),"") -> 0 | V9: =IF(AH9=1,T9-U9,"") -> 0 | W9: =IF(E9=1,IFERROR(INDEX(Current!$K$7:$K$56,MATCH($A9,Current!$A$7:$A$56,0)),""),"") -> 152800 | X9: =IF(F9=1,IFERROR(INDEX(Proposed!$L$7:$L$56,MATCH($A9,Proposed!$A$7:$A$56,0)),""),"") -> 28500 | Y9: =IF(AH9=1,W9-X9,"") -> 124300 | Z9: =IF(F9=1,IFERROR(INDEX(Proposed!$F$7:$F$56,MATCH($A9,Proposed!$A$7:$A$56,0)),""),"") -> 5000 | AA9: =IF(M9=1,IF(IF(L9=1,AL9,P9)>0,IF(L9=1,AL9,P9)*IFERROR(INDEX('Review & Decision'!$J$7:$J$56,MATCH($A9,'Review & Decision'!$A$7:$A$56,0)),""),IF(L9=1,AL9,P9)),0) -> 0 | AB9: =IF(M9=1,IF(IF(L9=1,AM9,S9)>0,IF(L9=1,AM9,S9)*IFERROR(INDEX('Review & Decision'!$K$7:$K$56,MATCH($A9,'Review & Decision'!$A$7:$A$56,0)),""),IF(L9=1,AM9,S9)),0) -> 0 | AC9: =IF(M9=1,IF(L9=1,AN9,V9),0) -> 0 | AD9: =IF(AND(M9=1,L9=0),Z9,0) -> 0 | AE9: =IF(AND(B9="Live",AI9="Realized"),1,0) -> 0 | AF9: =IF(AND(AE9=1,I9=0),"Missing measured evidence","No measurement warning") -> No measurement warning | AG9: =IF(AND(COUNTIF(Cases!$A$7:$A$56,$A9)=1,COUNTIF(Current!$A$7:$A$56,$A9)=1,COUNTIF(Proposed!$A$7:$A$56,$A9)=1,COUNTIF('Review & Decision'!$A$7:$A$56,$A9)=1,COUNTIF('Challenge Review'!$A$7:$A$56,$A9)=1,COUNTIF(Actuals!$A$7:$A$56,$A9)=1,COUNTIF(Classification!$A$7:$A$56,$A9)=1),1,0) -> 1 | AH9: =IF(AND(D9=1,E9=1,F9=1),1,0) -> 1 | AI9: =IF(COUNTIFS('Review & Decision'!$A$7:$A$56,$A9,'Review & Decision'!$H$7:$H$56,"<>")=1,IFERROR(INDEX('Review & Decision'!$H$7:$H$56,MATCH($A9,'Review & Decision'!$A$7:$A$56,0)),""),"") -> Modeled | AJ9: =IF(COUNTIFS('Review & Decision'!$A$7:$A$56,$A9,'Review & Decision'!$E$7:$E$56,"<>")=1,IFERROR(INDEX('Review & Decision'!$E$7:$E$56,MATCH($A9,'Review & Decision'!$A$7:$A$56,0)),""),"") -> Open | AK9: =IF(COUNTIFS('Review & Decision'!$A$7:$A$56,$A9,'Review & Decision'!$B$7:$B$56,"<>")=1,IFERROR(INDEX('Review & Decision'!$B$7:$B$56,MATCH($A9,'Review & Decision'!$A$7:$A$56,0)),""),"") -> Hypothesis | AL9: =IF(I9=1,IFERROR(INDEX(Actuals!$E$7:$E$56,MATCH($A9,Actuals!$A$7:$A$56,0)),""),"") | AM9: =IF(I9=1,IFERROR(INDEX(Actuals!$F$7:$F$56,MATCH($A9,Actuals!$A$7:$A$56,0)),""),"") | AN9: =IF(I9=1,IFERROR(INDEX(Actuals!$G$7:$G$56,MATCH($A9,Actuals!$A$7:$A$56,0)),""),"") | AO9: =IF(I9=1,IFERROR(INDEX(Actuals!$G$7:$G$56,MATCH($A9,Actuals!$A$7:$A$56,0)),"")+IFERROR(INDEX(Actuals!$H$7:$H$56,MATCH($A9,Actuals!$A$7:$A$56,0)),""),"") | AP9: =IF(COUNTIFS(Cases!$A$7:$A$56,$A9,Cases!$G$7:$G$56,"<>")=1,IFERROR(INDEX(Cases!$G$7:$G$56,MATCH($A9,Cases!$A$7:$A$56,0)),""),"") -> Simplify
A10: C004 | B10: =IF(COUNTIFS(Cases!$A$7:$A$56,$A10,Cases!$B$7:$B$56,"<>")=1,IFERROR(INDEX(Cases!$B$7:$B$56,MATCH($A10,Cases!$A$7:$A$56,0)),""),"") -> Example | C10: =IF(COUNTIFS(Cases!$A$7:$A$56,$A10,Cases!$C$7:$C$56,"<>")=1,IFERROR(INDEX(Cases!$C$7:$C$56,MATCH($A10,Cases!$A$7:$A$56,0)),""),"") -> Quarterly access reviews | D10: =IF(AND(AG10=1,OR(B10="Example",B10="Live"),OR(AP10="Simplify",AP10="Replace",AP10="Reduce scope",AP10="Retire",AP10="Retain"),COUNTIFS(Cases!$A$7:$A$56,$A10,Cases!$C$7:$C$56,"<>")=1,COUNTIFS(Cases!$A$7:$A$56,$A10,Cases!$D$7:$D$56,"<>")=1,COUNTIFS(Cases!$A$7:$A$56,$A10,Cases!$E$7:$E$56,"<>")=1,COUNTIFS(Cases!$A$7:$A$56,$A10,Cases!$F$7:$F$56,"<>")=1,COUNTIFS(Cases!$A$7:$A$56,$A10,Cases!$H$7:$H$56,"<>")=1,COUNTIFS(Cases!$A$7:$A$56,$A10,Cases!$I$7:$I$56,"<>")=1,LEN(TRIM(IF(COUNTIFS(Cases!$A$7:$A$56,$A10,Cases!$C$7:$C$56,"<>")=1,IFERROR(INDEX(Cases!$C$7:$C$56,MATCH($A10,Cases!$A$7:$A$56,0)),""),"")))>0,LEN(TRIM(IF(COUNTIFS(Cases!$A$7:$A$56,$A10,Cases!$D$7:$D$56,"<>")=1,IFERROR(INDEX(Cases!$D$7:$D$56,MATCH($A10,Cases!$A$7:$A$56,0)),""),"")))>0,LEN(TRIM(IF(COUNTIFS(Cases!$A$7:$A$56,$A10,Cases!$E$7:$E$56,"<>")=1,IFERROR(INDEX(Cases!$E$7:$E$56,MATCH($A10,Cases!$A$7:$A$56,0)),""),"")))>0,LEN(TRIM(IF(COUNTIFS(Cases!$A$7:$A$56,$A10,Cases!$F$7:$F$56,"<>")=1,IFERROR(INDEX(Cases!$F$7:$F$56,MATCH($A10,Cases!$A$7:$A$56,0)),""),"")))>0,LEN(TRIM(IF(COUNTIFS(Cases!$A$7:$A$56,$A10,Cases!$H$7:$H$56,"<>")=1,IFERROR(INDEX(Cases!$H$7:$H$56,MATCH($A10,Cases!$A$7:$A$56,0)),""),"")))>0,LEN(TRIM(IF(COUNTIFS(Cases!$A$7:$A$56,$A10,Cases!$I$7:$I$56,"<>")=1,IFERROR(INDEX(Cases!$I$7:$I$56,MATCH($A10,Cases!$A$7:$A$56,0)),""),"")))>0),1,0) -> 1 | E10: =IF(AND(AG10=1,IFERROR(INDEX(Current!$G$7:$G$56,MATCH($A10,Current!$A$7:$A$56,0)),"")="Ready"),1,0) -> 1 | F10: =IF(AND(AG10=1,IFERROR(INDEX(Proposed!$H$7:$H$56,MATCH($A10,Proposed!$A$7:$A$56,0)),"")="Ready",OR(AP10<>"Retain",AND(IFERROR(INDEX(Current!$B$7:$B$56,MATCH($A10,Current!$A$7:$A$56,0)),"")=IFERROR(INDEX(Proposed!$B$7:$B$56,MATCH($A10,Proposed!$A$7:$A$56,0)),""),IFERROR(INDEX(Current!$C$7:$C$56,MATCH($A10,Current!$A$7:$A$56,0)),"")=IFERROR(INDEX(Proposed!$C$7:$C$56,MATCH($A10,Proposed!$A$7:$A$56,0)),""),IFERROR(INDEX(Current!$D$7:$D$56,MATCH($A10,Current!$A$7:$A$56,0)),"")=IFERROR(INDEX(Proposed!$D$7:$D$56,MATCH($A10,Proposed!$A$7:$A$56,0)),""),IFERROR(INDEX(Current!$E$7:$E$56,MATCH($A10,Current!$A$7:$A$56,0)),"")=IFERROR(INDEX(Proposed!$E$7:$E$56,MATCH($A10,Proposed!$A$7:$A$56,0)),"")))),1,0) -> 1 | G10: =IF(COUNTIFS('Challenge Review'!$A$7:$A$56,$A10,'Challenge Review'!$K$7:$K$56,"<>")=1,IFERROR(INDEX('Challenge Review'!$K$7:$K$56,MATCH($A10,'Challenge Review'!$A$7:$A$56,0)),""),"") -> Unchecked | H10: =IF(AND(AG10=1,IFERROR(INDEX('Review & Decision'!$B$7:$B$56,MATCH($A10,'Review & Decision'!$A$7:$A$56,0)),"")="Evidence-backed",OR(IFERROR(INDEX('Review & Decision'!$C$7:$C$56,MATCH($A10,'Review & Decision'!$A$7:$A$56,0)),"")="Equivalent or better",AND(IFERROR(INDEX('Review & Decision'!$C$7:$C$56,MATCH($A10,'Review & Decision'!$A$7:$A$56,0)),"")="Accepted reduction",COUNTIFS('Review & Decision'!$A$7:$A$56,$A10,'Review & Decision'!$L$7:$L$56,"<>")=1)),COUNTIFS('Review & Decision'!$A$7:$A$56,$A10,'Review & Decision'!$D$7:$D$56,"<>")=1,COUNTIFS('Review & Decision'!$A$7:$A$56,$A10,'Review & Decision'!$F$7:$F$56,"<>")=1,OR(IFERROR(INDEX('Review & Decision'!$E$7:$E$56,MATCH($A10,'Review & Decision'!$A$7:$A$56,0)),"")="Approved",IFERROR(INDEX('Review & Decision'!$E$7:$E$56,MATCH($A10,'Review & Decision'!$A$7:$A$56,0)),"")="Implemented"),ISNUMBER(IFERROR(INDEX('Review & Decision'!$G$7:$G$56,MATCH($A10,'Review & Decision'!$A$7:$A$56,0)),"")),IFERROR(INDEX('Review & Decision'!$G$7:$G$56,MATCH($A10,'Review & Decision'!$A$7:$A$56,0)),"")>0,IFERROR(INDEX('Review & Decision'!$G$7:$G$56,MATCH($A10,'Review & Decision'!$A$7:$A$56,0)),"")<=Settings!$B$7,ISNUMBER(IFERROR(INDEX('Review & Decision'!$I$7:$I$56,MATCH($A10,'Review & Decision'!$A$7:$A$56,0)),"")),IFERROR(INDEX('Review & Decision'!$I$7:$I$56,MATCH($A10,'Review & Decision'!$A$7:$A$56,0)),"")>0,IFERROR(INDEX('Review & Decision'!$I$7:$I$56,MATCH($A10,'Review & Decision'!$A$7:$A$56,0)),"")<=Settings!$B$7,IFERROR(INDEX('Review & Decision'!$I$7:$I$56,MATCH($A10,'Review & Decision'!$A$7:$A$56,0)),"")>=IFERROR(INDEX('Review & Decision'!$G$7:$G$56,MATCH($A10,'Review & Decision'!$A$7:$A$56,0)),""),COUNTIFS('Review & Decision'!$A$7:$A$56,$A10,'Review & Decision'!$J$7:$J$56,"<>")=1,COUNTIFS('Review & Decision'!$A$7:$A$56,$A10,'Review & Decision'!$K$7:$K$56,"<>")=1,ISNUMBER(IFERROR(INDEX('Review & Decision'!$J$7:$J$56,MATCH($A10,'Review & Decision'!$A$7:$A$56,0)),"")),IFERROR(INDEX('Review & Decision'!$J$7:$J$56,MATCH($A10,'Review & Decision'!$A$7:$A$56,0)),"")>=0,IFERROR(INDEX('Review & Decision'!$J$7:$J$56,MATCH($A10,'Review & Decision'!$A$7:$A$56,0)),"")<=1,ISNUMBER(IFERROR(INDEX('Review & Decision'!$K$7:$K$56,MATCH($A10,'Review & Decision'!$A$7:$A$56,0)),"")),IFERROR(INDEX('Review & Decision'!$K$7:$K$56,MATCH($A10,'Review & Decision'!$A$7:$A$56,0)),"")>=0,IFERROR(INDEX('Review & Decision'!$K$7:$K$56,MATCH($A10,'Review & Decision'!$A$7:$A$56,0)),"")<=1,ISNUMBER(Settings!$B$7),Settings!$B$7>0,OR(Settings!$B$8="Approved + measured",Settings!$B$8="Measured only"),LEN(TRIM(IF(COUNTIFS('Review & Decision'!$A$7:$A$56,$A10,'Review & Decision'!$D$7:$D$56,"<>")=1,IFERROR(INDEX('Review & Decision'!$D$7:$D$56,MATCH($A10,'Review & Decision'!$A$7:$A$56,0)),""),"")))>0,LEN(TRIM(IF(COUNTIFS('Review & Decision'!$A$7:$A$56,$A10,'Review & Decision'!$F$7:$F$56,"<>")=1,IFERROR(INDEX('Review & Decision'!$F$7:$F$56,MATCH($A10,'Review & Decision'!$A$7:$A$56,0)),""),"")))>0,OR(IFERROR(INDEX('Review & Decision'!$C$7:$C$56,MATCH($A10,'Review & Decision'!$A$7:$A$56,0)),"")<>"Accepted reduction",LEN(TRIM(IF(COUNTIFS('Review & Decision'!$A$7:$A$56,$A10,'Review & Decision'!$L$7:$L$56,"<>")=1,IFERROR(INDEX('Review & Decision'!$L$7:$L$56,MATCH($A10,'Review & Decision'!$A$7:$A$56,0)),""),"")))>0)),1,0) -> 0 | I10: =IF(AND(AG10=1,IFERROR(INDEX(Actuals!$M$7:$M$56,MATCH($A10,Actuals!$A$7:$A$56,0)),"")="Ready",IFERROR(INDEX(Actuals!$D$7:$D$56,MATCH($A10,Actuals!$A$7:$A$56,0)),"")>=IFERROR(INDEX('Review & Decision'!$I$7:$I$56,MATCH($A10,'Review & Decision'!$A$7:$A$56,0)),"")),1,0) -> 0 | J10: =IF(AG10=0,"Fix duplicate / missing case ID",IF(B10="Inactive","Unused slot",IF(B10="Example","Example only — never in live planning",IF(D10=0,"Complete case scope and proposal",IF(E10=0,"Complete current inputs; confirm zeros",IF(F10=0,"Complete full proposed profile",IF(G10="Blocked","Blocked — resolve challenge concern",IF(AJ10="Rejected","Rejected — excluded from planning",IF(AND(AI10="Realized",I10=0),"Add measurements, period and evidence",IF(G10<>"Clear","Complete and sign challenge review",IF(H10=0,"Approve evidence, dates and usable shares",IF(AP10="Retain","Retained — no released resource",IF(L10=1,"Measured result eligible",IF(K10=1,"Approved forecast eligible","Modeled only — not allocatable")))))))))))))) -> Example only — never in live planning | K10: =IF(AND(B10="Live",AH10=1,G10="Clear",H10=1,AI10="Validated",AP10<>"Retain"),1,0) -> 0 | L10: =IF(AND(B10="Live",AH10=1,G10="Clear",H10=1,I10=1,AI10="Realized",AJ10="Implemented",AP10<>"Retain"),1,0) -> 0 | M10: =IF(OR(L10=1,AND(K10=1,Settings!$B$8="Approved + measured")),1,0) -> 0 | N10: =IF(E10=1,IFERROR(INDEX(Current!$H$7:$H$56,MATCH($A10,Current!$A$7:$A$56,0)),""),"") -> 800 | O10: =IF(F10=1,IFERROR(INDEX(Proposed!$I$7:$I$56,MATCH($A10,Proposed!$A$7:$A$56,0)),""),"") -> 100 | P10: =IF(AH10=1,N10-O10,"") -> 700 | Q10: =IF(E10=1,IFERROR(INDEX(Current!$I$7:$I$56,MATCH($A10,Current!$A$7:$A$56,0)),""),"") -> 160 | R10: =IF(F10=1,IFERROR(INDEX(Proposed!$J$7:$J$56,MATCH($A10,Proposed!$A$7:$A$56,0)),""),"") -> 40 | S10: =IF(AH10=1,Q10-R10,"") -> 120 | T10: =IF(E10=1,IFERROR(INDEX(Current!$E$7:$E$56,MATCH($A10,Current!$A$7:$A$56,0)),""),"") -> 0 | U10: =IF(F10=1,IFERROR(INDEX(Proposed!$E$7:$E$56,MATCH($A10,Proposed!$A$7:$A$56,0)),""),"") -> 15000 | V10: =IF(AH10=1,T10-U10,"") -> -15000 | W10: =IF(E10=1,IFERROR(INDEX(Current!$K$7:$K$56,MATCH($A10,Current!$A$7:$A$56,0)),""),"") -> 84000 | X10: =IF(F10=1,IFERROR(INDEX(Proposed!$L$7:$L$56,MATCH($A10,Proposed!$A$7:$A$56,0)),""),"") -> 27000 | Y10: =IF(AH10=1,W10-X10,"") -> 57000 | Z10: =IF(F10=1,IFERROR(INDEX(Proposed!$F$7:$F$56,MATCH($A10,Proposed!$A$7:$A$56,0)),""),"") -> 25000 | AA10: =IF(M10=1,IF(IF(L10=1,AL10,P10)>0,IF(L10=1,AL10,P10)*IFERROR(INDEX('Review & Decision'!$J$7:$J$56,MATCH($A10,'Review & Decision'!$A$7:$A$56,0)),""),IF(L10=1,AL10,P10)),0) -> 0 | AB10: =IF(M10=1,IF(IF(L10=1,AM10,S10)>0,IF(L10=1,AM10,S10)*IFERROR(INDEX('Review & Decision'!$K$7:$K$56,MATCH($A10,'Review & Decision'!$A$7:$A$56,0)),""),IF(L10=1,AM10,S10)),0) -> 0 | AC10: =IF(M10=1,IF(L10=1,AN10,V10),0) -> 0 | AD10: =IF(AND(M10=1,L10=0),Z10,0) -> 0 | AE10: =IF(AND(B10="Live",AI10="Realized"),1,0) -> 0 | AF10: =IF(AND(AE10=1,I10=0),"Missing measured evidence","No measurement warning") -> No measurement warning | AG10: =IF(AND(COUNTIF(Cases!$A$7:$A$56,$A10)=1,COUNTIF(Current!$A$7:$A$56,$A10)=1,COUNTIF(Proposed!$A$7:$A$56,$A10)=1,COUNTIF('Review & Decision'!$A$7:$A$56,$A10)=1,COUNTIF('Challenge Review'!$A$7:$A$56,$A10)=1,COUNTIF(Actuals!$A$7:$A$56,$A10)=1,COUNTIF(Classification!$A$7:$A$56,$A10)=1),1,0) -> 1 | AH10: =IF(AND(D10=1,E10=1,F10=1),1,0) -> 1 | AI10: =IF(COUNTIFS('Review & Decision'!$A$7:$A$56,$A10,'Review & Decision'!$H$7:$H$56,"<>")=1,IFERROR(INDEX('Review & Decision'!$H$7:$H$56,MATCH($A10,'Review & Decision'!$A$7:$A$56,0)),""),"") -> Modeled | AJ10: =IF(COUNTIFS('Review & Decision'!$A$7:$A$56,$A10,'Review & Decision'!$E$7:$E$56,"<>")=1,IFERROR(INDEX('Review & Decision'!$E$7:$E$56,MATCH($A10,'Review & Decision'!$A$7:$A$56,0)),""),"") -> Open | AK10: =IF(COUNTIFS('Review & Decision'!$A$7:$A$56,$A10,'Review & Decision'!$B$7:$B$56,"<>")=1,IFERROR(INDEX('Review & Decision'!$B$7:$B$56,MATCH($A10,'Review & Decision'!$A$7:$A$56,0)),""),"") -> Hypothesis | AL10: =IF(I10=1,IFERROR(INDEX(Actuals!$E$7:$E$56,MATCH($A10,Actuals!$A$7:$A$56,0)),""),"") | AM10: =IF(I10=1,IFERROR(INDEX(Actuals!$F$7:$F$56,MATCH($A10,Actuals!$A$7:$A$56,0)),""),"") | AN10: =IF(I10=1,IFERROR(INDEX(Actuals!$G$7:$G$56,MATCH($A10,Actuals!$A$7:$A$56,0)),""),"") | AO10: =IF(I10=1,IFERROR(INDEX(Actuals!$G$7:$G$56,MATCH($A10,Actuals!$A$7:$A$56,0)),"")+IFERROR(INDEX(Actuals!$H$7:$H$56,MATCH($A10,Actuals!$A$7:$A$56,0)),""),"") | AP10: =IF(COUNTIFS(Cases!$A$7:$A$56,$A10,Cases!$G$7:$G$56,"<>")=1,IFERROR(INDEX(Cases!$G$7:$G$56,MATCH($A10,Cases!$A$7:$A$56,0)),""),"") -> Replace
A11: C005 | B11: =IF(COUNTIFS(Cases!$A$7:$A$56,$A11,Cases!$B$7:$B$56,"<>")=1,IFERROR(INDEX(Cases!$B$7:$B$56,MATCH($A11,Cases!$A$7:$A$56,0)),""),"") -> Example | C11: =IF(COUNTIFS(Cases!$A$7:$A$56,$A11,Cases!$C$7:$C$56,"<>")=1,IFERROR(INDEX(Cases!$C$7:$C$56,MATCH($A11,Cases!$A$7:$A$56,0)),""),"") -> Supplier security questionnaires | D11: =IF(AND(AG11=1,OR(B11="Example",B11="Live"),OR(AP11="Simplify",AP11="Replace",AP11="Reduce scope",AP11="Retire",AP11="Retain"),COUNTIFS(Cases!$A$7:$A$56,$A11,Cases!$C$7:$C$56,"<>")=1,COUNTIFS(Cases!$A$7:$A$56,$A11,Cases!$D$7:$D$56,"<>")=1,COUNTIFS(Cases!$A$7:$A$56,$A11,Cases!$E$7:$E$56,"<>")=1,COUNTIFS(Cases!$A$7:$A$56,$A11,Cases!$F$7:$F$56,"<>")=1,COUNTIFS(Cases!$A$7:$A$56,$A11,Cases!$H$7:$H$56,"<>")=1,COUNTIFS(Cases!$A$7:$A$56,$A11,Cases!$I$7:$I$56,"<>")=1,LEN(TRIM(IF(COUNTIFS(Cases!$A$7:$A$56,$A11,Cases!$C$7:$C$56,"<>")=1,IFERROR(INDEX(Cases!$C$7:$C$56,MATCH($A11,Cases!$A$7:$A$56,0)),""),"")))>0,LEN(TRIM(IF(COUNTIFS(Cases!$A$7:$A$56,$A11,Cases!$D$7:$D$56,"<>")=1,IFERROR(INDEX(Cases!$D$7:$D$56,MATCH($A11,Cases!$A$7:$A$56,0)),""),"")))>0,LEN(TRIM(IF(COUNTIFS(Cases!$A$7:$A$56,$A11,Cases!$E$7:$E$56,"<>")=1,IFERROR(INDEX(Cases!$E$7:$E$56,MATCH($A11,Cases!$A$7:$A$56,0)),""),"")))>0,LEN(TRIM(IF(COUNTIFS(Cases!$A$7:$A$56,$A11,Cases!$F$7:$F$56,"<>")=1,IFERROR(INDEX(Cases!$F$7:$F$56,MATCH($A11,Cases!$A$7:$A$56,0)),""),"")))>0,LEN(TRIM(IF(COUNTIFS(Cases!$A$7:$A$56,$A11,Cases!$H$7:$H$56,"<>")=1,IFERROR(INDEX(Cases!$H$7:$H$56,MATCH($A11,Cases!$A$7:$A$56,0)),""),"")))>0,LEN(TRIM(IF(COUNTIFS(Cases!$A$7:$A$56,$A11,Cases!$I$7:$I$56,"<>")=1,IFERROR(INDEX(Cases!$I$7:$I$56,MATCH($A11,Cases!$A$7:$A$56,0)),""),"")))>0),1,0) -> 1 | E11: =IF(AND(AG11=1,IFERROR(INDEX(Current!$G$7:$G$56,MATCH($A11,Current!$A$7:$A$56,0)),"")="Ready"),1,0) -> 1 | F11: =IF(AND(AG11=1,IFERROR(INDEX(Proposed!$H$7:$H$56,MATCH($A11,Proposed!$A$7:$A$56,0)),"")="Ready",OR(AP11<>"Retain",AND(IFERROR(INDEX(Current!$B$7:$B$56,MATCH($A11,Current!$A$7:$A$56,0)),"")=IFERROR(INDEX(Proposed!$B$7:$B$56,MATCH($A11,Proposed!$A$7:$A$56,0)),""),IFERROR(INDEX(Current!$C$7:$C$56,MATCH($A11,Current!$A$7:$A$56,0)),"")=IFERROR(INDEX(Proposed!$C$7:$C$56,MATCH($A11,Proposed!$A$7:$A$56,0)),""),IFERROR(INDEX(Current!$D$7:$D$56,MATCH($A11,Current!$A$7:$A$56,0)),"")=IFERROR(INDEX(Proposed!$D$7:$D$56,MATCH($A11,Proposed!$A$7:$A$56,0)),""),IFERROR(INDEX(Current!$E$7:$E$56,MATCH($A11,Current!$A$7:$A$56,0)),"")=IFERROR(INDEX(Proposed!$E$7:$E$56,MATCH($A11,Proposed!$A$7:$A$56,0)),"")))),1,0) -> 1 | G11: =IF(COUNTIFS('Challenge Review'!$A$7:$A$56,$A11,'Challenge Review'!$K$7:$K$56,"<>")=1,IFERROR(INDEX('Challenge Review'!$K$7:$K$56,MATCH($A11,'Challenge Review'!$A$7:$A$56,0)),""),"") -> Unchecked | H11: =IF(AND(AG11=1,IFERROR(INDEX('Review & Decision'!$B$7:$B$56,MATCH($A11,'Review & Decision'!$A$7:$A$56,0)),"")="Evidence-backed",OR(IFERROR(INDEX('Review & Decision'!$C$7:$C$56,MATCH($A11,'Review & Decision'!$A$7:$A$56,0)),"")="Equivalent or better",AND(IFERROR(INDEX('Review & Decision'!$C$7:$C$56,MATCH($A11,'Review & Decision'!$A$7:$A$56,0)),"")="Accepted reduction",COUNTIFS('Review & Decision'!$A$7:$A$56,$A11,'Review & Decision'!$L$7:$L$56,"<>")=1)),COUNTIFS('Review & Decision'!$A$7:$A$56,$A11,'Review & Decision'!$D$7:$D$56,"<>")=1,COUNTIFS('Review & Decision'!$A$7:$A$56,$A11,'Review & Decision'!$F$7:$F$56,"<>")=1,OR(IFERROR(INDEX('Review & Decision'!$E$7:$E$56,MATCH($A11,'Review & Decision'!$A$7:$A$56,0)),"")="Approved",IFERROR(INDEX('Review & Decision'!$E$7:$E$56,MATCH($A11,'Review & Decision'!$A$7:$A$56,0)),"")="Implemented"),ISNUMBER(IFERROR(INDEX('Review & Decision'!$G$7:$G$56,MATCH($A11,'Review & Decision'!$A$7:$A$56,0)),"")),IFERROR(INDEX('Review & Decision'!$G$7:$G$56,MATCH($A11,'Review & Decision'!$A$7:$A$56,0)),"")>0,IFERROR(INDEX('Review & Decision'!$G$7:$G$56,MATCH($A11,'Review & Decision'!$A$7:$A$56,0)),"")<=Settings!$B$7,ISNUMBER(IFERROR(INDEX('Review & Decision'!$I$7:$I$56,MATCH($A11,'Review & Decision'!$A$7:$A$56,0)),"")),IFERROR(INDEX('Review & Decision'!$I$7:$I$56,MATCH($A11,'Review & Decision'!$A$7:$A$56,0)),"")>0,IFERROR(INDEX('Review & Decision'!$I$7:$I$56,MATCH($A11,'Review & Decision'!$A$7:$A$56,0)),"")<=Settings!$B$7,IFERROR(INDEX('Review & Decision'!$I$7:$I$56,MATCH($A11,'Review & Decision'!$A$7:$A$56,0)),"")>=IFERROR(INDEX('Review & Decision'!$G$7:$G$56,MATCH($A11,'Review & Decision'!$A$7:$A$56,0)),""),COUNTIFS('Review & Decision'!$A$7:$A$56,$A11,'Review & Decision'!$J$7:$J$56,"<>")=1,COUNTIFS('Review & Decision'!$A$7:$A$56,$A11,'Review & Decision'!$K$7:$K$56,"<>")=1,ISNUMBER(IFERROR(INDEX('Review & Decision'!$J$7:$J$56,MATCH($A11,'Review & Decision'!$A$7:$A$56,0)),"")),IFERROR(INDEX('Review & Decision'!$J$7:$J$56,MATCH($A11,'Review & Decision'!$A$7:$A$56,0)),"")>=0,IFERROR(INDEX('Review & Decision'!$J$7:$J$56,MATCH($A11,'Review & Decision'!$A$7:$A$56,0)),"")<=1,ISNUMBER(IFERROR(INDEX('Review & Decision'!$K$7:$K$56,MATCH($A11,'Review & Decision'!$A$7:$A$56,0)),"")),IFERROR(INDEX('Review & Decision'!$K$7:$K$56,MATCH($A11,'Review & Decision'!$A$7:$A$56,0)),"")>=0,IFERROR(INDEX('Review & Decision'!$K$7:$K$56,MATCH($A11,'Review & Decision'!$A$7:$A$56,0)),"")<=1,ISNUMBER(Settings!$B$7),Settings!$B$7>0,OR(Settings!$B$8="Approved + measured",Settings!$B$8="Measured only"),LEN(TRIM(IF(COUNTIFS('Review & Decision'!$A$7:$A$56,$A11,'Review & Decision'!$D$7:$D$56,"<>")=1,IFERROR(INDEX('Review & Decision'!$D$7:$D$56,MATCH($A11,'Review & Decision'!$A$7:$A$56,0)),""),"")))>0,LEN(TRIM(IF(COUNTIFS('Review & Decision'!$A$7:$A$56,$A11,'Review & Decision'!$F$7:$F$56,"<>")=1,IFERROR(INDEX('Review & Decision'!$F$7:$F$56,MATCH($A11,'Review & Decision'!$A$7:$A$56,0)),""),"")))>0,OR(IFERROR(INDEX('Review & Decision'!$C$7:$C$56,MATCH($A11,'Review & Decision'!$A$7:$A$56,0)),"")<>"Accepted reduction",LEN(TRIM(IF(COUNTIFS('Review & Decision'!$A$7:$A$56,$A11,'Review & Decision'!$L$7:$L$56,"<>")=1,IFERROR(INDEX('Review & Decision'!$L$7:$L$56,MATCH($A11,'Review & Decision'!$A$7:$A$56,0)),""),"")))>0)),1,0) -> 0 | I11: =IF(AND(AG11=1,IFERROR(INDEX(Actuals!$M$7:$M$56,MATCH($A11,Actuals!$A$7:$A$56,0)),"")="Ready",IFERROR(INDEX(Actuals!$D$7:$D$56,MATCH($A11,Actuals!$A$7:$A$56,0)),"")>=IFERROR(INDEX('Review & Decision'!$I$7:$I$56,MATCH($A11,'Review & Decision'!$A$7:$A$56,0)),"")),1,0) -> 0 | J11: =IF(AG11=0,"Fix duplicate / missing case ID",IF(B11="Inactive","Unused slot",IF(B11="Example","Example only — never in live planning",IF(D11=0,"Complete case scope and proposal",IF(E11=0,"Complete current inputs; confirm zeros",IF(F11=0,"Complete full proposed profile",IF(G11="Blocked","Blocked — resolve challenge concern",IF(AJ11="Rejected","Rejected — excluded from planning",IF(AND(AI11="Realized",I11=0),"Add measurements, period and evidence",IF(G11<>"Clear","Complete and sign challenge review",IF(H11=0,"Approve evidence, dates and usable shares",IF(AP11="Retain","Retained — no released resource",IF(L11=1,"Measured result eligible",IF(K11=1,"Approved forecast eligible","Modeled only — not allocatable")))))))))))))) -> Example only — never in live planning | K11: =IF(AND(B11="Live",AH11=1,G11="Clear",H11=1,AI11="Validated",AP11<>"Retain"),1,0) -> 0 | L11: =IF(AND(B11="Live",AH11=1,G11="Clear",H11=1,I11=1,AI11="Realized",AJ11="Implemented",AP11<>"Retain"),1,0) -> 0 | M11: =IF(OR(L11=1,AND(K11=1,Settings!$B$8="Approved + measured")),1,0) -> 0 | N11: =IF(E11=1,IFERROR(INDEX(Current!$H$7:$H$56,MATCH($A11,Current!$A$7:$A$56,0)),""),"") -> 0 | O11: =IF(F11=1,IFERROR(INDEX(Proposed!$I$7:$I$56,MATCH($A11,Proposed!$A$7:$A$56,0)),""),"") -> 0 | P11: =IF(AH11=1,N11-O11,"") -> 0 | Q11: =IF(E11=1,IFERROR(INDEX(Current!$I$7:$I$56,MATCH($A11,Current!$A$7:$A$56,0)),""),"") -> 800 | R11: =IF(F11=1,IFERROR(INDEX(Proposed!$J$7:$J$56,MATCH($A11,Proposed!$A$7:$A$56,0)),""),"") -> 170 | S11: =IF(AH11=1,Q11-R11,"") -> 630 | T11: =IF(E11=1,IFERROR(INDEX(Current!$E$7:$E$56,MATCH($A11,Current!$A$7:$A$56,0)),""),"") -> 0 | U11: =IF(F11=1,IFERROR(INDEX(Proposed!$E$7:$E$56,MATCH($A11,Proposed!$A$7:$A$56,0)),""),"") -> 10000 | V11: =IF(AH11=1,T11-U11,"") -> -10000 | W11: =IF(E11=1,IFERROR(INDEX(Current!$K$7:$K$56,MATCH($A11,Current!$A$7:$A$56,0)),""),"") -> 60000 | X11: =IF(F11=1,IFERROR(INDEX(Proposed!$L$7:$L$56,MATCH($A11,Proposed!$A$7:$A$56,0)),""),"") -> 22750 | Y11: =IF(AH11=1,W11-X11,"") -> 37250 | Z11: =IF(F11=1,IFERROR(INDEX(Proposed!$F$7:$F$56,MATCH($A11,Proposed!$A$7:$A$56,0)),""),"") -> 8000 | AA11: =IF(M11=1,IF(IF(L11=1,AL11,P11)>0,IF(L11=1,AL11,P11)*IFERROR(INDEX('Review & Decision'!$J$7:$J$56,MATCH($A11,'Review & Decision'!$A$7:$A$56,0)),""),IF(L11=1,AL11,P11)),0) -> 0 | AB11: =IF(M11=1,IF(IF(L11=1,AM11,S11)>0,IF(L11=1,AM11,S11)*IFERROR(INDEX('Review & Decision'!$K$7:$K$56,MATCH($A11,'Review & Decision'!$A$7:$A$56,0)),""),IF(L11=1,AM11,S11)),0) -> 0 | AC11: =IF(M11=1,IF(L11=1,AN11,V11),0) -> 0 | AD11: =IF(AND(M11=1,L11=0),Z11,0) -> 0 | AE11: =IF(AND(B11="Live",AI11="Realized"),1,0) -> 0 | AF11: =IF(AND(AE11=1,I11=0),"Missing measured evidence","No measurement warning") -> No measurement warning | AG11: =IF(AND(COUNTIF(Cases!$A$7:$A$56,$A11)=1,COUNTIF(Current!$A$7:$A$56,$A11)=1,COUNTIF(Proposed!$A$7:$A$56,$A11)=1,COUNTIF('Review & Decision'!$A$7:$A$56,$A11)=1,COUNTIF('Challenge Review'!$A$7:$A$56,$A11)=1,COUNTIF(Actuals!$A$7:$A$56,$A11)=1,COUNTIF(Classification!$A$7:$A$56,$A11)=1),1,0) -> 1 | AH11: =IF(AND(D11=1,E11=1,F11=1),1,0) -> 1 | AI11: =IF(COUNTIFS('Review & Decision'!$A$7:$A$56,$A11,'Review & Decision'!$H$7:$H$56,"<>")=1,IFERROR(INDEX('Review & Decision'!$H$7:$H$56,MATCH($A11,'Review & Decision'!$A$7:$A$56,0)),""),"") -> Modeled | AJ11: =IF(COUNTIFS('Review & Decision'!$A$7:$A$56,$A11,'Review & Decision'!$E$7:$E$56,"<>")=1,IFERROR(INDEX('Review & Decision'!$E$7:$E$56,MATCH($A11,'Review & Decision'!$A$7:$A$56,0)),""),"") -> Open | AK11: =IF(COUNTIFS('Review & Decision'!$A$7:$A$56,$A11,'Review & Decision'!$B$7:$B$56,"<>")=1,IFERROR(INDEX('Review & Decision'!$B$7:$B$56,MATCH($A11,'Review & Decision'!$A$7:$A$56,0)),""),"") -> Hypothesis | AL11: =IF(I11=1,IFERROR(INDEX(Actuals!$E$7:$E$56,MATCH($A11,Actuals!$A$7:$A$56,0)),""),"") | AM11: =IF(I11=1,IFERROR(INDEX(Actuals!$F$7:$F$56,MATCH($A11,Actuals!$A$7:$A$56,0)),""),"") | AN11: =IF(I11=1,IFERROR(INDEX(Actuals!$G$7:$G$56,MATCH($A11,Actuals!$A$7:$A$56,0)),""),"") | AO11: =IF(I11=1,IFERROR(INDEX(Actuals!$G$7:$G$56,MATCH($A11,Actuals!$A$7:$A$56,0)),"")+IFERROR(INDEX(Actuals!$H$7:$H$56,MATCH($A11,Actuals!$A$7:$A$56,0)),""),"") | AP11: =IF(COUNTIFS(Cases!$A$7:$A$56,$A11,Cases!$G$7:$G$56,"<>")=1,IFERROR(INDEX(Cases!$G$7:$G$56,MATCH($A11,Cases!$A$7:$A$56,0)),""),"") -> Replace
A12: C006 | B12: =IF(COUNTIFS(Cases!$A$7:$A$56,$A12,Cases!$B$7:$B$56,"<>")=1,IFERROR(INDEX(Cases!$B$7:$B$56,MATCH($A12,Cases!$A$7:$A$56,0)),""),"") -> Example | C12: =IF(COUNTIFS(Cases!$A$7:$A$56,$A12,Cases!$C$7:$C$56,"<>")=1,IFERROR(INDEX(Cases!$C$7:$C$56,MATCH($A12,Cases!$A$7:$A$56,0)),""),"") -> Vulnerability remediation prioritization | D12: =IF(AND(AG12=1,OR(B12="Example",B12="Live"),OR(AP12="Simplify",AP12="Replace",AP12="Reduce scope",AP12="Retire",AP12="Retain"),COUNTIFS(Cases!$A$7:$A$56,$A12,Cases!$C$7:$C$56,"<>")=1,COUNTIFS(Cases!$A$7:$A$56,$A12,Cases!$D$7:$D$56,"<>")=1,COUNTIFS(Cases!$A$7:$A$56,$A12,Cases!$E$7:$E$56,"<>")=1,COUNTIFS(Cases!$A$7:$A$56,$A12,Cases!$F$7:$F$56,"<>")=1,COUNTIFS(Cases!$A$7:$A$56,$A12,Cases!$H$7:$H$56,"<>")=1,COUNTIFS(Cases!$A$7:$A$56,$A12,Cases!$I$7:$I$56,"<>")=1,LEN(TRIM(IF(COUNTIFS(Cases!$A$7:$A$56,$A12,Cases!$C$7:$C$56,"<>")=1,IFERROR(INDEX(Cases!$C$7:$C$56,MATCH($A12,Cases!$A$7:$A$56,0)),""),"")))>0,LEN(TRIM(IF(COUNTIFS(Cases!$A$7:$A$56,$A12,Cases!$D$7:$D$56,"<>")=1,IFERROR(INDEX(Cases!$D$7:$D$56,MATCH($A12,Cases!$A$7:$A$56,0)),""),"")))>0,LEN(TRIM(IF(COUNTIFS(Cases!$A$7:$A$56,$A12,Cases!$E$7:$E$56,"<>")=1,IFERROR(INDEX(Cases!$E$7:$E$56,MATCH($A12,Cases!$A$7:$A$56,0)),""),"")))>0,LEN(TRIM(IF(COUNTIFS(Cases!$A$7:$A$56,$A12,Cases!$F$7:$F$56,"<>")=1,IFERROR(INDEX(Cases!$F$7:$F$56,MATCH($A12,Cases!$A$7:$A$56,0)),""),"")))>0,LEN(TRIM(IF(COUNTIFS(Cases!$A$7:$A$56,$A12,Cases!$H$7:$H$56,"<>")=1,IFERROR(INDEX(Cases!$H$7:$H$56,MATCH($A12,Cases!$A$7:$A$56,0)),""),"")))>0,LEN(TRIM(IF(COUNTIFS(Cases!$A$7:$A$56,$A12,Cases!$I$7:$I$56,"<>")=1,IFERROR(INDEX(Cases!$I$7:$I$56,MATCH($A12,Cases!$A$7:$A$56,0)),""),"")))>0),1,0) -> 1 | E12: =IF(AND(AG12=1,IFERROR(INDEX(Current!$G$7:$G$56,MATCH($A12,Current!$A$7:$A$56,0)),"")="Ready"),1,0) -> 1 | F12: =IF(AND(AG12=1,IFERROR(INDEX(Proposed!$H$7:$H$56,MATCH($A12,Proposed!$A$7:$A$56,0)),"")="Ready",OR(AP12<>"Retain",AND(IFERROR(INDEX(Current!$B$7:$B$56,MATCH($A12,Current!$A$7:$A$56,0)),"")=IFERROR(INDEX(Proposed!$B$7:$B$56,MATCH($A12,Proposed!$A$7:$A$56,0)),""),IFERROR(INDEX(Current!$C$7:$C$56,MATCH($A12,Current!$A$7:$A$56,0)),"")=IFERROR(INDEX(Proposed!$C$7:$C$56,MATCH($A12,Proposed!$A$7:$A$56,0)),""),IFERROR(INDEX(Current!$D$7:$D$56,MATCH($A12,Current!$A$7:$A$56,0)),"")=IFERROR(INDEX(Proposed!$D$7:$D$56,MATCH($A12,Proposed!$A$7:$A$56,0)),""),IFERROR(INDEX(Current!$E$7:$E$56,MATCH($A12,Current!$A$7:$A$56,0)),"")=IFERROR(INDEX(Proposed!$E$7:$E$56,MATCH($A12,Proposed!$A$7:$A$56,0)),"")))),1,0) -> 1 | G12: =IF(COUNTIFS('Challenge Review'!$A$7:$A$56,$A12,'Challenge Review'!$K$7:$K$56,"<>")=1,IFERROR(INDEX('Challenge Review'!$K$7:$K$56,MATCH($A12,'Challenge Review'!$A$7:$A$56,0)),""),"") -> Unchecked | H12: =IF(AND(AG12=1,IFERROR(INDEX('Review & Decision'!$B$7:$B$56,MATCH($A12,'Review & Decision'!$A$7:$A$56,0)),"")="Evidence-backed",OR(IFERROR(INDEX('Review & Decision'!$C$7:$C$56,MATCH($A12,'Review & Decision'!$A$7:$A$56,0)),"")="Equivalent or better",AND(IFERROR(INDEX('Review & Decision'!$C$7:$C$56,MATCH($A12,'Review & Decision'!$A$7:$A$56,0)),"")="Accepted reduction",COUNTIFS('Review & Decision'!$A$7:$A$56,$A12,'Review & Decision'!$L$7:$L$56,"<>")=1)),COUNTIFS('Review & Decision'!$A$7:$A$56,$A12,'Review & Decision'!$D$7:$D$56,"<>")=1,COUNTIFS('Review & Decision'!$A$7:$A$56,$A12,'Review & Decision'!$F$7:$F$56,"<>")=1,OR(IFERROR(INDEX('Review & Decision'!$E$7:$E$56,MATCH($A12,'Review & Decision'!$A$7:$A$56,0)),"")="Approved",IFERROR(INDEX('Review & Decision'!$E$7:$E$56,MATCH($A12,'Review & Decision'!$A$7:$A$56,0)),"")="Implemented"),ISNUMBER(IFERROR(INDEX('Review & Decision'!$G$7:$G$56,MATCH($A12,'Review & Decision'!$A$7:$A$56,0)),"")),IFERROR(INDEX('Review & Decision'!$G$7:$G$56,MATCH($A12,'Review & Decision'!$A$7:$A$56,0)),"")>0,IFERROR(INDEX('Review & Decision'!$G$7:$G$56,MATCH($A12,'Review & Decision'!$A$7:$A$56,0)),"")<=Settings!$B$7,ISNUMBER(IFERROR(INDEX('Review & Decision'!$I$7:$I$56,MATCH($A12,'Review & Decision'!$A$7:$A$56,0)),"")),IFERROR(INDEX('Review & Decision'!$I$7:$I$56,MATCH($A12,'Review & Decision'!$A$7:$A$56,0)),"")>0,IFERROR(INDEX('Review & Decision'!$I$7:$I$56,MATCH($A12,'Review & Decision'!$A$7:$A$56,0)),"")<=Settings!$B$7,IFERROR(INDEX('Review & Decision'!$I$7:$I$56,MATCH($A12,'Review & Decision'!$A$7:$A$56,0)),"")>=IFERROR(INDEX('Review & Decision'!$G$7:$G$56,MATCH($A12,'Review & Decision'!$A$7:$A$56,0)),""),COUNTIFS('Review & Decision'!$A$7:$A$56,$A12,'Review & Decision'!$J$7:$J$56,"<>")=1,COUNTIFS('Review & Decision'!$A$7:$A$56,$A12,'Review & Decision'!$K$7:$K$56,"<>")=1,ISNUMBER(IFERROR(INDEX('Review & Decision'!$J$7:$J$56,MATCH($A12,'Review & Decision'!$A$7:$A$56,0)),"")),IFERROR(INDEX('Review & Decision'!$J$7:$J$56,MATCH($A12,'Review & Decision'!$A$7:$A$56,0)),"")>=0,IFERROR(INDEX('Review & Decision'!$J$7:$J$56,MATCH($A12,'Review & Decision'!$A$7:$A$56,0)),"")<=1,ISNUMBER(IFERROR(INDEX('Review & Decision'!$K$7:$K$56,MATCH($A12,'Review & Decision'!$A$7:$A$56,0)),"")),IFERROR(INDEX('Review & Decision'!$K$7:$K$56,MATCH($A12,'Review & Decision'!$A$7:$A$56,0)),"")>=0,IFERROR(INDEX('Review & Decision'!$K$7:$K$56,MATCH($A12,'Review & Decision'!$A$7:$A$56,0)),"")<=1,ISNUMBER(Settings!$B$7),Settings!$B$7>0,OR(Settings!$B$8="Approved + measured",Settings!$B$8="Measured only"),LEN(TRIM(IF(COUNTIFS('Review & Decision'!$A$7:$A$56,$A12,'Review & Decision'!$D$7:$D$56,"<>")=1,IFERROR(INDEX('Review & Decision'!$D$7:$D$56,MATCH($A12,'Review & Decision'!$A$7:$A$56,0)),""),"")))>0,LEN(TRIM(IF(COUNTIFS('Review & Decision'!$A$7:$A$56,$A12,'Review & Decision'!$F$7:$F$56,"<>")=1,IFERROR(INDEX('Review & Decision'!$F$7:$F$56,MATCH($A12,'Review & Decision'!$A$7:$A$56,0)),""),"")))>0,OR(IFERROR(INDEX('Review & Decision'!$C$7:$C$56,MATCH($A12,'Review & Decision'!$A$7:$A$56,0)),"")<>"Accepted reduction",LEN(TRIM(IF(COUNTIFS('Review & Decision'!$A$7:$A$56,$A12,'Review & Decision'!$L$7:$L$56,"<>")=1,IFERROR(INDEX('Review & Decision'!$L$7:$L$56,MATCH($A12,'Review & Decision'!$A$7:$A$56,0)),""),"")))>0)),1,0) -> 0 | I12: =IF(AND(AG12=1,IFERROR(INDEX(Actuals!$M$7:$M$56,MATCH($A12,Actuals!$A$7:$A$56,0)),"")="Ready",IFERROR(INDEX(Actuals!$D$7:$D$56,MATCH($A12,Actuals!$A$7:$A$56,0)),"")>=IFERROR(INDEX('Review & Decision'!$I$7:$I$56,MATCH($A12,'Review & Decision'!$A$7:$A$56,0)),"")),1,0) -> 0 | J12: =IF(AG12=0,"Fix duplicate / missing case ID",IF(B12="Inactive","Unused slot",IF(B12="Example","Example only — never in live planning",IF(D12=0,"Complete case scope and proposal",IF(E12=0,"Complete current inputs; confirm zeros",IF(F12=0,"Complete full proposed profile",IF(G12="Blocked","Blocked — resolve challenge concern",IF(AJ12="Rejected","Rejected — excluded from planning",IF(AND(AI12="Realized",I12=0),"Add measurements, period and evidence",IF(G12<>"Clear","Complete and sign challenge review",IF(H12=0,"Approve evidence, dates and usable shares",IF(AP12="Retain","Retained — no released resource",IF(L12=1,"Measured result eligible",IF(K12=1,"Approved forecast eligible","Modeled only — not allocatable")))))))))))))) -> Example only — never in live planning | K12: =IF(AND(B12="Live",AH12=1,G12="Clear",H12=1,AI12="Validated",AP12<>"Retain"),1,0) -> 0 | L12: =IF(AND(B12="Live",AH12=1,G12="Clear",H12=1,I12=1,AI12="Realized",AJ12="Implemented",AP12<>"Retain"),1,0) -> 0 | M12: =IF(OR(L12=1,AND(K12=1,Settings!$B$8="Approved + measured")),1,0) -> 0 | N12: =IF(E12=1,IFERROR(INDEX(Current!$H$7:$H$56,MATCH($A12,Current!$A$7:$A$56,0)),""),"") -> 0 | O12: =IF(F12=1,IFERROR(INDEX(Proposed!$I$7:$I$56,MATCH($A12,Proposed!$A$7:$A$56,0)),""),"") -> 0 | P12: =IF(AH12=1,N12-O12,"") -> 0 | Q12: =IF(E12=1,IFERROR(INDEX(Current!$I$7:$I$56,MATCH($A12,Current!$A$7:$A$56,0)),""),"") -> 1400 | R12: =IF(F12=1,IFERROR(INDEX(Proposed!$J$7:$J$56,MATCH($A12,Proposed!$A$7:$A$56,0)),""),"") -> 1100 | S12: =IF(AH12=1,Q12-R12,"") -> 300 | T12: =IF(E12=1,IFERROR(INDEX(Current!$E$7:$E$56,MATCH($A12,Current!$A$7:$A$56,0)),""),"") -> 0 | U12: =IF(F12=1,IFERROR(INDEX(Proposed!$E$7:$E$56,MATCH($A12,Proposed!$A$7:$A$56,0)),""),"") -> 0 | V12: =IF(AH12=1,T12-U12,"") -> 0 | W12: =IF(E12=1,IFERROR(INDEX(Current!$K$7:$K$56,MATCH($A12,Current!$A$7:$A$56,0)),""),"") -> 105000 | X12: =IF(F12=1,IFERROR(INDEX(Proposed!$L$7:$L$56,MATCH($A12,Proposed!$A$7:$A$56,0)),""),"") -> 82500 | Y12: =IF(AH12=1,W12-X12,"") -> 22500 | Z12: =IF(F12=1,IFERROR(INDEX(Proposed!$F$7:$F$56,MATCH($A12,Proposed!$A$7:$A$56,0)),""),"") -> 5000 | AA12: =IF(M12=1,IF(IF(L12=1,AL12,P12)>0,IF(L12=1,AL12,P12)*IFERROR(INDEX('Review & Decision'!$J$7:$J$56,MATCH($A12,'Review & Decision'!$A$7:$A$56,0)),""),IF(L12=1,AL12,P12)),0) -> 0 | AB12: =IF(M12=1,IF(IF(L12=1,AM12,S12)>0,IF(L12=1,AM12,S12)*IFERROR(INDEX('Review & Decision'!$K$7:$K$56,MATCH($A12,'Review & Decision'!$A$7:$A$56,0)),""),IF(L12=1,AM12,S12)),0) -> 0 | AC12: =IF(M12=1,IF(L12=1,AN12,V12),0) -> 0 | AD12: =IF(AND(M12=1,L12=0),Z12,0) -> 0 | AE12: =IF(AND(B12="Live",AI12="Realized"),1,0) -> 0 | AF12: =IF(AND(AE12=1,I12=0),"Missing measured evidence","No measurement warning") -> No measurement warning | AG12: =IF(AND(COUNTIF(Cases!$A$7:$A$56,$A12)=1,COUNTIF(Current!$A$7:$A$56,$A12)=1,COUNTIF(Proposed!$A$7:$A$56,$A12)=1,COUNTIF('Review & Decision'!$A$7:$A$56,$A12)=1,COUNTIF('Challenge Review'!$A$7:$A$56,$A12)=1,COUNTIF(Actuals!$A$7:$A$56,$A12)=1,COUNTIF(Classification!$A$7:$A$56,$A12)=1),1,0) -> 1 | AH12: =IF(AND(D12=1,E12=1,F12=1),1,0) -> 1 | AI12: =IF(COUNTIFS('Review & Decision'!$A$7:$A$56,$A12,'Review & Decision'!$H$7:$H$56,"<>")=1,IFERROR(INDEX('Review & Decision'!$H$7:$H$56,MATCH($A12,'Review & Decision'!$A$7:$A$56,0)),""),"") -> Modeled | AJ12: =IF(COUNTIFS('Review & Decision'!$A$7:$A$56,$A12,'Review & Decision'!$E$7:$E$56,"<>")=1,IFERROR(INDEX('Review & Decision'!$E$7:$E$56,MATCH($A12,'Review & Decision'!$A$7:$A$56,0)),""),"") -> Open | AK12: =IF(COUNTIFS('Review & Decision'!$A$7:$A$56,$A12,'Review & Decision'!$B$7:$B$56,"<>")=1,IFERROR(INDEX('Review & Decision'!$B$7:$B$56,MATCH($A12,'Review & Decision'!$A$7:$A$56,0)),""),"") -> Hypothesis | AL12: =IF(I12=1,IFERROR(INDEX(Actuals!$E$7:$E$56,MATCH($A12,Actuals!$A$7:$A$56,0)),""),"") | AM12: =IF(I12=1,IFERROR(INDEX(Actuals!$F$7:$F$56,MATCH($A12,Actuals!$A$7:$A$56,0)),""),"") | AN12: =IF(I12=1,IFERROR(INDEX(Actuals!$G$7:$G$56,MATCH($A12,Actuals!$A$7:$A$56,0)),""),"") | AO12: =IF(I12=1,IFERROR(INDEX(Actuals!$G$7:$G$56,MATCH($A12,Actuals!$A$7:$A$56,0)),"")+IFERROR(INDEX(Actuals!$H$7:$H$56,MATCH($A12,Actuals!$A$7:$A$56,0)),""),"") | AP12: =IF(COUNTIFS(Cases!$A$7:$A$56,$A12,Cases!$G$7:$G$56,"<>")=1,IFERROR(INDEX(Cases!$G$7:$G$56,MATCH($A12,Cases!$A$7:$A$56,0)),""),"") -> Simplify
A13: C007 | B13: =IF(COUNTIFS(Cases!$A$7:$A$56,$A13,Cases!$B$7:$B$56,"<>")=1,IFERROR(INDEX(Cases!$B$7:$B$56,MATCH($A13,Cases!$A$7:$A$56,0)),""),"") -> Example | C13: =IF(COUNTIFS(Cases!$A$7:$A$56,$A13,Cases!$C$7:$C$56,"<>")=1,IFERROR(INDEX(Cases!$C$7:$C$56,MATCH($A13,Cases!$A$7:$A$56,0)),""),"") -> Workplace access restrictions | D13: =IF(AND(AG13=1,OR(B13="Example",B13="Live"),OR(AP13="Simplify",AP13="Replace",AP13="Reduce scope",AP13="Retire",AP13="Retain"),COUNTIFS(Cases!$A$7:$A$56,$A13,Cases!$C$7:$C$56,"<>")=1,COUNTIFS(Cases!$A$7:$A$56,$A13,Cases!$D$7:$D$56,"<>")=1,COUNTIFS(Cases!$A$7:$A$56,$A13,Cases!$E$7:$E$56,"<>")=1,COUNTIFS(Cases!$A$7:$A$56,$A13,Cases!$F$7:$F$56,"<>")=1,COUNTIFS(Cases!$A$7:$A$56,$A13,Cases!$H$7:$H$56,"<>")=1,COUNTIFS(Cases!$A$7:$A$56,$A13,Cases!$I$7:$I$56,"<>")=1,LEN(TRIM(IF(COUNTIFS(Cases!$A$7:$A$56,$A13,Cases!$C$7:$C$56,"<>")=1,IFERROR(INDEX(Cases!$C$7:$C$56,MATCH($A13,Cases!$A$7:$A$56,0)),""),"")))>0,LEN(TRIM(IF(COUNTIFS(Cases!$A$7:$A$56,$A13,Cases!$D$7:$D$56,"<>")=1,IFERROR(INDEX(Cases!$D$7:$D$56,MATCH($A13,Cases!$A$7:$A$56,0)),""),"")))>0,LEN(TRIM(IF(COUNTIFS(Cases!$A$7:$A$56,$A13,Cases!$E$7:$E$56,"<>")=1,IFERROR(INDEX(Cases!$E$7:$E$56,MATCH($A13,Cases!$A$7:$A$56,0)),""),"")))>0,LEN(TRIM(IF(COUNTIFS(Cases!$A$7:$A$56,$A13,Cases!$F$7:$F$56,"<>")=1,IFERROR(INDEX(Cases!$F$7:$F$56,MATCH($A13,Cases!$A$7:$A$56,0)),""),"")))>0,LEN(TRIM(IF(COUNTIFS(Cases!$A$7:$A$56,$A13,Cases!$H$7:$H$56,"<>")=1,IFERROR(INDEX(Cases!$H$7:$H$56,MATCH($A13,Cases!$A$7:$A$56,0)),""),"")))>0,LEN(TRIM(IF(COUNTIFS(Cases!$A$7:$A$56,$A13,Cases!$I$7:$I$56,"<>")=1,IFERROR(INDEX(Cases!$I$7:$I$56,MATCH($A13,Cases!$A$7:$A$56,0)),""),"")))>0),1,0) -> 1 | E13: =IF(AND(AG13=1,IFERROR(INDEX(Current!$G$7:$G$56,MATCH($A13,Current!$A$7:$A$56,0)),"")="Ready"),1,0) -> 1 | F13: =IF(AND(AG13=1,IFERROR(INDEX(Proposed!$H$7:$H$56,MATCH($A13,Proposed!$A$7:$A$56,0)),"")="Ready",OR(AP13<>"Retain",AND(IFERROR(INDEX(Current!$B$7:$B$56,MATCH($A13,Current!$A$7:$A$56,0)),"")=IFERROR(INDEX(Proposed!$B$7:$B$56,MATCH($A13,Proposed!$A$7:$A$56,0)),""),IFERROR(INDEX(Current!$C$7:$C$56,MATCH($A13,Current!$A$7:$A$56,0)),"")=IFERROR(INDEX(Proposed!$C$7:$C$56,MATCH($A13,Proposed!$A$7:$A$56,0)),""),IFERROR(INDEX(Current!$D$7:$D$56,MATCH($A13,Current!$A$7:$A$56,0)),"")=IFERROR(INDEX(Proposed!$D$7:$D$56,MATCH($A13,Proposed!$A$7:$A$56,0)),""),IFERROR(INDEX(Current!$E$7:$E$56,MATCH($A13,Current!$A$7:$A$56,0)),"")=IFERROR(INDEX(Proposed!$E$7:$E$56,MATCH($A13,Proposed!$A$7:$A$56,0)),"")))),1,0) -> 1 | G13: =IF(COUNTIFS('Challenge Review'!$A$7:$A$56,$A13,'Challenge Review'!$K$7:$K$56,"<>")=1,IFERROR(INDEX('Challenge Review'!$K$7:$K$56,MATCH($A13,'Challenge Review'!$A$7:$A$56,0)),""),"") -> Unchecked | H13: =IF(AND(AG13=1,IFERROR(INDEX('Review & Decision'!$B$7:$B$56,MATCH($A13,'Review & Decision'!$A$7:$A$56,0)),"")="Evidence-backed",OR(IFERROR(INDEX('Review & Decision'!$C$7:$C$56,MATCH($A13,'Review & Decision'!$A$7:$A$56,0)),"")="Equivalent or better",AND(IFERROR(INDEX('Review & Decision'!$C$7:$C$56,MATCH($A13,'Review & Decision'!$A$7:$A$56,0)),"")="Accepted reduction",COUNTIFS('Review & Decision'!$A$7:$A$56,$A13,'Review & Decision'!$L$7:$L$56,"<>")=1)),COUNTIFS('Review & Decision'!$A$7:$A$56,$A13,'Review & Decision'!$D$7:$D$56,"<>")=1,COUNTIFS('Review & Decision'!$A$7:$A$56,$A13,'Review & Decision'!$F$7:$F$56,"<>")=1,OR(IFERROR(INDEX('Review & Decision'!$E$7:$E$56,MATCH($A13,'Review & Decision'!$A$7:$A$56,0)),"")="Approved",IFERROR(INDEX('Review & Decision'!$E$7:$E$56,MATCH($A13,'Review & Decision'!$A$7:$A$56,0)),"")="Implemented"),ISNUMBER(IFERROR(INDEX('Review & Decision'!$G$7:$G$56,MATCH($A13,'Review & Decision'!$A$7:$A$56,0)),"")),IFERROR(INDEX('Review & Decision'!$G$7:$G$56,MATCH($A13,'Review & Decision'!$A$7:$A$56,0)),"")>0,IFERROR(INDEX('Review & Decision'!$G$7:$G$56,MATCH($A13,'Review & Decision'!$A$7:$A$56,0)),"")<=Settings!$B$7,ISNUMBER(IFERROR(INDEX('Review & Decision'!$I$7:$I$56,MATCH($A13,'Review & Decision'!$A$7:$A$56,0)),"")),IFERROR(INDEX('Review & Decision'!$I$7:$I$56,MATCH($A13,'Review & Decision'!$A$7:$A$56,0)),"")>0,IFERROR(INDEX('Review & Decision'!$I$7:$I$56,MATCH($A13,'Review & Decision'!$A$7:$A$56,0)),"")<=Settings!$B$7,IFERROR(INDEX('Review & Decision'!$I$7:$I$56,MATCH($A13,'Review & Decision'!$A$7:$A$56,0)),"")>=IFERROR(INDEX('Review & Decision'!$G$7:$G$56,MATCH($A13,'Review & Decision'!$A$7:$A$56,0)),""),COUNTIFS('Review & Decision'!$A$7:$A$56,$A13,'Review & Decision'!$J$7:$J$56,"<>")=1,COUNTIFS('Review & Decision'!$A$7:$A$56,$A13,'Review & Decision'!$K$7:$K$56,"<>")=1,ISNUMBER(IFERROR(INDEX('Review & Decision'!$J$7:$J$56,MATCH($A13,'Review & Decision'!$A$7:$A$56,0)),"")),IFERROR(INDEX('Review & Decision'!$J$7:$J$56,MATCH($A13,'Review & Decision'!$A$7:$A$56,0)),"")>=0,IFERROR(INDEX('Review & Decision'!$J$7:$J$56,MATCH($A13,'Review & Decision'!$A$7:$A$56,0)),"")<=1,ISNUMBER(IFERROR(INDEX('Review & Decision'!$K$7:$K$56,MATCH($A13,'Review & Decision'!$A$7:$A$56,0)),"")),IFERROR(INDEX('Review & Decision'!$K$7:$K$56,MATCH($A13,'Review & Decision'!$A$7:$A$56,0)),"")>=0,IFERROR(INDEX('Review & Decision'!$K$7:$K$56,MATCH($A13,'Review & Decision'!$A$7:$A$56,0)),"")<=1,ISNUMBER(Settings!$B$7),Settings!$B$7>0,OR(Settings!$B$8="Approved + measured",Settings!$B$8="Measured only"),LEN(TRIM(IF(COUNTIFS('Review & Decision'!$A$7:$A$56,$A13,'Review & Decision'!$D$7:$D$56,"<>")=1,IFERROR(INDEX('Review & Decision'!$D$7:$D$56,MATCH($A13,'Review & Decision'!$A$7:$A$56,0)),""),"")))>0,LEN(TRIM(IF(COUNTIFS('Review & Decision'!$A$7:$A$56,$A13,'Review & Decision'!$F$7:$F$56,"<>")=1,IFERROR(INDEX('Review & Decision'!$F$7:$F$56,MATCH($A13,'Review & Decision'!$A$7:$A$56,0)),""),"")))>0,OR(IFERROR(INDEX('Review & Decision'!$C$7:$C$56,MATCH($A13,'Review & Decision'!$A$7:$A$56,0)),"")<>"Accepted reduction",LEN(TRIM(IF(COUNTIFS('Review & Decision'!$A$7:$A$56,$A13,'Review & Decision'!$L$7:$L$56,"<>")=1,IFERROR(INDEX('Review & Decision'!$L$7:$L$56,MATCH($A13,'Review & Decision'!$A$7:$A$56,0)),""),"")))>0)),1,0) -> 0 | I13: =IF(AND(AG13=1,IFERROR(INDEX(Actuals!$M$7:$M$56,MATCH($A13,Actuals!$A$7:$A$56,0)),"")="Ready",IFERROR(INDEX(Actuals!$D$7:$D$56,MATCH($A13,Actuals!$A$7:$A$56,0)),"")>=IFERROR(INDEX('Review & Decision'!$I$7:$I$56,MATCH($A13,'Review & Decision'!$A$7:$A$56,0)),"")),1,0) -> 0 | J13: =IF(AG13=0,"Fix duplicate / missing case ID",IF(B13="Inactive","Unused slot",IF(B13="Example","Example only — never in live planning",IF(D13=0,"Complete case scope and proposal",IF(E13=0,"Complete current inputs; confirm zeros",IF(F13=0,"Complete full proposed profile",IF(G13="Blocked","Blocked — resolve challenge concern",IF(AJ13="Rejected","Rejected — excluded from planning",IF(AND(AI13="Realized",I13=0),"Add measurements, period and evidence",IF(G13<>"Clear","Complete and sign challenge review",IF(H13=0,"Approve evidence, dates and usable shares",IF(AP13="Retain","Retained — no released resource",IF(L13=1,"Measured result eligible",IF(K13=1,"Approved forecast eligible","Modeled only — not allocatable")))))))))))))) -> Example only — never in live planning | K13: =IF(AND(B13="Live",AH13=1,G13="Clear",H13=1,AI13="Validated",AP13<>"Retain"),1,0) -> 0 | L13: =IF(AND(B13="Live",AH13=1,G13="Clear",H13=1,I13=1,AI13="Realized",AJ13="Implemented",AP13<>"Retain"),1,0) -> 0 | M13: =IF(OR(L13=1,AND(K13=1,Settings!$B$8="Approved + measured")),1,0) -> 0 | N13: =IF(E13=1,IFERROR(INDEX(Current!$H$7:$H$56,MATCH($A13,Current!$A$7:$A$56,0)),""),"") -> 3300 | O13: =IF(F13=1,IFERROR(INDEX(Proposed!$I$7:$I$56,MATCH($A13,Proposed!$A$7:$A$56,0)),""),"") -> 800 | P13: =IF(AH13=1,N13-O13,"") -> 2500 | Q13: =IF(E13=1,IFERROR(INDEX(Current!$I$7:$I$56,MATCH($A13,Current!$A$7:$A$56,0)),""),"") -> 100 | R13: =IF(F13=1,IFERROR(INDEX(Proposed!$J$7:$J$56,MATCH($A13,Proposed!$A$7:$A$56,0)),""),"") -> 60 | S13: =IF(AH13=1,Q13-R13,"") -> 40 | T13: =IF(E13=1,IFERROR(INDEX(Current!$E$7:$E$56,MATCH($A13,Current!$A$7:$A$56,0)),""),"") -> 0 | U13: =IF(F13=1,IFERROR(INDEX(Proposed!$E$7:$E$56,MATCH($A13,Proposed!$A$7:$A$56,0)),""),"") -> 12000 | V13: =IF(AH13=1,T13-U13,"") -> -12000 | W13: =IF(E13=1,IFERROR(INDEX(Current!$K$7:$K$56,MATCH($A13,Current!$A$7:$A$56,0)),""),"") -> 205500 | X13: =IF(F13=1,IFERROR(INDEX(Proposed!$L$7:$L$56,MATCH($A13,Proposed!$A$7:$A$56,0)),""),"") -> 64500 | Y13: =IF(AH13=1,W13-X13,"") -> 141000 | Z13: =IF(F13=1,IFERROR(INDEX(Proposed!$F$7:$F$56,MATCH($A13,Proposed!$A$7:$A$56,0)),""),"") -> 15000 | AA13: =IF(M13=1,IF(IF(L13=1,AL13,P13)>0,IF(L13=1,AL13,P13)*IFERROR(INDEX('Review & Decision'!$J$7:$J$56,MATCH($A13,'Review & Decision'!$A$7:$A$56,0)),""),IF(L13=1,AL13,P13)),0) -> 0 | AB13: =IF(M13=1,IF(IF(L13=1,AM13,S13)>0,IF(L13=1,AM13,S13)*IFERROR(INDEX('Review & Decision'!$K$7:$K$56,MATCH($A13,'Review & Decision'!$A$7:$A$56,0)),""),IF(L13=1,AM13,S13)),0) -> 0 | AC13: =IF(M13=1,IF(L13=1,AN13,V13),0) -> 0 | AD13: =IF(AND(M13=1,L13=0),Z13,0) -> 0 | AE13: =IF(AND(B13="Live",AI13="Realized"),1,0) -> 0 | AF13: =IF(AND(AE13=1,I13=0),"Missing measured evidence","No measurement warning") -> No measurement warning | AG13: =IF(AND(COUNTIF(Cases!$A$7:$A$56,$A13)=1,COUNTIF(Current!$A$7:$A$56,$A13)=1,COUNTIF(Proposed!$A$7:$A$56,$A13)=1,COUNTIF('Review & Decision'!$A$7:$A$56,$A13)=1,COUNTIF('Challenge Review'!$A$7:$A$56,$A13)=1,COUNTIF(Actuals!$A$7:$A$56,$A13)=1,COUNTIF(Classification!$A$7:$A$56,$A13)=1),1,0) -> 1 | AH13: =IF(AND(D13=1,E13=1,F13=1),1,0) -> 1 | AI13: =IF(COUNTIFS('Review & Decision'!$A$7:$A$56,$A13,'Review & Decision'!$H$7:$H$56,"<>")=1,IFERROR(INDEX('Review & Decision'!$H$7:$H$56,MATCH($A13,'Review & Decision'!$A$7:$A$56,0)),""),"") -> Modeled | AJ13: =IF(COUNTIFS('Review & Decision'!$A$7:$A$56,$A13,'Review & Decision'!$E$7:$E$56,"<>")=1,IFERROR(INDEX('Review & Decision'!$E$7:$E$56,MATCH($A13,'Review & Decision'!$A$7:$A$56,0)),""),"") -> Open | AK13: =IF(COUNTIFS('Review & Decision'!$A$7:$A$56,$A13,'Review & Decision'!$B$7:$B$56,"<>")=1,IFERROR(INDEX('Review & Decision'!$B$7:$B$56,MATCH($A13,'Review & Decision'!$A$7:$A$56,0)),""),"") -> Hypothesis | AL13: =IF(I13=1,IFERROR(INDEX(Actuals!$E$7:$E$56,MATCH($A13,Actuals!$A$7:$A$56,0)),""),"") | AM13: =IF(I13=1,IFERROR(INDEX(Actuals!$F$7:$F$56,MATCH($A13,Actuals!$A$7:$A$56,0)),""),"") | AN13: =IF(I13=1,IFERROR(INDEX(Actuals!$G$7:$G$56,MATCH($A13,Actuals!$A$7:$A$56,0)),""),"") | AO13: =IF(I13=1,IFERROR(INDEX(Actuals!$G$7:$G$56,MATCH($A13,Actuals!$A$7:$A$56,0)),"")+IFERROR(INDEX(Actuals!$H$7:$H$56,MATCH($A13,Actuals!$A$7:$A$56,0)),""),"") | AP13: =IF(COUNTIFS(Cases!$A$7:$A$56,$A13,Cases!$G$7:$G$56,"<>")=1,IFERROR(INDEX(Cases!$G$7:$G$56,MATCH($A13,Cases!$A$7:$A$56,0)),""),"") -> Simplify
A14: C008 | B14: =IF(COUNTIFS(Cases!$A$7:$A$56,$A14,Cases!$B$7:$B$56,"<>")=1,IFERROR(INDEX(Cases!$B$7:$B$56,MATCH($A14,Cases!$A$7:$A$56,0)),""),"") -> Example | C14: =IF(COUNTIFS(Cases!$A$7:$A$56,$A14,Cases!$C$7:$C$56,"<>")=1,IFERROR(INDEX(Cases!$C$7:$C$56,MATCH($A14,Cases!$A$7:$A$56,0)),""),"") -> Policy and risk assessment workshops | D14: =IF(AND(AG14=1,OR(B14="Example",B14="Live"),OR(AP14="Simplify",AP14="Replace",AP14="Reduce scope",AP14="Retire",AP14="Retain"),COUNTIFS(Cases!$A$7:$A$56,$A14,Cases!$C$7:$C$56,"<>")=1,COUNTIFS(Cases!$A$7:$A$56,$A14,Cases!$D$7:$D$56,"<>")=1,COUNTIFS(Cases!$A$7:$A$56,$A14,Cases!$E$7:$E$56,"<>")=1,COUNTIFS(Cases!$A$7:$A$56,$A14,Cases!$F$7:$F$56,"<>")=1,COUNTIFS(Cases!$A$7:$A$56,$A14,Cases!$H$7:$H$56,"<>")=1,COUNTIFS(Cases!$A$7:$A$56,$A14,Cases!$I$7:$I$56,"<>")=1,LEN(TRIM(IF(COUNTIFS(Cases!$A$7:$A$56,$A14,Cases!$C$7:$C$56,"<>")=1,IFERROR(INDEX(Cases!$C$7:$C$56,MATCH($A14,Cases!$A$7:$A$56,0)),""),"")))>0,LEN(TRIM(IF(COUNTIFS(Cases!$A$7:$A$56,$A14,Cases!$D$7:$D$56,"<>")=1,IFERROR(INDEX(Cases!$D$7:$D$56,MATCH($A14,Cases!$A$7:$A$56,0)),""),"")))>0,LEN(TRIM(IF(COUNTIFS(Cases!$A$7:$A$56,$A14,Cases!$E$7:$E$56,"<>")=1,IFERROR(INDEX(Cases!$E$7:$E$56,MATCH($A14,Cases!$A$7:$A$56,0)),""),"")))>0,LEN(TRIM(IF(COUNTIFS(Cases!$A$7:$A$56,$A14,Cases!$F$7:$F$56,"<>")=1,IFERROR(INDEX(Cases!$F$7:$F$56,MATCH($A14,Cases!$A$7:$A$56,0)),""),"")))>0,LEN(TRIM(IF(COUNTIFS(Cases!$A$7:$A$56,$A14,Cases!$H$7:$H$56,"<>")=1,IFERROR(INDEX(Cases!$H$7:$H$56,MATCH($A14,Cases!$A$7:$A$56,0)),""),"")))>0,LEN(TRIM(IF(COUNTIFS(Cases!$A$7:$A$56,$A14,Cases!$I$7:$I$56,"<>")=1,IFERROR(INDEX(Cases!$I$7:$I$56,MATCH($A14,Cases!$A$7:$A$56,0)),""),"")))>0),1,0) -> 1 | E14: =IF(AND(AG14=1,IFERROR(INDEX(Current!$G$7:$G$56,MATCH($A14,Current!$A$7:$A$56,0)),"")="Ready"),1,0) -> 1 | F14: =IF(AND(AG14=1,IFERROR(INDEX(Proposed!$H$7:$H$56,MATCH($A14,Proposed!$A$7:$A$56,0)),"")="Ready",OR(AP14<>"Retain",AND(IFERROR(INDEX(Current!$B$7:$B$56,MATCH($A14,Current!$A$7:$A$56,0)),"")=IFERROR(INDEX(Proposed!$B$7:$B$56,MATCH($A14,Proposed!$A$7:$A$56,0)),""),IFERROR(INDEX(Current!$C$7:$C$56,MATCH($A14,Current!$A$7:$A$56,0)),"")=IFERROR(INDEX(Proposed!$C$7:$C$56,MATCH($A14,Proposed!$A$7:$A$56,0)),""),IFERROR(INDEX(Current!$D$7:$D$56,MATCH($A14,Current!$A$7:$A$56,0)),"")=IFERROR(INDEX(Proposed!$D$7:$D$56,MATCH($A14,Proposed!$A$7:$A$56,0)),""),IFERROR(INDEX(Current!$E$7:$E$56,MATCH($A14,Current!$A$7:$A$56,0)),"")=IFERROR(INDEX(Proposed!$E$7:$E$56,MATCH($A14,Proposed!$A$7:$A$56,0)),"")))),1,0) -> 1 | G14: =IF(COUNTIFS('Challenge Review'!$A$7:$A$56,$A14,'Challenge Review'!$K$7:$K$56,"<>")=1,IFERROR(INDEX('Challenge Review'!$K$7:$K$56,MATCH($A14,'Challenge Review'!$A$7:$A$56,0)),""),"") -> Unchecked | H14: =IF(AND(AG14=1,IFERROR(INDEX('Review & Decision'!$B$7:$B$56,MATCH($A14,'Review & Decision'!$A$7:$A$56,0)),"")="Evidence-backed",OR(IFERROR(INDEX('Review & Decision'!$C$7:$C$56,MATCH($A14,'Review & Decision'!$A$7:$A$56,0)),"")="Equivalent or better",AND(IFERROR(INDEX('Review & Decision'!$C$7:$C$56,MATCH($A14,'Review & Decision'!$A$7:$A$56,0)),"")="Accepted reduction",COUNTIFS('Review & Decision'!$A$7:$A$56,$A14,'Review & Decision'!$L$7:$L$56,"<>")=1)),COUNTIFS('Review & Decision'!$A$7:$A$56,$A14,'Review & Decision'!$D$7:$D$56,"<>")=1,COUNTIFS('Review & Decision'!$A$7:$A$56,$A14,'Review & Decision'!$F$7:$F$56,"<>")=1,OR(IFERROR(INDEX('Review & Decision'!$E$7:$E$56,MATCH($A14,'Review & Decision'!$A$7:$A$56,0)),"")="Approved",IFERROR(INDEX('Review & Decision'!$E$7:$E$56,MATCH($A14,'Review & Decision'!$A$7:$A$56,0)),"")="Implemented"),ISNUMBER(IFERROR(INDEX('Review & Decision'!$G$7:$G$56,MATCH($A14,'Review & Decision'!$A$7:$A$56,0)),"")),IFERROR(INDEX('Review & Decision'!$G$7:$G$56,MATCH($A14,'Review & Decision'!$A$7:$A$56,0)),"")>0,IFERROR(INDEX('Review & Decision'!$G$7:$G$56,MATCH($A14,'Review & Decision'!$A$7:$A$56,0)),"")<=Settings!$B$7,ISNUMBER(IFERROR(INDEX('Review & Decision'!$I$7:$I$56,MATCH($A14,'Review & Decision'!$A$7:$A$56,0)),"")),IFERROR(INDEX('Review & Decision'!$I$7:$I$56,MATCH($A14,'Review & Decision'!$A$7:$A$56,0)),"")>0,IFERROR(INDEX('Review & Decision'!$I$7:$I$56,MATCH($A14,'Review & Decision'!$A$7:$A$56,0)),"")<=Settings!$B$7,IFERROR(INDEX('Review & Decision'!$I$7:$I$56,MATCH($A14,'Review & Decision'!$A$7:$A$56,0)),"")>=IFERROR(INDEX('Review & Decision'!$G$7:$G$56,MATCH($A14,'Review & Decision'!$A$7:$A$56,0)),""),COUNTIFS('Review & Decision'!$A$7:$A$56,$A14,'Review & Decision'!$J$7:$J$56,"<>")=1,COUNTIFS('Review & Decision'!$A$7:$A$56,$A14,'Review & Decision'!$K$7:$K$56,"<>")=1,ISNUMBER(IFERROR(INDEX('Review & Decision'!$J$7:$J$56,MATCH($A14,'Review & Decision'!$A$7:$A$56,0)),"")),IFERROR(INDEX('Review & Decision'!$J$7:$J$56,MATCH($A14,'Review & Decision'!$A$7:$A$56,0)),"")>=0,IFERROR(INDEX('Review & Decision'!$J$7:$J$56,MATCH($A14,'Review & Decision'!$A$7:$A$56,0)),"")<=1,ISNUMBER(IFERROR(INDEX('Review & Decision'!$K$7:$K$56,MATCH($A14,'Review & Decision'!$A$7:$A$56,0)),"")),IFERROR(INDEX('Review & Decision'!$K$7:$K$56,MATCH($A14,'Review & Decision'!$A$7:$A$56,0)),"")>=0,IFERROR(INDEX('Review & Decision'!$K$7:$K$56,MATCH($A14,'Review & Decision'!$A$7:$A$56,0)),"")<=1,ISNUMBER(Settings!$B$7),Settings!$B$7>0,OR(Settings!$B$8="Approved + measured",Settings!$B$8="Measured only"),LEN(TRIM(IF(COUNTIFS('Review & Decision'!$A$7:$A$56,$A14,'Review & Decision'!$D$7:$D$56,"<>")=1,IFERROR(INDEX('Review & Decision'!$D$7:$D$56,MATCH($A14,'Review & Decision'!$A$7:$A$56,0)),""),"")))>0,LEN(TRIM(IF(COUNTIFS('Review & Decision'!$A$7:$A$56,$A14,'Review & Decision'!$F$7:$F$56,"<>")=1,IFERROR(INDEX('Review & Decision'!$F$7:$F$56,MATCH($A14,'Review & Decision'!$A$7:$A$56,0)),""),"")))>0,OR(IFERROR(INDEX('Review & Decision'!$C$7:$C$56,MATCH($A14,'Review & Decision'!$A$7:$A$56,0)),"")<>"Accepted reduction",LEN(TRIM(IF(COUNTIFS('Review & Decision'!$A$7:$A$56,$A14,'Review & Decision'!$L$7:$L$56,"<>")=1,IFERROR(INDEX('Review & Decision'!$L$7:$L$56,MATCH($A14,'Review & Decision'!$A$7:$A$56,0)),""),"")))>0)),1,0) -> 0 | I14: =IF(AND(AG14=1,IFERROR(INDEX(Actuals!$M$7:$M$56,MATCH($A14,Actuals!$A$7:$A$56,0)),"")="Ready",IFERROR(INDEX(Actuals!$D$7:$D$56,MATCH($A14,Actuals!$A$7:$A$56,0)),"")>=IFERROR(INDEX('Review & Decision'!$I$7:$I$56,MATCH($A14,'Review & Decision'!$A$7:$A$56,0)),"")),1,0) -> 0 | J14: =IF(AG14=0,"Fix duplicate / missing case ID",IF(B14="Inactive","Unused slot",IF(B14="Example","Example only — never in live planning",IF(D14=0,"Complete case scope and proposal",IF(E14=0,"Complete current inputs; confirm zeros",IF(F14=0,"Complete full proposed profile",IF(G14="Blocked","Blocked — resolve challenge concern",IF(AJ14="Rejected","Rejected — excluded from planning",IF(AND(AI14="Realized",I14=0),"Add measurements, period and evidence",IF(G14<>"Clear","Complete and sign challenge review",IF(H14=0,"Approve evidence, dates and usable shares",IF(AP14="Retain","Retained — no released resource",IF(L14=1,"Measured result eligible",IF(K14=1,"Approved forecast eligible","Modeled only — not allocatable")))))))))))))) -> Example only — never in live planning | K14: =IF(AND(B14="Live",AH14=1,G14="Clear",H14=1,AI14="Validated",AP14<>"Retain"),1,0) -> 0 | L14: =IF(AND(B14="Live",AH14=1,G14="Clear",H14=1,I14=1,AI14="Realized",AJ14="Implemented",AP14<>"Retain"),1,0) -> 0 | M14: =IF(OR(L14=1,AND(K14=1,Settings!$B$8="Approved + measured")),1,0) -> 0 | N14: =IF(E14=1,IFERROR(INDEX(Current!$H$7:$H$56,MATCH($A14,Current!$A$7:$A$56,0)),""),"") -> 600 | O14: =IF(F14=1,IFERROR(INDEX(Proposed!$I$7:$I$56,MATCH($A14,Proposed!$A$7:$A$56,0)),""),"") -> 150 | P14: =IF(AH14=1,N14-O14,"") -> 450 | Q14: =IF(E14=1,IFERROR(INDEX(Current!$I$7:$I$56,MATCH($A14,Current!$A$7:$A$56,0)),""),"") -> 120 | R14: =IF(F14=1,IFERROR(INDEX(Proposed!$J$7:$J$56,MATCH($A14,Proposed!$A$7:$A$56,0)),""),"") -> 40 | S14: =IF(AH14=1,Q14-R14,"") -> 80 | T14: =IF(E14=1,IFERROR(INDEX(Current!$E$7:$E$56,MATCH($A14,Current!$A$7:$A$56,0)),""),"") -> 0 | U14: =IF(F14=1,IFERROR(INDEX(Proposed!$E$7:$E$56,MATCH($A14,Proposed!$A$7:$A$56,0)),""),"") -> 0 | V14: =IF(AH14=1,T14-U14,"") -> 0 | W14: =IF(E14=1,IFERROR(INDEX(Current!$K$7:$K$56,MATCH($A14,Current!$A$7:$A$56,0)),""),"") -> 63000 | X14: =IF(F14=1,IFERROR(INDEX(Proposed!$L$7:$L$56,MATCH($A14,Proposed!$A$7:$A$56,0)),""),"") -> 16500 | Y14: =IF(AH14=1,W14-X14,"") -> 46500 | Z14: =IF(F14=1,IFERROR(INDEX(Proposed!$F$7:$F$56,MATCH($A14,Proposed!$A$7:$A$56,0)),""),"") -> 2000 | AA14: =IF(M14=1,IF(IF(L14=1,AL14,P14)>0,IF(L14=1,AL14,P14)*IFERROR(INDEX('Review & Decision'!$J$7:$J$56,MATCH($A14,'Review & Decision'!$A$7:$A$56,0)),""),IF(L14=1,AL14,P14)),0) -> 0 | AB14: =IF(M14=1,IF(IF(L14=1,AM14,S14)>0,IF(L14=1,AM14,S14)*IFERROR(INDEX('Review & Decision'!$K$7:$K$56,MATCH($A14,'Review & Decision'!$A$7:$A$56,0)),""),IF(L14=1,AM14,S14)),0) -> 0 | AC14: =IF(M14=1,IF(L14=1,AN14,V14),0) -> 0 | AD14: =IF(AND(M14=1,L14=0),Z14,0) -> 0 | AE14: =IF(AND(B14="Live",AI14="Realized"),1,0) -> 0 | AF14: =IF(AND(AE14=1,I14=0),"Missing measured evidence","No measurement warning") -> No measurement warning | AG14: =IF(AND(COUNTIF(Cases!$A$7:$A$56,$A14)=1,COUNTIF(Current!$A$7:$A$56,$A14)=1,COUNTIF(Proposed!$A$7:$A$56,$A14)=1,COUNTIF('Review & Decision'!$A$7:$A$56,$A14)=1,COUNTIF('Challenge Review'!$A$7:$A$56,$A14)=1,COUNTIF(Actuals!$A$7:$A$56,$A14)=1,COUNTIF(Classification!$A$7:$A$56,$A14)=1),1,0) -> 1 | AH14: =IF(AND(D14=1,E14=1,F14=1),1,0) -> 1 | AI14: =IF(COUNTIFS('Review & Decision'!$A$7:$A$56,$A14,'Review & Decision'!$H$7:$H$56,"<>")=1,IFERROR(INDEX('Review & Decision'!$H$7:$H$56,MATCH($A14,'Review & Decision'!$A$7:$A$56,0)),""),"") -> Modeled | AJ14: =IF(COUNTIFS('Review & Decision'!$A$7:$A$56,$A14,'Review & Decision'!$E$7:$E$56,"<>")=1,IFERROR(INDEX('Review & Decision'!$E$7:$E$56,MATCH($A14,'Review & Decision'!$A$7:$A$56,0)),""),"") -> Open | AK14: =IF(COUNTIFS('Review & Decision'!$A$7:$A$56,$A14,'Review & Decision'!$B$7:$B$56,"<>")=1,IFERROR(INDEX('Review & Decision'!$B$7:$B$56,MATCH($A14,'Review & Decision'!$A$7:$A$56,0)),""),"") -> Hypothesis | AL14: =IF(I14=1,IFERROR(INDEX(Actuals!$E$7:$E$56,MATCH($A14,Actuals!$A$7:$A$56,0)),""),"") | AM14: =IF(I14=1,IFERROR(INDEX(Actuals!$F$7:$F$56,MATCH($A14,Actuals!$A$7:$A$56,0)),""),"") | AN14: =IF(I14=1,IFERROR(INDEX(Actuals!$G$7:$G$56,MATCH($A14,Actuals!$A$7:$A$56,0)),""),"") | AO14: =IF(I14=1,IFERROR(INDEX(Actuals!$G$7:$G$56,MATCH($A14,Actuals!$A$7:$A$56,0)),"")+IFERROR(INDEX(Actuals!$H$7:$H$56,MATCH($A14,Actuals!$A$7:$A$56,0)),""),"") | AP14: =IF(COUNTIFS(Cases!$A$7:$A$56,$A14,Cases!$G$7:$G$56,"<>")=1,IFERROR(INDEX(Cases!$G$7:$G$56,MATCH($A14,Cases!$A$7:$A$56,0)),""),"") -> Simplify
A15: C009 | B15: =IF(COUNTIFS(Cases!$A$7:$A$56,$A15,Cases!$B$7:$B$56,"<>")=1,IFERROR(INDEX(Cases!$B$7:$B$56,MATCH($A15,Cases!$A$7:$A$56,0)),""),"") -> Example | C15: =IF(COUNTIFS(Cases!$A$7:$A$56,$A15,Cases!$C$7:$C$56,"<>")=1,IFERROR(INDEX(Cases!$C$7:$C$56,MATCH($A15,Cases!$A$7:$A$56,0)),""),"") -> Phishing-resistant authentication | D15: =IF(AND(AG15=1,OR(B15="Example",B15="Live"),OR(AP15="Simplify",AP15="Replace",AP15="Reduce scope",AP15="Retire",AP15="Retain"),COUNTIFS(Cases!$A$7:$A$56,$A15,Cases!$C$7:$C$56,"<>")=1,COUNTIFS(Cases!$A$7:$A$56,$A15,Cases!$D$7:$D$56,"<>")=1,COUNTIFS(Cases!$A$7:$A$56,$A15,Cases!$E$7:$E$56,"<>")=1,COUNTIFS(Cases!$A$7:$A$56,$A15,Cases!$F$7:$F$56,"<>")=1,COUNTIFS(Cases!$A$7:$A$56,$A15,Cases!$H$7:$H$56,"<>")=1,COUNTIFS(Cases!$A$7:$A$56,$A15,Cases!$I$7:$I$56,"<>")=1,LEN(TRIM(IF(COUNTIFS(Cases!$A$7:$A$56,$A15,Cases!$C$7:$C$56,"<>")=1,IFERROR(INDEX(Cases!$C$7:$C$56,MATCH($A15,Cases!$A$7:$A$56,0)),""),"")))>0,LEN(TRIM(IF(COUNTIFS(Cases!$A$7:$A$56,$A15,Cases!$D$7:$D$56,"<>")=1,IFERROR(INDEX(Cases!$D$7:$D$56,MATCH($A15,Cases!$A$7:$A$56,0)),""),"")))>0,LEN(TRIM(IF(COUNTIFS(Cases!$A$7:$A$56,$A15,Cases!$E$7:$E$56,"<>")=1,IFERROR(INDEX(Cases!$E$7:$E$56,MATCH($A15,Cases!$A$7:$A$56,0)),""),"")))>0,LEN(TRIM(IF(COUNTIFS(Cases!$A$7:$A$56,$A15,Cases!$F$7:$F$56,"<>")=1,IFERROR(INDEX(Cases!$F$7:$F$56,MATCH($A15,Cases!$A$7:$A$56,0)),""),"")))>0,LEN(TRIM(IF(COUNTIFS(Cases!$A$7:$A$56,$A15,Cases!$H$7:$H$56,"<>")=1,IFERROR(INDEX(Cases!$H$7:$H$56,MATCH($A15,Cases!$A$7:$A$56,0)),""),"")))>0,LEN(TRIM(IF(COUNTIFS(Cases!$A$7:$A$56,$A15,Cases!$I$7:$I$56,"<>")=1,IFERROR(INDEX(Cases!$I$7:$I$56,MATCH($A15,Cases!$A$7:$A$56,0)),""),"")))>0),1,0) -> 1 | E15: =IF(AND(AG15=1,IFERROR(INDEX(Current!$G$7:$G$56,MATCH($A15,Current!$A$7:$A$56,0)),"")="Ready"),1,0) -> 1 | F15: =IF(AND(AG15=1,IFERROR(INDEX(Proposed!$H$7:$H$56,MATCH($A15,Proposed!$A$7:$A$56,0)),"")="Ready",OR(AP15<>"Retain",AND(IFERROR(INDEX(Current!$B$7:$B$56,MATCH($A15,Current!$A$7:$A$56,0)),"")=IFERROR(INDEX(Proposed!$B$7:$B$56,MATCH($A15,Proposed!$A$7:$A$56,0)),""),IFERROR(INDEX(Current!$C$7:$C$56,MATCH($A15,Current!$A$7:$A$56,0)),"")=IFERROR(INDEX(Proposed!$C$7:$C$56,MATCH($A15,Proposed!$A$7:$A$56,0)),""),IFERROR(INDEX(Current!$D$7:$D$56,MATCH($A15,Current!$A$7:$A$56,0)),"")=IFERROR(INDEX(Proposed!$D$7:$D$56,MATCH($A15,Proposed!$A$7:$A$56,0)),""),IFERROR(INDEX(Current!$E$7:$E$56,MATCH($A15,Current!$A$7:$A$56,0)),"")=IFERROR(INDEX(Proposed!$E$7:$E$56,MATCH($A15,Proposed!$A$7:$A$56,0)),"")))),1,0) -> 1 | G15: =IF(COUNTIFS('Challenge Review'!$A$7:$A$56,$A15,'Challenge Review'!$K$7:$K$56,"<>")=1,IFERROR(INDEX('Challenge Review'!$K$7:$K$56,MATCH($A15,'Challenge Review'!$A$7:$A$56,0)),""),"") -> Unchecked | H15: =IF(AND(AG15=1,IFERROR(INDEX('Review & Decision'!$B$7:$B$56,MATCH($A15,'Review & Decision'!$A$7:$A$56,0)),"")="Evidence-backed",OR(IFERROR(INDEX('Review & Decision'!$C$7:$C$56,MATCH($A15,'Review & Decision'!$A$7:$A$56,0)),"")="Equivalent or better",AND(IFERROR(INDEX('Review & Decision'!$C$7:$C$56,MATCH($A15,'Review & Decision'!$A$7:$A$56,0)),"")="Accepted reduction",COUNTIFS('Review & Decision'!$A$7:$A$56,$A15,'Review & Decision'!$L$7:$L$56,"<>")=1)),COUNTIFS('Review & Decision'!$A$7:$A$56,$A15,'Review & Decision'!$D$7:$D$56,"<>")=1,COUNTIFS('Review & Decision'!$A$7:$A$56,$A15,'Review & Decision'!$F$7:$F$56,"<>")=1,OR(IFERROR(INDEX('Review & Decision'!$E$7:$E$56,MATCH($A15,'Review & Decision'!$A$7:$A$56,0)),"")="Approved",IFERROR(INDEX('Review & Decision'!$E$7:$E$56,MATCH($A15,'Review & Decision'!$A$7:$A$56,0)),"")="Implemented"),ISNUMBER(IFERROR(INDEX('Review & Decision'!$G$7:$G$56,MATCH($A15,'Review & Decision'!$A$7:$A$56,0)),"")),IFERROR(INDEX('Review & Decision'!$G$7:$G$56,MATCH($A15,'Review & Decision'!$A$7:$A$56,0)),"")>0,IFERROR(INDEX('Review & Decision'!$G$7:$G$56,MATCH($A15,'Review & Decision'!$A$7:$A$56,0)),"")<=Settings!$B$7,ISNUMBER(IFERROR(INDEX('Review & Decision'!$I$7:$I$56,MATCH($A15,'Review & Decision'!$A$7:$A$56,0)),"")),IFERROR(INDEX('Review & Decision'!$I$7:$I$56,MATCH($A15,'Review & Decision'!$A$7:$A$56,0)),"")>0,IFERROR(INDEX('Review & Decision'!$I$7:$I$56,MATCH($A15,'Review & Decision'!$A$7:$A$56,0)),"")<=Settings!$B$7,IFERROR(INDEX('Review & Decision'!$I$7:$I$56,MATCH($A15,'Review & Decision'!$A$7:$A$56,0)),"")>=IFERROR(INDEX('Review & Decision'!$G$7:$G$56,MATCH($A15,'Review & Decision'!$A$7:$A$56,0)),""),COUNTIFS('Review & Decision'!$A$7:$A$56,$A15,'Review & Decision'!$J$7:$J$56,"<>")=1,COUNTIFS('Review & Decision'!$A$7:$A$56,$A15,'Review & Decision'!$K$7:$K$56,"<>")=1,ISNUMBER(IFERROR(INDEX('Review & Decision'!$J$7:$J$56,MATCH($A15,'Review & Decision'!$A$7:$A$56,0)),"")),IFERROR(INDEX('Review & Decision'!$J$7:$J$56,MATCH($A15,'Review & Decision'!$A$7:$A$56,0)),"")>=0,IFERROR(INDEX('Review & Decision'!$J$7:$J$56,MATCH($A15,'Review & Decision'!$A$7:$A$56,0)),"")<=1,ISNUMBER(IFERROR(INDEX('Review & Decision'!$K$7:$K$56,MATCH($A15,'Review & Decision'!$A$7:$A$56,0)),"")),IFERROR(INDEX('Review & Decision'!$K$7:$K$56,MATCH($A15,'Review & Decision'!$A$7:$A$56,0)),"")>=0,IFERROR(INDEX('Review & Decision'!$K$7:$K$56,MATCH($A15,'Review & Decision'!$A$7:$A$56,0)),"")<=1,ISNUMBER(Settings!$B$7),Settings!$B$7>0,OR(Settings!$B$8="Approved + measured",Settings!$B$8="Measured only"),LEN(TRIM(IF(COUNTIFS('Review & Decision'!$A$7:$A$56,$A15,'Review & Decision'!$D$7:$D$56,"<>")=1,IFERROR(INDEX('Review & Decision'!$D$7:$D$56,MATCH($A15,'Review & Decision'!$A$7:$A$56,0)),""),"")))>0,LEN(TRIM(IF(COUNTIFS('Review & Decision'!$A$7:$A$56,$A15,'Review & Decision'!$F$7:$F$56,"<>")=1,IFERROR(INDEX('Review & Decision'!$F$7:$F$56,MATCH($A15,'Review & Decision'!$A$7:$A$56,0)),""),"")))>0,OR(IFERROR(INDEX('Review & Decision'!$C$7:$C$56,MATCH($A15,'Review & Decision'!$A$7:$A$56,0)),"")<>"Accepted reduction",LEN(TRIM(IF(COUNTIFS('Review & Decision'!$A$7:$A$56,$A15,'Review & Decision'!$L$7:$L$56,"<>")=1,IFERROR(INDEX('Review & Decision'!$L$7:$L$56,MATCH($A15,'Review & Decision'!$A$7:$A$56,0)),""),"")))>0)),1,0) -> 0 | I15: =IF(AND(AG15=1,IFERROR(INDEX(Actuals!$M$7:$M$56,MATCH($A15,Actuals!$A$7:$A$56,0)),"")="Ready",IFERROR(INDEX(Actuals!$D$7:$D$56,MATCH($A15,Actuals!$A$7:$A$56,0)),"")>=IFERROR(INDEX('Review & Decision'!$I$7:$I$56,MATCH($A15,'Review & Decision'!$A$7:$A$56,0)),"")),1,0) -> 0 | J15: =IF(AG15=0,"Fix duplicate / missing case ID",IF(B15="Inactive","Unused slot",IF(B15="Example","Example only — never in live planning",IF(D15=0,"Complete case scope and proposal",IF(E15=0,"Complete current inputs; confirm zeros",IF(F15=0,"Complete full proposed profile",IF(G15="Blocked","Blocked — resolve challenge concern",IF(AJ15="Rejected","Rejected — excluded from planning",IF(AND(AI15="Realized",I15=0),"Add measurements, period and evidence",IF(G15<>"Clear","Complete and sign challenge review",IF(H15=0,"Approve evidence, dates and usable shares",IF(AP15="Retain","Retained — no released resource",IF(L15=1,"Measured result eligible",IF(K15=1,"Approved forecast eligible","Modeled only — not allocatable")))))))))))))) -> Example only — never in live planning | K15: =IF(AND(B15="Live",AH15=1,G15="Clear",H15=1,AI15="Validated",AP15<>"Retain"),1,0) -> 0 | L15: =IF(AND(B15="Live",AH15=1,G15="Clear",H15=1,I15=1,AI15="Realized",AJ15="Implemented",AP15<>"Retain"),1,0) -> 0 | M15: =IF(OR(L15=1,AND(K15=1,Settings!$B$8="Approved + measured")),1,0) -> 0 | N15: =IF(E15=1,IFERROR(INDEX(Current!$H$7:$H$56,MATCH($A15,Current!$A$7:$A$56,0)),""),"") -> 1100 | O15: =IF(F15=1,IFERROR(INDEX(Proposed!$I$7:$I$56,MATCH($A15,Proposed!$A$7:$A$56,0)),""),"") -> 1100 | P15: =IF(AH15=1,N15-O15,"") -> 0 | Q15: =IF(E15=1,IFERROR(INDEX(Current!$I$7:$I$56,MATCH($A15,Current!$A$7:$A$56,0)),""),"") -> 80 | R15: =IF(F15=1,IFERROR(INDEX(Proposed!$J$7:$J$56,MATCH($A15,Proposed!$A$7:$A$56,0)),""),"") -> 80 | S15: =IF(AH15=1,Q15-R15,"") -> 0 | T15: =IF(E15=1,IFERROR(INDEX(Current!$E$7:$E$56,MATCH($A15,Current!$A$7:$A$56,0)),""),"") -> 4000 | U15: =IF(F15=1,IFERROR(INDEX(Proposed!$E$7:$E$56,MATCH($A15,Proposed!$A$7:$A$56,0)),""),"") -> 4000 | V15: =IF(AH15=1,T15-U15,"") -> 0 | W15: =IF(E15=1,IFERROR(INDEX(Current!$K$7:$K$56,MATCH($A15,Current!$A$7:$A$56,0)),""),"") -> 76000 | X15: =IF(F15=1,IFERROR(INDEX(Proposed!$L$7:$L$56,MATCH($A15,Proposed!$A$7:$A$56,0)),""),"") -> 76000 | Y15: =IF(AH15=1,W15-X15,"") -> 0 | Z15: =IF(F15=1,IFERROR(INDEX(Proposed!$F$7:$F$56,MATCH($A15,Proposed!$A$7:$A$56,0)),""),"") -> 0 | AA15: =IF(M15=1,IF(IF(L15=1,AL15,P15)>0,IF(L15=1,AL15,P15)*IFERROR(INDEX('Review & Decision'!$J$7:$J$56,MATCH($A15,'Review & Decision'!$A$7:$A$56,0)),""),IF(L15=1,AL15,P15)),0) -> 0 | AB15: =IF(M15=1,IF(IF(L15=1,AM15,S15)>0,IF(L15=1,AM15,S15)*IFERROR(INDEX('Review & Decision'!$K$7:$K$56,MATCH($A15,'Review & Decision'!$A$7:$A$56,0)),""),IF(L15=1,AM15,S15)),0) -> 0 | AC15: =IF(M15=1,IF(L15=1,AN15,V15),0) -> 0 | AD15: =IF(AND(M15=1,L15=0),Z15,0) -> 0 | AE15: =IF(AND(B15="Live",AI15="Realized"),1,0) -> 0 | AF15: =IF(AND(AE15=1,I15=0),"Missing measured evidence","No measurement warning") -> No measurement warning | AG15: =IF(AND(COUNTIF(Cases!$A$7:$A$56,$A15)=1,COUNTIF(Current!$A$7:$A$56,$A15)=1,COUNTIF(Proposed!$A$7:$A$56,$A15)=1,COUNTIF('Review & Decision'!$A$7:$A$56,$A15)=1,COUNTIF('Challenge Review'!$A$7:$A$56,$A15)=1,COUNTIF(Actuals!$A$7:$A$56,$A15)=1,COUNTIF(Classification!$A$7:$A$56,$A15)=1),1,0) -> 1 | AH15: =IF(AND(D15=1,E15=1,F15=1),1,0) -> 1 | AI15: =IF(COUNTIFS('Review & Decision'!$A$7:$A$56,$A15,'Review & Decision'!$H$7:$H$56,"<>")=1,IFERROR(INDEX('Review & Decision'!$H$7:$H$56,MATCH($A15,'Review & Decision'!$A$7:$A$56,0)),""),"") -> Modeled | AJ15: =IF(COUNTIFS('Review & Decision'!$A$7:$A$56,$A15,'Review & Decision'!$E$7:$E$56,"<>")=1,IFERROR(INDEX('Review & Decision'!$E$7:$E$56,MATCH($A15,'Review & Decision'!$A$7:$A$56,0)),""),"") -> Open | AK15: =IF(COUNTIFS('Review & Decision'!$A$7:$A$56,$A15,'Review & Decision'!$B$7:$B$56,"<>")=1,IFERROR(INDEX('Review & Decision'!$B$7:$B$56,MATCH($A15,'Review & Decision'!$A$7:$A$56,0)),""),"") -> Hypothesis | AL15: =IF(I15=1,IFERROR(INDEX(Actuals!$E$7:$E$56,MATCH($A15,Actuals!$A$7:$A$56,0)),""),"") | AM15: =IF(I15=1,IFERROR(INDEX(Actuals!$F$7:$F$56,MATCH($A15,Actuals!$A$7:$A$56,0)),""),"") | AN15: =IF(I15=1,IFERROR(INDEX(Actuals!$G$7:$G$56,MATCH($A15,Actuals!$A$7:$A$56,0)),""),"") | AO15: =IF(I15=1,IFERROR(INDEX(Actuals!$G$7:$G$56,MATCH($A15,Actuals!$A$7:$A$56,0)),"")+IFERROR(INDEX(Actuals!$H$7:$H$56,MATCH($A15,Actuals!$A$7:$A$56,0)),""),"") | AP15: =IF(COUNTIFS(Cases!$A$7:$A$56,$A15,Cases!$G$7:$G$56,"<>")=1,IFERROR(INDEX(Cases!$G$7:$G$56,MATCH($A15,Cases!$A$7:$A$56,0)),""),"") -> Retain
